Workbook
Name Slicer_Yrmo: #N/A

Sheet Lookup
A1: For drop down: | G1: Exp - House Maint | H1: House Maintenance | K1: For Personal Capital / Empower
A2: Exp - Rent | B2: Rent | G2: Exp - Utilities | H2: Utilities | K2: Credit Card Payments | L2: Delete
A3: Exp - House Maint | B3: House Maintenance | G3: Exp - Car Loan | H3: Car Loan | K3: Deposits | L3: Delete
A4: Exp - Utilities | B4: Utilities | G4: Exp - Cleaning | H4: Cleaning | K4: Investment Income | L4: Inc - Other
A5: Exp - Car Loan | B5: Car Loan | G5: Exp - Insurance | H5: Insurance | K5: Delete | L5: Delete
A6: Exp - Cleaning | B6: Cleaning | G6: Exp - Day Care | H6: Day Care | K6: Shopping | L6: Shopping
A7: Exp - Insurance | B7: Insurance | G7: Exp - Transportation | H7: Transportation | K7: Paychecks/Salary | L7: Inc - Other
A8: Exp - Day Care | B8: Day Care | G8: Exp - Restaurants | H8: Restaurants | K8: Credit Card Payments | L8: Delete
A9: Exp - Transportation | B9: Transportation | G9: Exp - Groceries | H9: Groceries | K9: Misc | L9: Misc
A10: Exp - Restaurants | B10: Restaurants | G10: Exp - Target | H10: Target | K10: Transfers | L10: Delete
A11: Exp - Groceries | B11: Groceries | G11: Exp - Gym | H11: Gym | K11: Delete - Other Expenses | L11: Delete
A12: Exp - Target | B12: Target | G12: Exp - Shopping | H12: Shopping | K12: Groceries | L12: Groceries
A13: Exp - Gym | B13: Gym | G13: Exp - Amazon | H13: Amazon | K13: Restaurants | L13: Restaurants
... A29: Inc - Other | B29: Inc - Other | G29: Delete | H29: Delete | K29: Car Loan | L29: Car Loan
A30: Inc - Dividend | B30: Dividend | G30: For suggested category: | K30: Healthcare | L30: Healthcare
A31: Delete | B31: Delete | G31: Description | H31: Category
G32: TYPE TRANSFER ID PAYPALSD11 CO PAYPAL ACH ECC PPD ACH Trace 22822 282464808 | H32: Shopping
G33: TYPE TRANSFER ID PAYPALSD11 CO PAYPAL ACH ECC PPD ACH Trace 23715 321924713 | H33: Shopping
G34: TYPE TRANSFER ID PAYPALSD11 CO PAYPAL ACH ECC PPD ACH Trace 96587 311867131 | H34: Shopping
G35: 06 455 Pond Promenade Chanhassen MN | H35: Delete
G36: 11003 NORTH LOOP MINNEAPOLIS MN | H36: Shopping
G37: 11003 NORTH LOOP MINNEAPOLIS MN 248335279 | H37: Shopping
G38: 11003 NORTH LOOP MINNEAPOLIS MN 290461321 | H38: Shopping
G39: 2020 OUTRUN ALD VIRTUA HTTPSRACEROSTMA 313537608 | H39: Gifts
G40: 3 DAY BLINDS LLC 8008003329 CA 283004524 | H40: House Maintenance
G41: 3 DAY BLINDS LLC 8008003329 CA 285992548 | H41: House Maintenance
G42: 47 Cardtronics C2 1301 MAIN ST ALAMOSA CO 326479211 | H42: Shopping
G43: 49 WINCO FOODS 160 2913 Max Aven | H43: Groceries
... G516: Chateau St. Jean | H516: Travel
G517: CHECK 2152
G518: CHECK 2342 | H518: Travel
G519: CHECK 2343 | H519: Shopping
G520: CHECK Processed Check PASSPORT | H520: Travel
G521: CHECK 2089 2089 | H521: Delete
G522: CHECK 2097 2097 | H522: Entertainment
G523: CHECK 2098 2098 | H523: Travel
G524: CHECK 2098 2098 | H524: 0
G525: CHECK 2100 2100 | H525: Delete
G526: CHECK 2103 2103 | H526: Entertainment
G527: CHECK 2103 2103 | H527: 0
G528: CHECK 2105 2105 | H528: House
G529: CHECK 2106 2106 | H529: House
G530: CHECK 2107 2107 | H530: House
G531: CHECK 2108 2108 | H531: House
G532: CHECK 2179 2179 | H532: House Maintenance
G533: CHECK 2180 2180 | H533: 0
G534: CHECK 2182 2182 | H534: Travel
G535: CHECK 2183 2183 | H535: House Maintenance
G536: CHECK 2184 2184 | H536: House Maintenance
G537: CHECK 2186 2186 | H537: Delete
G538: CHECK 2201 2201 | H538: Delete
G539: CHECK 2341 2341 | H539: Delete
G540: Check Paid #1139 | H540: Shopping
G541: Check Paid #1181 | H541: House
G542: Chevron | H542: Transportation
G543: CHEVRON CORP | H543: Dividend
G544: CHEVRON CORP | H544: Delete
G545: Chick-Fil-A | H545: Restaurants
... G2453: ZORBAZ ON GULL LAKE NISSWA MN | H2453: Restaurants
H2454: 401K

Sheet Trips
A1: Trip | B1: Start | C1: End
A2: Boston | B2: 45664 | C2: 45666
A3: Ireland | B3: 45677 | C3: 45682
A4: Ireland | B4: 45732 | C4: 45737
A5: Irealnd | B5: 45788 | C5: 45793
A6: Miami | B6: 45804 | C6: 45807
A7: Irealnd | B7: 45872 | C7: 45877
A8: Irealnd | B8: 45950 | C8: 45954

Sheet Actuals
A1: Yrmo | B1: Date | C1: Source | D1: Description | E1: Amount | F1: Category | G1: Suggested Cat Value | H1: Manual Cat Value | I1: Notes | J1: Amount2 | K1: ActiveRule | L1: Desc | M1: LongDesc | N1: InflowOutflow | O1: Short Desc | P1: RuleUsed | Q1: Tag
A2: 201907 | B2: 43648 | C2: Discover | D2: Amazon | E2: 3.97 | F2: Amazon | J2: 3.97 | K2: FALSE | N2: - | O2: =LEFT(Table2[[#This Row],[Description]],75) -> Amazon | P2: Create Rule; and Description='Amazon';Amazon
A3: 201907 | B3: 43648 | C3: Discover More Card | D3: Amazon | E3: 3.97 | F3: Amazon | J3: 3.97 | K3: FALSE | N3: - | O3: =LEFT(Table2[[#This Row],[Description]],75) -> Amazon
A4: 201907 | B4: 43648 | C4: Cash Rewards Visa Signature | D4: Borough | E4: 58.95 | F4: Restaurants | J4: 58.95 | K4: FALSE | N4: - | O4: =LEFT(Table2[[#This Row],[Description]],75) -> Borough | P4: Create Rule; and Description='Borough';Restaurants
A5: 201907 | B5: 43648 | C5: Cash Rewards Visa Signature | D5: Speedway | E5: 28.61 | F5: Transportation | J5: 28.61 | K5: FALSE | N5: - | O5: =LEFT(Table2[[#This Row],[Description]],75) -> Speedway
A6: 201907 | B6: 43648 | C6: Cash Rewards Visa Signature | D6: Transfer from POWERPLUS CHECKING | E6: -606.63 | F6: Delete | J6: 606.63 | K6: FALSE | N6: .+ | O6: =LEFT(Table2[[#This Row],[Description]],75) -> Transfer from POWERPLUS CHECKING
A7: 201907 | B7: 43648 | C7: POWERPLUS | D7: Transfer to Cash Rewards Visa Signature | E7: 606.63 | F7: Delete | J7: 606.63 | K7: FALSE | N7: - | O7: =LEFT(Table2[[#This Row],[Description]],75) -> Transfer to Cash Rewards Visa Signature | P7: Delete; and Description Like '%Transfer to Cash Rewards Visa Signature%';0
A8: 201907 | B8: 43648 | C8: POWERPLUS CHECKING | D8: Transfer to Cash Rewards Visa Signature | E8: 606.63 | F8: Delete | J8: 606.63 | K8: FALSE | N8: - | O8: =LEFT(Table2[[#This Row],[Description]],75) -> Transfer to Cash Rewards Visa Signature
A9: 201907 | B9: 43649 | C9: Discover | D9: Amazon | E9: 115.84 | F9: Amazon | J9: 115.84 | K9: FALSE | N9: - | O9: =LEFT(Table2[[#This Row],[Description]],75) -> Amazon | P9: Create Rule; and Description='Amazon';Amazon
A10: 201907 | B10: 43649 | C10: Discover More Card | D10: Amazon | E10: 115.84 | F10: Amazon | J10: 115.84 | K10: FALSE | N10: - | O10: =LEFT(Table2[[#This Row],[Description]],75) -> Amazon
A11: 201907 | B11: 43649 | C11: POWERPLUS | D11: CCLC TYPE INTERNET ID CO CCLC ACH ECC WEB ACH Trace 49616 233344358 | E11: 247.5 | F11: Day Care | J11: 247.5 | K11: FALSE | N11: - | O11: =LEFT(Table2[[#This Row],[Description]],75) -> CCLC TYPE INTERNET ID CO CCLC ACH ECC WEB ACH Trace 49616 233344358 | P11: Create Rule; and Description Like '%CCLC TYPE INTERNET ID%';Day Care
A12: 201907 | B12: 43649 | C12: POWERPLUS CHECKING | D12: CCLC TYPE INTERNET ID CO CCLC ACH ECC WEB ACH Trace 49616 233344358 | E12: 247.5 | F12: Day Care | J12: 247.5 | K12: FALSE | N12: - | O12: =LEFT(Table2[[#This Row],[Description]],75) -> CCLC TYPE INTERNET ID CO CCLC ACH ECC WEB ACH Trace 49616 233344358
A13: 201907 | B13: 43649 | C13: Cash Rewards Visa Signature | D13: Cub Foods | E13: 125.59 | F13: Groceries | J13: 125.59 | K13: FALSE | N13: - | O13: =LEFT(Table2[[#This Row],[Description]],75) -> Cub Foods
A14: 201907 | B14: 43649 | C14: Cash Rewards Visa Signature | D14: Transfer from POWERPLUS CHECKING | E14: -694.19 | F14: Delete | J14: 694.19 | K14: FALSE | N14: .+ | O14: =LEFT(Table2[[#This Row],[Description]],75) -> Transfer from POWERPLUS CHECKING
A15: 201907 | B15: 43649 | C15: POWERPLUS | D15: Transfer to Cash Rewards Visa Signature | E15: 694.19 | F15: Delete | J15: 694.19 | K15: FALSE | N15: - | O15: =LEFT(Table2[[#This Row],[Description]],75) -> Transfer to Cash Rewards Visa Signature | P15: Delete; and Description Like '%Transfer to Cash Rewards Visa Signature%';0
A16: 201907 | B16: 43649 | C16: POWERPLUS CHECKING | D16: Transfer to Cash Rewards Visa Signature | E16: 694.19 | F16: Delete | J16: 694.19 | K16: FALSE | N16: - | O16: =LEFT(Table2[[#This Row],[Description]],75) -> Transfer to Cash Rewards Visa Signature
A17: 201907 | B17: 43650 | C17: POWERPLUS | D17: Withdrawal Home To Loan Mortgage Payment Thank You 233602111 | E17: 2770.79 | F17: Rent | J17: 2770.79 | K17: FALSE | N17: - | O17: =LEFT(Table2[[#This Row],[Description]],75) -> Withdrawal Home To Loan Mortgage Payment Thank You 233602111 | P17: Create Rule; and Description Like '%Withdrawal Home To Loan Mortgage Payment%';Rent
A18: 201907 | B18: 43650 | C18: POWERPLUS CHECKING | D18: Withdrawal Home To Loan Mortgage Payment Thank You 233602111 | E18: 2770.79 | F18: Rent | J18: 2770.79 | K18: FALSE | N18: - | O18: =LEFT(Table2[[#This Row],[Description]],75) -> Withdrawal Home To Loan Mortgage Payment Thank You 233602111
A19: 201907 | B19: 43650 | C19: Cash Rewards Visa Signature | D19: Cub Foods | E19: 136.89 | F19: Groceries | J19: 136.89 | K19: FALSE | N19: - | O19: =LEFT(Table2[[#This Row],[Description]],75) -> Cub Foods
A20: 201907 | B20: 43650 | C20: Cash Rewards Visa Signature | D20: Dollar Tree | E20: 5.38 | F20: 0 | J20: 5.38 | K20: FALSE | N20: - | O20: =LEFT(Table2[[#This Row],[Description]],75) -> Dollar Tree
A21: 201907 | B21: 43650 | C21: Discover | D21: MIYABI EXCELSIOR MN | E21: 100.23 | F21: 0 | J21: 100.23 | K21: FALSE | N21: - | O21: =LEFT(Table2[[#This Row],[Description]],75) -> MIYABI EXCELSIOR MN
A22: 201907 | B22: 43650 | C22: Discover More Card | D22: MIYABI EXCELSIOR MN | E22: 100.23 | F22: 0 | J22: 100.23 | K22: FALSE | N22: - | O22: =LEFT(Table2[[#This Row],[Description]],75) -> MIYABI EXCELSIOR MN
A23: 201907 | B23: 43650 | C23: Cash Rewards Visa Signature | D23: SHOREWOOD LIQUOR EXCELSIOR MN 233755679 | E23: 9.87 | F23: 0 | J23: 9.87 | K23: FALSE | N23: - | O23: =LEFT(Table2[[#This Row],[Description]],75) -> SHOREWOOD LIQUOR EXCELSIOR MN 233755679
A24: 201907 | B24: 43650 | C24: Cash Rewards Visa Signature | D24: SHOREWOOD LIQUOR EXCELSIOR MN 233755680 | E24: 14.26 | F24: 0 | J24: 14.26 | K24: FALSE | N24: - | O24: =LEFT(Table2[[#This Row],[Description]],75) -> SHOREWOOD LIQUOR EXCELSIOR MN 233755680
A25: 201907 | B25: 43650 | C25: Cash Rewards Visa Signature | D25: SHOREWOOD TRUE VALUE EXCELSIOR MN 233755684 | E25: 33.29 | F25: 0 | J25: 33.29 | K25: FALSE | N25: - | O25: =LEFT(Table2[[#This Row],[Description]],75) -> SHOREWOOD TRUE VALUE EXCELSIOR MN 233755684
A26: 201907 | B26: 43650 | C26: Cash Rewards Visa Signature | D26: SOTA CLOTHING SPENCEDESIGNSMN 233755683 | E26: 114.71 | F26: Shopping | J26: 114.71 | K26: FALSE | N26: - | O26: =LEFT(Table2[[#This Row],[Description]],75) -> SOTA CLOTHING SPENCEDESIGNSMN 233755683
A27: 201907 | B27: 43651 | C27: 30 YR FIXED | D27: PAYMENT 234306694 | E27: -533.82 | F27: 0 | J27: 533.82 | K27: FALSE | N27: .+ | O27: =LEFT(Table2[[#This Row],[Description]],75) -> PAYMENT 234306694
A28: 201907 | B28: 43651 | C28: Target Credit Card | D28: CENTRAL CHECKOUT 79999999187086207507850 | E28: 130.45 | F28: Shopping | J28: 130.45 | K28: FALSE | N28: - | O28: =LEFT(Table2[[#This Row],[Description]],75) -> CENTRAL CHECKOUT 79999999187086207507850
A29: 201907 | B29: 43651 | C29: POWERPLUS | D29: College Savings TYPE ACH ID 550895818 CO College Savings ACH ECC PPD ACH Trace 48247 233797400 | E29: 100 | F29: College Savings | J29: 100 | K29: FALSE | N29: - | O29: =LEFT(Table2[[#This Row],[Description]],75) -> College Savings TYPE ACH ID 550895818 CO College Savings ACH ECC PPD ACH Tr | P29: Create Rule; and Description Like '%College Savings%';College Savings
A30: 201907 | B30: 43651 | C30: POWERPLUS CHECKING | D30: College Savings TYPE ACH ID 550895818 CO College Savings ACH ECC PPD ACH Trace 48247 233797400 | E30: 100 | F30: College Savings | J30: 100 | K30: FALSE | N30: - | O30: =LEFT(Table2[[#This Row],[Description]],75) -> College Savings TYPE ACH ID 550895818 CO College Savings ACH ECC PPD ACH Tr
A31: 201907 | B31: 43651 | C31: POWERPLUS | D31: Deposit by Check Deposit Anywhere check deposit 233928086 | E31: -32.85 | F31: 0 | J31: 32.85 | K31: FALSE | N31: + | O31: =LEFT(Table2[[#This Row],[Description]],75) -> Deposit by Check Deposit Anywhere check deposit 233928086
A32: 201907 | B32: 43651 | C32: POWERPLUS CHECKING | D32: Deposit by Check Deposit Anywhere check deposit 233928086 | E32: -32.85 | F32: 0 | J32: 32.85 | K32: FALSE | N32: .+ | O32: =LEFT(Table2[[#This Row],[Description]],75) -> Deposit by Check Deposit Anywhere check deposit 233928086
A33: 201907 | B33: 43651 | C33: Investor Checking | D33: INST XFER 190704 | E33: 12.99 | F33: 0 | J33: 12.99 | K33: FALSE | N33: - | O33: =LEFT(Table2[[#This Row],[Description]],75) -> INST XFER 190704
A34: 201907 | B34: 43651 | C34: Jeff Roth | D34: SCHWAB S&P 500 INDEX FD | E34: 150 | F34: Delete | J34: 150 | K34: FALSE | N34: - | O34: =LEFT(Table2[[#This Row],[Description]],75) -> SCHWAB S&P 500 INDEX FD | P34: Delete; and Description='SCHWAB S&P 500 INDEX FD' and inflowoutflow='-';0
A35: 201907 | B35: 43651 | C35: Roth Contributory IRA | D35: SCHWAB S&P 500 INDEX FD | E35: 150 | F35: Delete | J35: 150 | K35: FALSE | N35: - | O35: =LEFT(Table2[[#This Row],[Description]],75) -> SCHWAB S&P 500 INDEX FD | P35: Delete; and Description='SCHWAB S&P 500 INDEX FD' and inflowoutflow='-';0
A36: 201907 | B36: 43651 | C36: Jeff Roth | D36: SCHWAB TOTAL STOCK MKT INDEX | E36: 150 | F36: Delete | J36: 150 | K36: FALSE | N36: - | O36: =LEFT(Table2[[#This Row],[Description]],75) -> SCHWAB TOTAL STOCK MKT INDEX | P36: Delete; and Description='SCHWAB TOTAL STOCK MKT INDEX' and inflowoutflow='-';0
A37: 201907 | B37: 43651 | C37: Roth Contributory IRA | D37: SCHWAB TOTAL STOCK MKT INDEX | E37: 150 | F37: Delete | J37: 150 | K37: FALSE | N37: - | O37: =LEFT(Table2[[#This Row],[Description]],75) -> SCHWAB TOTAL STOCK MKT INDEX
A38: 201907 | B38: 43653 | C38: Cash Rewards Visa Signature | D38: Cabin Fever Sporting Goods Inc. | E38: 26.04 | F38: 0 | J38: 26.04 | K38: FALSE | N38: - | O38: =LEFT(Table2[[#This Row],[Description]],75) -> Cabin Fever Sporting Goods Inc.
A39: 201907 | B39: 43653 | C39: Cash Rewards Visa Signature | D39: Cabin Fever Sporting Goods Inc. | E39: 41 | F39: 0 | J39: 41 | K39: FALSE | N39: - | O39: =LEFT(Table2[[#This Row],[Description]],75) -> Cabin Fever Sporting Goods Inc.
A40: 201907 | B40: 43654 | C40: Discover | D40: ALLBIRDS 402-935-7733 CA | E40: 105 | F40: 0 | J40: 105 | K40: FALSE | N40: - | O40: =LEFT(Table2[[#This Row],[Description]],75) -> ALLBIRDS 402-935-7733 CA
A41: 201907 | B41: 43654 | C41: Discover More Card | D41: ALLBIRDS 402-935-7733 CA | E41: 105 | F41: 0 | J41: 105 | K41: FALSE | N41: - | O41: =LEFT(Table2[[#This Row],[Description]],75) -> ALLBIRDS 402-935-7733 CA
A42: 201907 | B42: 43654 | C42: POWERPLUS | D42: Deposit by Check Deposit Anywhere check deposit 234411967 | E42: -100 | F42: 0 | J42: 100 | K42: FALSE | N42: + | O42: =LEFT(Table2[[#This Row],[Description]],75) -> Deposit by Check Deposit Anywhere check deposit 234411967
A43: 201907 | B43: 43654 | C43: POWERPLUS CHECKING | D43: Deposit by Check Deposit Anywhere check deposit 234411967 | E43: -100 | F43: 0 | J43: 100 | K43: FALSE | N43: .+ | O43: =LEFT(Table2[[#This Row],[Description]],75) -> Deposit by Check Deposit Anywhere check deposit 234411967
A44: 201907 | B44: 43654 | C44: POWERPLUS | D44: Deposit by Check Deposit Anywhere check deposit 234411968 | E44: -50 | F44: 0 | J44: 50 | K44: FALSE | N44: + | O44: =LEFT(Table2[[#This Row],[Description]],75) -> Deposit by Check Deposit Anywhere check deposit 234411968
A45: 201907 | B45: 43654 | C45: POWERPLUS CHECKING | D45: Deposit by Check Deposit Anywhere check deposit 234411968 | E45: -50 | F45: 0 | J45: 50 | K45: FALSE | N45: .+ | O45: =LEFT(Table2[[#This Row],[Description]],75) -> Deposit by Check Deposit Anywhere check deposit 234411968
A46: 201907 | B46: 43654 | C46: Cash Rewards Visa Signature | D46: Prime VideoMH7ML21U2 8888023080 WA 234610356 | E46: 4.28 | F46: Entertainment | J46: 4.28 | K46: FALSE | N46: - | O46: =LEFT(Table2[[#This Row],[Description]],75) -> Prime VideoMH7ML21U2 8888023080 WA 234610356
A47: 201907 | B47: 43654 | C47: POWERPLUS | D47: Venmo Type Cashout | E47: -100 | F47: Delete | J47: 100 | K47: FALSE | N47: + | O47: =LEFT(Table2[[#This Row],[Description]],75) -> Venmo Type Cashout | P47: Delete; and Description='Venmo Type Cashout';0
A48: 201907 | B48: 43654 | C48: POWERPLUS CHECKING | D48: Venmo Type Cashout | E48: -100 | F48: Delete | J48: 100 | K48: FALSE | N48: .+ | O48: =LEFT(Table2[[#This Row],[Description]],75) -> Venmo Type Cashout | P48: Delete; and Description='Venmo Type Cashout';0
A49: 201907 | B49: 43655 | C49: Cash Rewards Visa Signature | D49: Amazon | E49: 13.93 | F49: Amazon | J49: 13.93 | K49: FALSE | N49: - | O49: =LEFT(Table2[[#This Row],[Description]],75) -> Amazon
A50: 201907 | B50: 43655 | C50: Cash Rewards Visa Signature | D50: Cub Foods | E50: 18.59 | F50: Groceries | J50: 18.59 | K50: FALSE | N50: - | O50: =LEFT(Table2[[#This Row],[Description]],75) -> Cub Foods
A51: 201907 | B51: 43655 | C51: Cash Rewards Visa Signature | D51: Cub Foods | E51: 100.68 | F51: Groceries | J51: 100.68 | K51: FALSE | N51: - | O51: =LEFT(Table2[[#This Row],[Description]],75) -> Cub Foods
A52: 201907 | B52: 43655 | C52: Investor Checking | D52: INST XFER 190708 | E52: 7.43 | F52: 0 | J52: 7.43 | K52: FALSE | N52: - | O52: =LEFT(Table2[[#This Row],[Description]],75) -> INST XFER 190708
A53: 201907 | B53: 43655 | C53: POWERPLUS | D53: Kaufman Hall Type | E53: -20.61 | F53: 0 | J53: 20.61 | K53: FALSE | N53: + | O53: =LEFT(Table2[[#This Row],[Description]],75) -> Kaufman Hall Type
A54: 201907 | B54: 43655 | C54: POWERPLUS CHECKING | D54: Kaufman Hall Type | E54: -20.61 | F54: 0 | J54: 20.61 | K54: FALSE | N54: .+ | O54: =LEFT(Table2[[#This Row],[Description]],75) -> Kaufman Hall Type
A55: 201907 | B55: 43655 | C55: POWERPLUS | D55: Venmo | E55: 25.5 | F55: 0 | J55: 25.5 | K55: FALSE | N55: - | O55: =LEFT(Table2[[#This Row],[Description]],75) -> Venmo
A56: 201907 | B56: 43655 | C56: POWERPLUS CHECKING | D56: Venmo | E56: 25.5 | F56: 0 | J56: 25.5 | K56: FALSE | N56: - | O56: =LEFT(Table2[[#This Row],[Description]],75) -> Venmo
A57: 201907 | B57: 43655 | C57: POWERPLUS | D57: Xcel Energy | E57: 119.79 | F57: Utilities | J57: 119.79 | K57: FALSE | N57: - | O57: =LEFT(Table2[[#This Row],[Description]],75) -> Xcel Energy | P57: Create Rule; and Description='Xcel Energy';Utilities
A58: 201907 | B58: 43655 | C58: POWERPLUS CHECKING | D58: Xcel Energy | E58: 119.79 | F58: Utilities | J58: 119.79 | K58: FALSE | N58: - | O58: =LEFT(Table2[[#This Row],[Description]],75) -> Xcel Energy
A59: 201907 | B59: 43656 | C59: Discover | D59: Amazon | E59: 26.83 | F59: Amazon | J59: 26.83 | K59: FALSE | N59: - | O59: =LEFT(Table2[[#This Row],[Description]],75) -> Amazon | P59: Create Rule; and Description='Amazon';Amazon
A60: 201907 | B60: 43656 | C60: Discover More Card | D60: Amazon | E60: 26.83 | F60: Amazon | J60: 26.83 | K60: FALSE | N60: - | O60: =LEFT(Table2[[#This Row],[Description]],75) -> Amazon
A61: 201907 | B61: 43656 | C61: POWERPLUS | D61: CCLC TYPE INTERNET ID CO CCLC ACH ECC WEB ACH Trace 46678 234870503 | E61: 247.5 | F61: Day Care | J61: 247.5 | K61: FALSE | N61: - | O61: =LEFT(Table2[[#This Row],[Description]],75) -> CCLC TYPE INTERNET ID CO CCLC ACH ECC WEB ACH Trace 46678 234870503 | P61: Create Rule; and Description Like '%CCLC TYPE INTERNET ID%';Day Care
A62: 201907 | B62: 43656 | C62: POWERPLUS CHECKING | D62: CCLC TYPE INTERNET ID CO CCLC ACH ECC WEB ACH Trace 46678 234870503 | E62: 247.5 | F62: Day Care | J62: 247.5 | K62: FALSE | N62: - | O62: =LEFT(Table2[[#This Row],[Description]],75) -> CCLC TYPE INTERNET ID CO CCLC ACH ECC WEB ACH Trace 46678 234870503
A63: 201907 | B63: 43656 | C63: Cash Rewards Visa Signature | D63: Milio's Sandwiches | E63: 15.27 | F63: 0 | J63: 15.27 | K63: FALSE | N63: - | O63: =LEFT(Table2[[#This Row],[Description]],75) -> Milio's Sandwiches | P63: Manual
A64: 201907 | B64: 43656 | C64: Cash Rewards Visa Signature | D64: SEAT ENGINE LLC 8887328364 PA 235209088 | E64: 43.5 | F64: 0 | J64: 43.5 | K64: FALSE | N64: - | O64: =LEFT(Table2[[#This Row],[Description]],75) -> SEAT ENGINE LLC 8887328364 PA 235209088
A65: 201907 | B65: 43656 | C65: Target Credit Card | D65: Target | E65: 29.7 | F65: Target | J65: 29.7 | K65: FALSE | N65: - | O65: =LEFT(Table2[[#This Row],[Description]],75) -> Target
A66: 201907 | B66: 43657 | C66: POWERPLUS | D66: Cargill Incorpor Type | E66: -87.26 | F66: Inc - Other | J66: 87.26 | K66: FALSE | N66: + | O66: =LEFT(Table2[[#This Row],[Description]],75) -> Cargill Incorpor Type | P66: Create Rule; and Description='Cargill Incorpor Type';Inc - Other
A67: 201907 | B67: 43657 | C67: POWERPLUS CHECKING | D67: Cargill Incorpor Type | E67: -87.26 | F67: Inc - Other | J67: 87.26 | K67: FALSE | N67: .+ | O67: =LEFT(Table2[[#This Row],[Description]],75) -> Cargill Incorpor Type
A68: 201907 | B68: 43657 | C68: Cash Rewards Visa Signature | D68: Hudson News | E68: 8.88 | F68: Transportation | J68: 8.88 | K68: FALSE | N68: - | O68: =LEFT(Table2[[#This Row],[Description]],75) -> Hudson News | P68: Create Rule; and Description='Hudson News';Transportation
A69: 201907 | B69: 43658 | C69: Cash Rewards Visa Signature | D69: Buffalo Niagara Taxi | E69: 9.92 | F69: Transportation | J69: 9.92 | K69: FALSE | N69: - | O69: =LEFT(Table2[[#This Row],[Description]],75) -> Buffalo Niagara Taxi
A70: 201907 | B70: 43659 | C70: Discover | D70: Acme | E70: 17.8 | F70: 0 | J70: 17.8 | K70: FALSE | N70: - | O70: =LEFT(Table2[[#This Row],[Description]],75) -> Acme
A71: 201907 | B71: 43659 | C71: Discover More Card | D71: Acme | E71: 17.8 | F71: 0 | J71: 17.8 | K71: FALSE | N71: - | O71: =LEFT(Table2[[#This Row],[Description]],75) -> Acme | P71: Manual
A72: 201907 | B72: 43659 | C72: Discover | D72: BAR LA GRASSA MINNEAPOLIS MN | E72: 131.79 | F72: 0 | J72: 131.79 | K72: FALSE | N72: - | O72: =LEFT(Table2[[#This Row],[Description]],75) -> BAR LA GRASSA MINNEAPOLIS MN
A73: 201907 | B73: 43659 | C73: Discover More Card | D73: BAR LA GRASSA MINNEAPOLIS MN | E73: 131.79 | F73: 0 | J73: 131.79 | K73: FALSE | N73: - | O73: =LEFT(Table2[[#This Row],[Description]],75) -> BAR LA GRASSA MINNEAPOLIS MN | P73: Manual
A74: 201907 | B74: 43659 | C74: POWERPLUS | D74: CARGILL COCOA TYPE DIR DEP ID CO CARGILL COCOA ACH ECC PPD ACH Trace 05327 235786427 | E74: -2439.29 | F74: Inc - Britney | J74: 2439.29 | K74: FALSE | N74: + | O74: =LEFT(Table2[[#This Row],[Description]],75) -> CARGILL COCOA TYPE DIR DEP ID CO CARGILL COCOA ACH ECC PPD ACH Trace 05327 | P74: Create Rule; and Description Like '%CARGILL COCOA TYPE DIR DEP ID%';Inc - Britney
A75: 201907 | B75: 43659 | C75: POWERPLUS CHECKING | D75: CARGILL COCOA TYPE DIR DEP ID CO CARGILL COCOA ACH ECC PPD ACH Trace 05327 235786427 | E75: -2439.29 | F75: Inc - Britney | J75: 2439.29 | K75: FALSE | N75: .+ | O75: =LEFT(Table2[[#This Row],[Description]],75) -> CARGILL COCOA TYPE DIR DEP ID CO CARGILL COCOA ACH ECC PPD ACH Trace 05327
A76: 201907 | B76: 43659 | C76: Target Credit Card | D76: CENTRAL CHECKOUT 79999999194135608672416 | E76: 153.38 | F76: Shopping | J76: 153.38 | K76: FALSE | N76: - | O76: =LEFT(Table2[[#This Row],[Description]],75) -> CENTRAL CHECKOUT 79999999194135608672416
A77: 201907 | B77: 43659 | C77: POWERPLUS | D77: KAUFMAN HALL TYPE DIRECT DEP ID CO KAUFMAN HALL ACH ECC PPD ACH Trace 45671 235786428 | E77: -2570.35 | F77: Inc - Jeff | J77: 2570.35 | K77: FALSE | N77: + | O77: =LEFT(Table2[[#This Row],[Description]],75) -> KAUFMAN HALL TYPE DIRECT DEP ID CO KAUFMAN HALL ACH ECC PPD ACH Trace 45671 | P77: Create Rule; and Description Like '%KAUFMAN HALL TYPE DIRECT DEP ID%';Inc - Jeff
A78: 201907 | B78: 43659 | C78: POWERPLUS CHECKING | D78: KAUFMAN HALL TYPE DIRECT DEP ID CO KAUFMAN HALL ACH ECC PPD ACH Trace 45671 235786428 | E78: -2570.35 | F78: Inc - Jeff | J78: 2570.35 | K78: FALSE | N78: .+ | O78: =LEFT(Table2[[#This Row],[Description]],75) -> KAUFMAN HALL TYPE DIRECT DEP ID CO KAUFMAN HALL ACH ECC PPD ACH Trace 45671
A79: 201907 | B79: 43659 | C79: POWERPLUS | D79: Washington Gas | E79: 103 | F79: 0 | J79: 103 | K79: FALSE | N79: - | O79: =LEFT(Table2[[#This Row],[Description]],75) -> Washington Gas
A80: 201907 | B80: 43659 | C80: POWERPLUS CHECKING | D80: Washington Gas | E80: 103 | F80: 0 | J80: 103 | K80: FALSE | N80: - | O80: =LEFT(Table2[[#This Row],[Description]],75) -> Washington Gas | P80: Manual
A81: 201907 | B81: 43660 | C81: Cash Rewards Visa Signature | D81: CARGILL PRODUC20081436 WAYZATA MN 235985503 | E81: 43.91 | F81: Groceries | J81: 43.91 | K81: FALSE | N81: - | O81: =LEFT(Table2[[#This Row],[Description]],75) -> CARGILL PRODUC20081436 WAYZATA MN 235985503
A82: 201907 | B82: 43660 | C82: Cash Rewards Visa Signature | D82: CARGILL PRODUC20081436 WAYZATA MN 235985504 | E82: 48.25 | F82: Groceries | J82: 48.25 | K82: FALSE | N82: - | O82: =LEFT(Table2[[#This Row],[Description]],75) -> CARGILL PRODUC20081436 WAYZATA MN 235985504
A83: 201907 | B83: 43660 | C83: Cash Rewards Visa Signature | D83: Cub Foods | E83: 92.89 | F83: Groceries | J83: 92.89 | K83: FALSE | N83: - | O83: =LEFT(Table2[[#This Row],[Description]],75) -> Cub Foods
A84: 201907 | B84: 43660 | C84: Cash Rewards Visa Signature | D84: NORTH COOP CHAHASSEN MN 235985506 | E84: 62.13 | F84: 0 | J84: 62.13 | K84: FALSE | N84: - | O84: =LEFT(Table2[[#This Row],[Description]],75) -> NORTH COOP CHAHASSEN MN 235985506 | P84: Manual
A85: 201907 | B85: 43660 | C85: Cash Rewards Visa Signature | D85: NORTH COOP CHAHASSEN MN 235985507 | E85: 18.73 | F85: 0 | J85: 18.73 | K85: FALSE | N85: - | O85: =LEFT(Table2[[#This Row],[Description]],75) -> NORTH COOP CHAHASSEN MN 235985507 | P85: Manual
A86: 201907 | B86: 43661 | C86: Discover | D86: Amazon | E86: 9.64 | F86: Amazon | J86: 9.64 | K86: FALSE | N86: - | O86: =LEFT(Table2[[#This Row],[Description]],75) -> Amazon | P86: Create Rule; and Description='Amazon';Amazon
A87: 201907 | B87: 43661 | C87: Discover More Card | D87: Amazon | E87: 9.64 | F87: Amazon | J87: 9.64 | K87: FALSE | N87: - | O87: =LEFT(Table2[[#This Row],[Description]],75) -> Amazon
A88: 201907 | B88: 43661 | C88: POWERPLUS | D88: American Family Insurance | E88: 99.03 | F88: Insurance | J88: 99.03 | K88: FALSE | N88: - | O88: =LEFT(Table2[[#This Row],[Description]],75) -> American Family Insurance | P88: Create Rule; and Description='American Family Insurance';Insurance
A89: 201907 | B89: 43661 | C89: POWERPLUS CHECKING | D89: American Family Insurance | E89: 99.03 | F89: Insurance | J89: 99.03 | K89: FALSE | N89: - | O89: =LEFT(Table2[[#This Row],[Description]],75) -> American Family Insurance
A90: 201907 | B90: 43661 | C90: Cash Rewards Visa Signature | D90: Lululemon | E90: 68 | F90: Shopping | J90: 68 | K90: FALSE | N90: - | O90: =LEFT(Table2[[#This Row],[Description]],75) -> Lululemon | P90: Create Rule; and Description='Lululemon';Shopping
A91: 201907 | B91: 43661 | C91: Cash Rewards Visa Signature | D91: SHOREWOOD LIQUOR EXCELSIOR MN 236288792 | E91: 32.91 | F91: 0 | J91: 32.91 | K91: FALSE | N91: - | O91: =LEFT(Table2[[#This Row],[Description]],75) -> SHOREWOOD LIQUOR EXCELSIOR MN 236288792 | P91: Manual
A92: 201907 | B92: 43661 | C92: Roth Contributory IRA | D92: Tfr JPMORGAN CHASE BAN, CARGILL COCOA & | E92: -150 | F92: Roth | J92: 150 | K92: FALSE | N92: .+ | O92: =LEFT(Table2[[#This Row],[Description]],75) -> Tfr JPMORGAN CHASE BAN, CARGILL COCOA &
A93: 201907 | B93: 43661 | C93: Jeff Roth | D93: Tfr JPMORGAN CHASE BAN, KAUFMAN HALL | E93: -211 | F93: Roth | J93: 211 | K93: FALSE | N93: + | O93: =LEFT(Table2[[#This Row],[Description]],75) -> Tfr JPMORGAN CHASE BAN, KAUFMAN HALL | P93: Create Rule; and Description='Tfr JPMORGAN CHASE BAN, KAUFMAN HALL';Roth
A94: 201907 | B94: 43661 | C94: Roth Contributory IRA | D94: Tfr JPMORGAN CHASE BAN, KAUFMAN HALL | E94: -211 | F94: Roth | J94: 211 | K94: FALSE | N94: .+ | O94: =LEFT(Table2[[#This Row],[Description]],75) -> Tfr JPMORGAN CHASE BAN, KAUFMAN HALL
A95: 201907 | B95: 43661 | C95: Cash Rewards Visa Signature | D95: Total Wine and More | E95: 76.95 | F95: Groceries | J95: 76.95 | K95: FALSE | N95: - | O95: =LEFT(Table2[[#This Row],[Description]],75) -> Total Wine and More | P95: Create Rule; and Description='Total Wine and More';Groceries
A96: 201907 | B96: 43661 | C96: Cash Rewards Visa Signature | D96: Transfer from POWERPLUS CHECKING | E96: -381.36 | F96: Delete | J96: 381.36 | K96: FALSE | N96: .+ | O96: =LEFT(Table2[[#This Row],[Description]],75) -> Transfer from POWERPLUS CHECKING
A97: 201907 | B97: 43661 | C97: POWERPLUS | D97: Transfer to Cash Rewards Visa Signature | E97: 381.36 | F97: Delete | J97: 381.36 | K97: FALSE | N97: - | O97: =LEFT(Table2[[#This Row],[Description]],75) -> Transfer to Cash Rewards Visa Signature | P97: Delete; and Description Like '%Transfer to Cash Rewards Visa Signature%';0
A98: 201907 | B98: 43661 | C98: POWERPLUS CHECKING | D98: Transfer to Cash Rewards Visa Signature | E98: 381.36 | F98: Delete | J98: 381.36 | K98: FALSE | N98: - | O98: =LEFT(Table2[[#This Row],[Description]],75) -> Transfer to Cash Rewards Visa Signature
A99: 201907 | B99: 43661 | C99: KAUFMAN | D99: VANG TARGET RET 2050 | E99: -1058.95 | F99: 401K | J99: 1058.95 | K99: FALSE | N99: .+ | O99: =LEFT(Table2[[#This Row],[Description]],75) -> VANG TARGET RET 2050
A100: 201907 | B100: 43661 | C100: Cash Rewards Visa Signature | D100: Walgreens | E100: 24.4 | F100: Shopping | J100: 24.4 | K100: FALSE | N100: - | O100: =LEFT(Table2[[#This Row],[Description]],75) -> Walgreens
...

Sheet Actuals Lookup
A1: Yrmo | B1: Date | C1: Source | D1: Description | E1: Amount | F1: Category
A2: 202301 | B2: 44927 | C2: DISCOVER MORE CARD | D2: AMAZON MUSIC*H06YQ2L23 888-802-3080 WA 2SZOGVT1ISL | E2: 5.36 | F2: Amazon
A3: 202301 | B3: 44927 | C3: Cash Rewards Visa Signature | D3: CARIBOU COFFEE CO #116 REF #001280 | E3: -6.43 | F3: Restaurants
A4: 202301 | B4: 44927 | C4: Cash Rewards Visa Signature | D4: HOME2 SUITES EDEN PRAIRIE REF #031953 | E4: -25 | F4: Travel
A5: 202301 | B5: 44927 | C5: DISCOVER MORE CARD | D5: LUNDS&BYERLYS CHANHAS CHANHASSEN MN | E5: 194.66 | F5: Groceries
A6: 202301 | B6: 44927 | C6: HIGHLANDER | D6: Payments Home Banking Transfer From Share 70 REF # 2402682 | E6: -618.65 | F6: Delete
A7: 202301 | B7: 44927 | C7: Cash Rewards Visa Signature | D7: PIZZA LUCE VI INC 952-767-0854 MN | E7: 57.01 | F7: Restaurants
A8: 202301 | B8: 44927 | C8: POWERPLUS | D8: Withdrawal Home Banking Transfer To Loan 02 REF # 1940599 | E8: 618.65 | F8: Car Loan
A9: 202301 | B9: 44927 | C9: POWERPLUS | D9: Withdrawal Home Banking Transfer To Loan 02 REF # 2402682 | E9: 618.65 | F9: Delete
A10: 202301 | B10: 44928 | C10: Cash Rewards Visa Signature | D10: CUB FOODS #1636 SHOREWOOD MN | E10: 15.66 | F10: Restaurants
A11: 202301 | B11: 44928 | C11: Cash Rewards Visa Signature | D11: HBRSUBSCRIPTION 800-988-0886 MA | E11: 20 | F11: Utilities
A12: 202301 | B12: 44928 | C12: Cash Rewards Visa Signature | D12: SP MINNESOTA ICE MAZE MINNESOTAICEM MN | E12: 84.2 | F12: Entertainment
A13: 202301 | B13: 44929 | C13: DISCOVER MORE CARD | D13: AMZN MKTP US*7B5D40OE3 AMZN.COM/BILLWA 73FWI3OC7KE | E13: 32.2 | F13: Amazon
... A560: 202303 | B560: 45016 | C560: Powerplus - Ending in 8s01 | D560: Discover Bank | E560: -11500 | F560: Delete
A561: 202304 | B561: 45017 | D561: Cleaning | E561: 250 | F561: Cleaning
A562: 202304 | B562: 45017 | C562: Delta Skymiles Platinum - Ending in 1007 | D562: Food Truck Alley Saint Paul Mn 03xkdpv5d3e Xxxxxx0055 | E562: 45.41 | F562: Restaurants
A563: 202304 | B563: 45017 | C563: Delta Skymiles Platinum - Ending in 1007 | D563: Food Truck Alley Saint Paul Mn 03xkdpv5d3e Xxxxxx0055 | E563: -45.41 | F563: Restaurants
A564: 202304 | B564: 45017 | C564: Discover More Card - Ending in 7779 | D564: Publix | E564: 267.01 | F564: Groceries
A565: 202304 | B565: 45017 | C565: Discover More Card - Ending in 7779 | D565: Publix | E565: -267.01 | F565: Groceries
A566: 202304 | B566: 45017 | C566: Delta Skymiles Platinum - Ending in 1007 | D566: Smokin R's Bbq Naples Fl Rqdp9hw5zii Squareup.com/receipts | E566: 41.5 | F566: Restaurants
A567: 202304 | B567: 45017 | C567: Delta Skymiles Platinum - Ending in 1007 | D567: Smokin R's Bbq Naples Fl Rqdp9hw5zii Squareup.com/receipts | E567: -41.5 | F567: Restaurants
A568: 202304 | B568: 45017 | C568: Powerplus - Ending in 8s36 | D568: Withdrawal Home Banking Transfer To Loan 02 REF # 3832345 | E568: 618.65 | F568: Car Loan
A569: 202304 | B569: 45018 | C569: Cash Rewards Visa Signature - Ending in 5977 | D569: Amazon Music*HY9257YF0 888-802-3080 WA REF #24692162V302TS4ZQ | E569: 5.36 | F569: Shopping
A570: 202304 | B570: 45018 | C570: Cash Rewards Visa Signature - Ending in 5976 | D570: AMZN Mktp US*HS8HE9CE0 Amzn.com/billWA REF #24692162V305QQLWQ | E570: 15.96 | F570: Amazon
A571: 202304 | B571: 45018 | C571: Delta Skymiles Platinum - Ending in 1007 | D571: Mcdonald's | E571: 15.85 | F571: Restaurants
A572: 202304 | B572: 45018 | C572: Delta Skymiles Platinum - Ending in 1007 | D572: Mcdonald's | E572: -15.85 | F572: Restaurants
A573: 202304 | B573: 45018 | C573: Cash Rewards Visa Signature - Ending in 5978 | D573: SP NORMAL BRAND LLC THENORMALBRAN CREDIT REF #24492162S000H2HSP | E573: -89 | F573: Entertainment
... A739: 202305 | B739: 45047 | C739: Cash Rewards Visa Signature - Ending in 6005 | D739: AMZN Mktp US*HM40K3AB2 Amzn.com/billWA REF #24692163T33HK4QV6 | E739: 77.98 | F739: Amazon
A740: 202305 | B740: 45047 | D740: Cleaning | E740: 250 | F740: Cleaning
A741: 202305 | B741: 45047 | C741: Cash Rewards Visa Signature - Ending in 6008 | D741: HILTON GARDEN INN BOSTON EAST BOSTON MA REF #24275393RS66HS55Z | E741: 301.15 | F741: Delete
A742: 202305 | B742: 45047 | C742: Cash Rewards Visa Signature - Ending in 6009 | D742: JAXON GREY MINNEAPOLIS MN REF #24269793R2XTA5RDS | E742: 392 | F742: Shopping
A743: 202305 | B743: 45047 | C743: Powerplus - Ending in 8s78 | D743: Payment to American Express | E743: 2631.79 | F743: Delete
A744: 202305 | B744: 45047 | C744: Powerplus - Ending in 8s79 | D744: Payment to Baxter Credit Union | E744: 2606.27 | F744: Rent
A745: 202305 | B745: 45047 | C745: Cash Rewards Visa Signature - Ending in 6004 | D745: SCHEELS EDEN PRAIRIE EDEN PRAIRIE CREDIT REF #74138293TP6Q5W11J | E745: -54 | F745: Shopping
A746: 202305 | B746: 45047 | C746: Powerplus - Ending in 8s82 | D746: Transfer to PayPal | E746: 6.47 | F746: Shopping
A747: 202305 | B747: 45047 | C747: Powerplus - Ending in 8s81 | D747: Transfer to Venmo | E747: 35 | F747: Shopping
A748: 202305 | B748: 45047 | C748: Cash Rewards Visa Signature - Ending in 6007 | D748: TST* Red Cow - 1st Ave 612-238-0050 MN REF #24692163R32YMJV0G | E748: 58.81 | F748: Restaurants
A749: 202305 | B749: 45047 | C749: Powerplus - Ending in 8s80 | D749: Withdrawal ACH College Savings TYPE: ACH ID: XX5818 CO: College Savings Entry Class Code: ACH Trace Number: XX3102 | E749: 500 | F749: Delete
A750: 202305 | B750: 45047 | C750: Powerplus - Ending in 8s77 | D750: Withdrawal Home Banking Transfer To Loan 02 REF # XX4306 | E750: 618.65 | F750: Car Loan
A751: 202305 | B751: 45048 | C751: Cash Rewards Visa Signature - Ending in 5997 | D751: AMZN Mktp US*HM5QO4GT2 Amzn.com/billWA REF #24692163S346Y5WE6 | E751: 82.64 | F751: Amazon
A752: 202305 | B752: 45048 | C752: Cash Rewards Visa Signature - Ending in 5999 | D752: JAXON GREY-EDINA EDINA MN REF #24269793TEJ80KFGX | E752: 68 | F752: Shopping
... A1264: 202308 | B1264: 45139 | C1264: Delta Skymiles Platinum - Ending in 1007 | D1264: Target | E1264: 102.55 | F1264: Target
A1265: 202308 | B1265: 45139 | C1265: Powerplus - Ending in 8s67 | D1265: Transfer to College Station | E1265: 500 | F1265: #N/A
A1266: 202308 | B1266: 45139 | C1266: Powerplus - Ending in 8s68 | D1266: Withdrawal ACH MHCHILDCARELLC TYPE: DUES ID: XX8198 CO: MHCHILDCARELLC Entry Class Code: ACH Trace Number: XX4406 | E1266: 265 | F1266: Day Care
A1267: 202308 | B1267: 45139 | C1267: Powerplus - Ending in 8s69 | D1267: Withdrawal Home Banking Transfer To Loan 02 REF # XX2243 | E1267: 618.65 | F1267: Car Loan
A1268: 202308 | B1268: 45140 | C1268: Powerplus - Ending in 8s94 | D1268: BCY*BACKCOUNTRY.COM 800-409- CREDIT REF #74692166M32G39RAV | E1268: -154.02 | F1268: Shopping
A1269: 202308 | B1269: 45140 | C1269: Powerplus - Ending in 8s95 | D1269: COMPANY STORE WAYZATA MN REF #24943006NW5TTMGPD | E1269: 37.84 | F1269: Groceries
A1270: 202308 | B1270: 45140 | C1270: Delta Skymiles Platinum - Ending in 1007 | D1270: Jaxen Grey - Ridgedaminnetonka Xxxxxxxxxxx Xxxxxx8672 | E1270: -216 | F1270: Shopping
A1271: 202308 | B1271: 45140 | C1271: Powerplus - Ending in 8s65 | D1271: Transfer to Discover Bank | E1271: 40000 | F1271: Delete
A1272: 202308 | B1272: 45140 | C1272: Delta Skymiles Platinum - Ending in 1007 | D1272: Tst* Lost Bay Llc 00excelsior Mn Xxxxxxx3215 Restaurant | E1272: 127.78 | F1272: Shopping
A1273: 202308 | B1273: 45141 | C1273: Powerplus - Ending in 8s92 | D1273: AMZN Mktp US*TH0ZS5IQ2 Amzn.com/billWA REF #24692166N331JD3FY | E1273: 24.99 | F1273: Amazon
A1274: 202308 | B1274: 45141 | C1274: Powerplus - Ending in 8s91 | D1274: AMZN Mktp US*TH8A86BG1 Amzn.com/billWA REF #24692166N336BYVTA | E1274: 10.19 | F1274: Amazon
A1275: 202308 | B1275: 45141 | C1275: Delta Skymiles Platinum - Ending in 1007 | D1275: Bmw | E1275: 766.62 | F1275: Transportation
A1276: 202308 | B1276: 45141 | C1276: Powerplus - Ending in 8s64 | D1276: Cargill Inc Deposit | E1276: -3524.05 | F1276: Britney
A1277: 202308 | B1277: 45141 | C1277: Delta Skymiles Platinum - Ending in 1007 | D1277: Centro | E1277: 15.55 | F1277: Restaurants
... A1322: 202308 | B1322: 45148 | C1322: Powerplus - Ending in 8s73 | D1322: HALSEY44* #33614 HALSEY44.COM CA REF #24492166X0014NSSK | E1322: 130 | F1322: Shopping
A1323: 202308 | B1323: 45148 | C1323: Powerplus - Ending in 8s74 | D1323: NA'S THAI CAFE CHANHASSEN MN REF #24055226X60ZHX75X | E1323: 123.36 | F1323: #REF!
A1324: 202308 | B1324: 45148 | C1324: Delta Skymiles Platinum - Ending in 1007 | D1324: Total Wine & More | E1324: 51.6 | F1324: Groceries
A1325: 202308 | B1325: 45149 | C1325: Delta Skymiles Platinum - Ending in 1007 | D1325: Aroma | E1325: 3.46 | F1325: Transportation
A1326: 202308 | B1326: 45149 | C1326: Powerplus - Ending in 8s70 | D1326: CARGILL STORE WAYZATA MN REF #24943006YRLQ5EJZ7 | E1326: 3.75 | F1326: Groceries
A1327: 202308 | B1327: 45149 | C1327: Powerplus - Ending in 8s69 | D1327: COSTCO WHSE #0783 EDEN PRAIRIE MN REF #24943006ZS4AFHLTQ | E1327: 122.46 | F1327: Groceries
A1328: 202308 | B1328: 45149 | C1328: Delta Skymiles Platinum - Ending in 1007 | D1328: Cub Foods | E1328: 43.61 | F1328: Groceries
A1329: 202308 | B1329: 45149 | C1329: Delta Skymiles Platinum - Ending in 1007 | D1329: Kowalski's Market | E1329: 7.13 | F1329: Groceries
A1330: 202308 | B1330: 45149 | C1330: Delta Skymiles Platinum - Ending in 1007 | D1330: Miyabi | E1330: 49.61 | F1330: Restaurants
A1331: 202308 | B1331: 45149 | C1331: Delta Skymiles Platinum - Ending in 1007 | D1331: N 4543 State Hwy 22 Shawano Wi Xxxxxxxxxxx Xxxxxx4454 | E1331: 57.98 | F1331: Utilities
A1332: 202308 | B1332: 45149 | C1332: Powerplus - Ending in 8s71 | D1332: Netflix 1 8445052993 CA REF #24002846Y00FSZAWK | E1332: 25.36 | F1332: Utilities
A1333: 202308 | B1333: 45149 | C1333: Powerplus - Ending in 8s68 | D1333: SHUTTERFLY INC. 650-610- CREDIT REF #74492156YLXRP9S68 | E1333: -57.68 | F1333: Shopping
A1334: 202308 | B1334: 45149 | C1334: Delta Skymiles Platinum - Ending in 1007 | D1334: Thornberry Creek | E1334: 28 | F1334: Entertainment
A1335: 202308 | B1335: 45149 | C1335: Delta Skymiles Platinum - Ending in 1007 | D1335: Thornberry Creek | E1335: 48 | F1335: Entertainment
... A1357: 202308 | B1357: 45154 | C1357: Powerplus - Ending in 8s61 | D1357: WAYZATA CAFE WAYZATA MN REF #249430074W5XJE6EK | E1357: 7.74 | F1357: Restaurants
A1358: 202308 | B1358: 45154 | C1358: Powerplus - Ending in 8s52 | D1358: Withdrawal ACH NORTHERN STAR EV TYPE: SES:XX0330 ID: XX3620 CO: NORTHERN STAR EV NAME: NORTHERN STAR SCOUTI Entry Class Code: WEB ACH Trace Number: XX4504 | E1358: 205 | F1358: #N/A
A1359: 202308 | B1359: 45155 | C1359: Powerplus - Ending in 8s50 | D1359: Cargill Inc Deposit | E1359: -3630.74 | F1359: Britney
A1360: 202308 | B1360: 45155 | C1360: Powerplus - Ending in 8s51 | D1360: Deposit ACH EMPYREAN SOLUTIO TYPE: XX9000 ID: XX3620 CO: EMPYREAN SOLUTIO Entry Class Code: ACH Trace Number: XX0574 | E1360: -2417.85 | F1360: Jeff
A1361: 202308 | B1361: 45155 | C1361: Delta Skymiles Platinum - Ending in 1007 | D1361: Sumo & Smoh Chaska Mn V2oux13jscj Squareup.com/receipts | E1361: 39.16 | F1361: Restaurants
A1362: 202308 | B1362: 45156 | C1362: Discover More Card - Ending in 7779 | D1362: Directpay Full Balance | E1362: -33.8 | F1362: Delete
A1363: 202308 | B1363: 45156 | C1363: Delta Skymiles Platinum - Ending in 1007 | D1363: Go Concessions 0000 Oakdale Mn Xxxxxxxx Xxx-xxx-9138 | E1363: 14.96 | F1363: Entertainment
A1364: 202308 | B1364: 45156 | C1364: Delta Skymiles Platinum - Ending in 1007 | D1364: Holiday Stationstores | E1364: 56.25 | F1364: Groceries
A1365: 202308 | B1365: 45156 | C1365: Powerplus - Ending in 8s49 | D1365: Withdrawal ACH MN DIR ACH TYPE: CONTRIB ID: XX7162 CO: MN DIR ACH NAME: XX2601 Entry Class Code: WEB ACH Trace Number: XX8183 | E1365: 650 | F1365: Day Care
A1366: 202308 | B1366: 45158 | C1366: Powerplus - Ending in 8s60 | D1366: BCS*MINNETONKA COMMUNITY 952-401-6800 MN REF #24137467701FF7NF1 | E1366: 178.5 | F1366: Day Care
A1367: 202308 | B1367: 45158 | C1367: Delta Skymiles Platinum - Ending in 1007 | D1367: Tst* Maynards - Outsexcelsior Mn Xxxxxxx3013 Restaurant | E1367: 116.2 | F1367: Restaurants
A1368: 202308 | B1368: 45159 | C1368: Powerplus - Ending in 8s59 | D1368: BONFES PLUMBING HEATING A651-3326633 MN REF #242753978S66L4SKD | E1368: 11 | F1368: Utilities
A1369: 202308 | B1369: 45159 | C1369: Delta Skymiles Platinum - Ending in 1007 | D1369: Caribou Coffee | E1369: 12.24 | F1369: Restaurants
A1370: 202308 | B1370: 45159 | C1370: Powerplus - Ending in 8s45 | D1370: Deposit Home Banking Transfer From Share 01 REF # XX2129 | E1370: -3000 | F1370: Delete
... A1564: 202309 | B1564: 45188 | C1564: Delta Skymiles Platinum - Ending in 1007 | D1564: Aplpay Order.noodlesbroomfield Co | E1564: 32.48 | F1564: Restaurants
A1565: 202309 | B1565: 45188 | C1565: Delta Skymiles Platinum - Ending in 1007 | D1565: Carrolls Irish Giftscork | E1565: 10.68 | F1565: #N/A
A1566: 202309 | B1566: 45188 | C1566: Powerplus - Ending in 8s46 | D1566: Draft 2350 Tracer XX1247 | E1566: 53 | F1566: Shopping
A1567: 202309 | B1567: 45188 | C1567: Cash Rewards Visa Signature - Ending in 5944 | D1567: HMSHost | E1567: 3.53 | F1567: Restaurants
A1568: 202309 | B1568: 45188 | C1568: Powerplus - Ending in 8s47 | D1568: Payment to Discover Bank | E1568: 159.26 | F1568: Delete
A1569: 202309 | B1569: 45188 | C1569: Cash Rewards Visa Signature - Ending in 5945 | D1569: PV CAB 01 MIDLETON IE REF #XX6866HMS4ATR | E1569: 29.93 | F1569: Delete
A1570: 202309 | B1570: 45188 | C1570: Powerplus - Ending in 8s45 | D1570: Transfer from Venmo | E1570: -3173.88 | F1570: Delete
A1571: 202309 | B1571: 45188 | C1571: Powerplus - Ending in 8s48 | D1571: Transfer to PayPal | E1571: 2.99 | F1571: Shopping
A1572: 202309 | B1572: 45189 | C1572: Cash Rewards Visa Signature - Ending in 5939 | D1572: 5 POINTS DELI AND CAFE CORK CITY IE REF #XX8700T1T2E2 | E1572: 45.27 | F1572: Delete
A1573: 202309 | B1573: 45189 | C1573: Cash Rewards Visa Signature - Ending in 5937 | D1573: Burnt Pizza | E1573: 45.48 | F1573: Delete
A1574: 202309 | B1574: 45189 | C1574: Cash Rewards Visa Signature - Ending in 5942 | D1574: Google Cloud Storage | E1574: 0.49 | F1574: Utilities
A1575: 202309 | B1575: 45189 | C1575: Cash Rewards Visa Signature - Ending in 5940 | D1575: MCW 1602-MINNETONKA XX8113 MN REF #XX0586VALFABJS | E1575: -0.7 | F1575: Day Care
A1576: 202309 | B1576: 45189 | C1576: Cash Rewards Visa Signature - Ending in 5943 | D1576: Noodles & Company | E1576: 3.76 | F1576: Restaurants
A1577: 202309 | B1577: 45189 | C1577: Powerplus - Ending in 8s43 | D1577: Payment to American Express | E1577: 9950.69 | F1577: Delete
... A1740: 202310 | B1740: 45216 | C1740: Delta Skymiles Platinum - Ending in 1007 | D1740: Speedway | E1740: 62.44 | F1740: Transportation
A1741: 202310 | B1741: 45216 | C1741: Delta Skymiles Platinum - Ending in 1007 | D1741: Target | E1741: 34.93 | F1741: #N/A
A1742: 202310 | B1742: 45216 | C1742: Powerplus - Ending in 8s30 | D1742: Transfer to Venmo | E1742: 132 | F1742: Shopping
...

Sheet Main 2
C2: ='1 MO'!C2 -> 45992
C4: ="Truitt Financials "&TEXT(C2,"MMMM")&" "&TEXT(C2,"YYYY") -> Truitt Financials December 2025
Q7: Budget | R7: Actual
C8: Spending
C9: Monthly Budget: | D9: ='1 MO'!D35 -> 13150 | H9: YTD Budget: | I9: =YTD!D31 -> 157800 | P9: Healthcare | Q9: ='2025 Budget'!O31 -> 2400 | R9: =YTD!C33 -> 3948.01
C10: Spend | D10: ='1 MO'!C35 -> 12529.33 | H10: YTD Spend: | I10: =YTD!C31 -> 164559.5 | P10: House | Q10: ='2025 Budget'!O32 -> 81132 | R10: =YTD!C34 -> 265799.33
P11: Travel | Q11: ='2025 Budget'!O33 -> 13500 | R11: =YTD!C35 -> 16470.36
P14: Financial Goals:
P15: Pay for Cooper & Tuckers college
P16: Retire comfortably
P17: Update house
P18: Stay in budget & reduce stress around finances
P21: 2023 | Q21: -27700
P22: 2022 | Q22: 371119
C23: Yearly Spend Budget: | D23: ='2025 Budget'!O34 -> 97032 | H23: Total Year Budget: | I23: ='2025 Budget'!O36 -> 254832 | P23: 2021 | Q23: 327571
C24: Yearly Spend: | D24: =YTD!C36 -> 286217.7 | H24: Reforecast Budget: | I24: =Revised!P47 -> 450777.2 | P24: 2020 | Q24: 253416
P25: 2019 | Q25: 229415
P26: 2018 | Q26: 188488
P27: 2017 | Q27: 149370
C37: Income | H37: Savings
C38: Projected | D38: ='Main Detail'!D42 -> 391496.07 | H38: Projected | I38: ='Main Detail'!D69 -> 112569
C39: Actual | D39: ='Main Detail'!D51 -> 496800.83 | H39: Actual | I39: ='Main Detail'!D89 -> 117472
C52: Outlook
C80: Balance Sheet
C84: Assets | D84: =EOMONTH(C2,0) -> 46022 | E84: 45657 | F84: $Δ | G84: %Δ
C85: Schwab | D85: 533442.75 | E85: 563767.81 | F85: =D85-E85 -> -30325.06 | G85: =(D85-E85)/E85 -> -0.053789981
C86: Voya (Fidelity) 401K | D86: 555402.24 | E86: 448660.4 | F86: =D86-E86 -> 106741.84 | G86: =(D86-E86)/E86 -> 0.23791233
C87: Vanguard 401K | D87: 511072.69 | E87: 397733.35 | F87: =D87-E87 -> 113339.34 | G87: =(D87-E87)/E87 -> 0.28496313 | M87: *estimated, not available | Q87: CARGILL PARTNERSHIP PLAN
C88: BCU | D88: 19355.62 | E88: 22997 | F88: =D88-E88 -> -3641.38 | G88: =(D88-E88)/E88 -> -0.15834152 | Q88: CARGILL EMPLOYEE RETIREMENT ACCOUNT
C89: HSA | D89: =12330.52+8282.39 -> 20612.91 | E89: 15167.42 | F89: =D89-E89 -> 5445.49 | G89: =(D89-E89)/E89 -> 0.35902546
C90: Discover | D90: 5682.5 | E90: 77311.72 | F90: =D90-E90 -> -71629.22 | G90: =(D90-E90)/E90 -> -0.92649885
C91: Cargill | D91: 32232.83 | E91: 23000 | F91: =D91-E91 -> 9232.83 | G91: =(D91-E91)/E91 -> 0.40142739
C92: House | D92: =705400*0.94 -> 663076 | E92: 659128 | F92: =D92-E92 -> 3948 | G92: =(D92-E92)/E92 -> 0.0059897319
C93: Highlander | D93: =19766*0.9 -> 17789.4 | E93: 17789.4 | F93: =D93-E93 -> 0 | G93: =(D93-E93)/E93 -> 0
C94: BMW | D94: 7114 | E94: 7114 | F94: =D94-E94 -> 0 | G94: =(D94-E94)/E94 -> 0
C95: Total | D95: =SUM(D85:D94) -> 2365780.9 | E95: 2232669.1 | F95: =D95-E95 -> 133111.84 | G95: =(D95-E95)/E95 -> 0.059620048
C97: Liabilities
C98: House | D98: 358864.86 | E98: 368980.21 | F98: =D98-E98 -> -10115.35 | G98: =(D98-E98)/E98 -> -0.027414343
C99: Total | D99: =SUM(D98:D98) -> 358864.86 | E99: 368980.21 | F99: =D99-E99 -> -10115.35 | G99: =(D99-E99)/E99 -> -0.027414343
Q100: Kelly Blue Book
C101: Equity | Q101: Highlander (5TDDZRFH8HS392730): Good
C102: House | D102: =D92-D98 -> 304211.14 | E102: 290147.79 | F102: =D102-E102 -> 14063.35 | G102: =(D102-E102)/E102 -> 0.048469609 | Q102: BMW (WBAEK73454B322356): Good
C103: Car | D103: =SUM(D93:D94) -> 24903.4 | E103: 24903.4 | F103: =D103-E103 -> 0 | G103: =(D103-E103)/E103 -> 0
C104: Retirement | D104: =SUM(D86:D87) -> 1066474.9 | E104: 846393.75 | F104: =D104-E104 -> 220081.18 | G104: =(D104-E104)/E104 -> 0.26002222
C105: Investments | D105: =SUM(D85,D91) -> 565675.58 | E105: 586767.81 | F105: =D105-E105 -> -21092.23 | G105: =(D105-E105)/E105 -> -0.035946467
C106: Savings | D106: =SUM(D90,D89) -> 26295.41 | E106: 92479.14 | F106: =D106-E106 -> -66183.73 | G106: =(D106-E106)/E106 -> -0.71566118
C107: Credit Union | D107: =D88 -> 19355.62 | E107: 22997 | F107: =D107-E107 -> -3641.38 | G107: =(D107-E107)/E107 -> -0.15834152
C109: Net Worth | D109: =SUM(D102:D107) -> 2006916.1 | E109: 1863688.9 | F109: =D109-E109 -> 143227.19 | G109: =(D109-E109)/E109 -> 0.076851448
C140: Retirement
C144: Retirement Balance: | D144: ='Retire Graph'!C6 -> 1156474.9
C145: Yearly Contribution: | D145: =SUM('Main Detail'!D72:D73,'Main Detail'!D76:D77) -> 62000
C146: Total Contributions: | D146: =(D147-YEAR(C2))*D145 -> 1674000
C147: Reitrement Year: | D147: ='Retire Graph'!C3 -> 2052
C187: *Assumes continued contributions and no withdrawls until retirement year
C189: Need 25x Annual Spend
C190: Annual Spend: | D190: =Revised!P34+Revised!P36+Revised!P38 -> 184977.87
C191: 25X Spend: | D191: =D190*25 -> 4624446.8
C192: Currently Have: | D192: =D144 -> 1156474.9
C193: Current Multiplier | D193: =D192/D190 -> 6.2519637

Sheet Cash
B2: Steps:
B3: (1) Update cash postions / bonus
B4: (2) Sell stock / remove Sell Stock amount / Update cash positions
B5: (3) Change future Sell Stock values to cover all cost
B7: Kitchen Cost | C7: 189000
B10: Cash
B11: Discover | C11: 0
B12: BCU | C12: 71347 | D12: cash here but need for buffer/operating
B13: Schwab | C13: 0
C14: =SUM(C11:C13) -> 71347
B16: Cash | C16: Date
K17: 25% on signing, 25% the third week in July, 25% the second week in August and 25% at the end of August.
K19: Payment Schedule
K20: Date
B21: Sell stock | C21: Sell Stock | D21: Brit Bonus | E21: Total | F21: Pmt | K21: sign | L21: 43250 | M21: paid
B22: 45779 | C22: =IF(B22<TODAY(),0,6000) -> 0 | E22: =C14 -> 71347 | K22: 45852 | L22: 43250 | M22: paid
B23: =B22+7 -> 45786 | C23: =IF(B23<TODAY(),0,6000) -> 0 | E23: =E22+SUM(C23:D23)-F23 -> 71347 | K23: Furniture | L23: 20000
B24: =B23+7 -> 45793 | C24: =IF(B24<TODAY(),0,6000) -> 0 | E24: =E23+SUM(C24:D24)-F24 -> 71347 | K24: 45902 | L24: 43250
B25: =B24+7 -> 45800 | C25: =IF(B25<TODAY(),0,6000) -> 0 | E25: =E24+SUM(C25:D25)-F25 -> 71347 | K25: 45914 | L25: 43250
B26: =B25+7 -> 45807 | C26: =IF(B26<TODAY(),0,6000) -> 0 | E26: =E25+SUM(C26:D26)-F26 -> 71347 | K26: Italy | L26: 10000
B27: =B26+7 -> 45814 | C27: =IF(B27<TODAY(),0,6000) -> 0 | E27: =E26+SUM(C27:D27)-F27 -> 71347
B28: =B27+7 -> 45821 | C28: =IF(B28<TODAY(),0,6000) -> 0 | E28: =E27+SUM(C28:D28)-F28 -> 71347
B29: =B28+7 -> 45828 | C29: =IF(B29<TODAY(),0,6000) -> 0 | E29: =E28+SUM(C29:D29)-F29 -> 71347
B30: =B29+7 -> 45835 | E30: =E29+SUM(C30:D30)-F30 -> 71347
B31: =B30+7 -> 45842 | E31: =E30+SUM(C31:D31)-F31 -> 71347
B32: =B31+7 -> 45849 | E32: =E31+SUM(C32:D32)-F32 -> 71347
B33: =B32+7 -> 45856 | E33: =E32+SUM(C33:D33)-F33 -> 71347
B34: =B33+7 -> 45863 | E34: =E33+SUM(C34:D34)-F34 -> 71347
B35: =B34+7 -> 45870 | D35: =D17 -> 0 | E35: =E34+SUM(C35:D35)-F35 -> 71347
B36: =B35+7 -> 45877 | E36: =E35+SUM(C36:D36)-F36 -> 71347
B37: =B36+7 -> 45884 | E37: =E36+SUM(C37:D37)-F37 -> 71347
B38: =B37+7 -> 45891 | E38: =E37+SUM(C38:D38)-F38 -> 71347
B39: =B38+7 -> 45898 | E39: =E38+SUM(C39:D39)-F39 -> 71347
B40: =B39+7 -> 45905 | C40: 9000 | E40: =E39+SUM(C40:D40)-F40 -> 37097 | F40: =L24 -> 43250
B41: =B40+7 -> 45912 | C41: 9000 | E41: =E40+SUM(C41:D41)-F41 -> 26097 | F41: =L23 -> 20000
B42: =B41+7 -> 45919 | C42: 9000 | E42: =E41+SUM(C42:D42)-F42 -> 35097
B43: =B42+7 -> 45926 | C43: 9000 | E43: =E42+SUM(C43:D43)-F43 -> 847 | F43: =L25 -> 43250
B44: =B43+7 -> 45933 | C44: 9000 | E44: =E43+SUM(C44:D44)-F44 -> 9847
B45: =B44+7 -> 45940 | E45: =E44+SUM(C45:D45)-F45 -> -153 | F45: =L26 -> 10000
B46: =B45+7 -> 45947 | E46: =E45+SUM(C46:D46)-F46 -> -153

Sheet Main Detail
T4: Projection Waterfall | U4: Actual Waterfall
R5: Income | S5: Income | T5: =D42 -> 391496.07 | U5: =D51 -> 496800.83
R6: Tax | S6: Tax | T6: =-D30 -> -109618.9 | U6: =-U5*D92 -> -144072.24
R7: Expenses | S7: Expenses | T7: =-'2025 Budget'!O36 -> -254832 | U7: =-Revised!P47 -> -450777.2
R8: Savings | S8: Savings | T8: =-D69 -> -112569 | U8: =-D89 -> -117472
R9: Left Over | S9: Left Over | T9: =-SUM(T5:T8) -> 85523.83 | U9: =-SUM(U5:U8) -> 215520.61
X11: Projection | Y11: Actual
S12: Tax | T12: =-T6 -> 109618.9 | U12: =-U6 -> 144072.24 | W12: Tax | X12: =T12/$T$5 -> 0.28 | Y12: =U12/$U$5 -> 0.29
S13: Expenses | T13: =-T7 -> 254832 | U13: =-U7 -> 450777.2 | W13: Expenses | X13: =T13/$T$5 -> 0.65091841 | Y13: =U13/$U$5 -> 0.90736
S14: Savings | T14: =-T8 -> 112569 | U14: =-U8 -> 117472 | W14: Savings | X14: =T14/$T$5 -> 0.28753545 | Y14: =U14/$U$5 -> 0.23645693
S15: Left Over | T15: =-T9 -> -85523.83 | U15: =-U9 -> -215520.61 | W15: Left Over | X15: =T15/$T$5 -> -0.21845386 | Y15: =U15/$U$5 -> -0.43381693
C21: Assumptions
C27: Simple Percentages | D27: Projected | E27: Actual
C28: Income | D28: =D42 -> 391496.07 | E28: =D51 -> 496800.83
C29: Tax % | D29: 0.28 | E29: 0.28
C30: Tax $ | D30: =D28*D29 -> 109618.9 | E30: =E28*E29 -> 139104.23
C31: Savings % | D31: 0.28 | E31: 0.28
C32: Savings $ | D32: =D31*D28 -> 109618.9 | E32: =E31*E28 -> 139104.23
C33: Leftover for Spending | D33: =D28-D30-D32 -> 172258.27 | E33: =E28-E30-E32 -> 218592.37
C37: Income Projection
C38: Brit Salary | D38: 160000
C39: Brit Bonus | D39: 25000
C40: Jeff Salary | D40: 181496.07
C41: Jeff Bonus | D41: 25000
C42: Total | D42: =SUM(D38:D41) -> 391496.07
C44: Income Actual | D44: Total | E44: Jan | F44: Feb | G44: Mar | H44: Apr | I44: May | J44: Jun | K44: Jul | L44: Aug | M44: Sep | N44: Oct | O44: Nov | P44: Dec
C45: Brit Salary | D45: =SUM(E45:P45) -> 172000 | E45: =172000/12 -> 14333.333 | F45: =172000/12 -> 14333.333 | G45: =172000/12 -> 14333.333 | H45: =172000/12 -> 14333.333 | I45: =172000/12 -> 14333.333 | J45: =172000/12 -> 14333.333 | K45: =172000/12 -> 14333.333 | L45: =172000/12 -> 14333.333 | ... P45: =172000/12 -> 14333.333
C46: Brit Bonus | D46: =SUM(E46:P46) -> 50000 | L46: 50000
C47: Brit Stock | D47: =SUM(E47:P47) -> 55000 | L47: 55000
C48: Jeff Salary | D48: =SUM(E48:P48) -> 187725 | E48: =187725/12 -> 15643.75 | F48: =187725/12 -> 15643.75 | G48: =187725/12 -> 15643.75 | H48: =187725/12 -> 15643.75 | I48: =187725/12 -> 15643.75 | J48: =187725/12 -> 15643.75 | K48: =187725/12 -> 15643.75 | L48: =187725/12 -> 15643.75 | ... P48: =187725/12 -> 15643.75
C49: Jeff Bonus | D49: =SUM(E49:P49) -> 32075.83 | G49: =32075.83 -> 32075.83
C50: Inheritance | D50: =SUM(E50:P50) -> 0
C51: Total | D51: =SUM(D45:D50) -> 496800.83
C54: Savings Projection | D54: Total
C55: Brit - 401K | D55: 23500 | E55: =D55/D45 -> 0.13662791
C56: Brit - Traditional IRA | D56: 7000
C57: Brit -Brokerage | D57: 5200
C58: Jeff - 401K | D58: 23500 | E58: =D58/D48 -> 0.12518311
C59: Jeff - Traditional IRA | D59: 7000
C60: Jeff - Brokerage | D60: 14400
C61: HSA | D61: 1042
C62: Tucker College | D62: =650*12 -> 7800
C63: Cooper College | D63: =650*12 -> 7800
C64: Rainy Day
C65: Mortgage Principal | D65: 9327
C66: Mortgage Prepay / Invest
C67: I Bonds
C68: Discover | D68: 6000
C69: Total | D69: =SUM(D55:D68) -> 112569
C71: Savings Actual | D71: Total | E71: Jan | F71: Feb | G71: Mar | H71: Apr | I71: May | J71: Jun | K71: Jul | L71: Aug | M71: Sep | N71: Oct | O71: Nov | P71: Dec
C72: Brit - 401K | D72: =SUM(E72:P72) -> 23500 | E72: =23500/12 -> 1958.3333 | F72: =23500/12 -> 1958.3333 | G72: =23500/12 -> 1958.3333 | H72: =23500/12 -> 1958.3333 | I72: =23500/12 -> 1958.3333 | J72: =23500/12 -> 1958.3333 | K72: =23500/12 -> 1958.3333 | L72: =23500/12 -> 1958.3333 | ... P72: =23500/12 -> 1958.3333
C73: Brit - Traditional IRA | D73: =SUM(E73:P73) -> 7500 | E73: =7500/12 -> 625 | F73: =7500/12 -> 625 | G73: =7500/12 -> 625 | H73: =7500/12 -> 625 | I73: =7500/12 -> 625 | J73: =7500/12 -> 625 | K73: =7500/12 -> 625 | L73: =7500/12 -> 625 | ... P73: =7500/12 -> 625
C74: Brit -Brokerage | D74: =SUM(E74:P74) -> 4800 | E74: 400 | F74: 400 | G74: 400 | H74: 400 | I74: 400 | J74: 400 | K74: 400 | L74: 400 | M74: 400 | N74: 400 | O74: 400 | P74: 400
C75: Brit - Cargill Stock | D75: =SUM(E75:P75) -> 0
C76: Jeff - 401K | D76: =SUM(E76:P76) -> 23500 | E76: =23500/12 -> 1958.3333 | F76: =23500/12 -> 1958.3333 | G76: =23500/12 -> 1958.3333 | H76: =23500/12 -> 1958.3333 | I76: =23500/12 -> 1958.3333 | J76: =23500/12 -> 1958.3333 | K76: =23500/12 -> 1958.3333 | L76: =23500/12 -> 1958.3333 | ... P76: =23500/12 -> 1958.3333
C77: Jeff - Traditional IRA | D77: =SUM(E77:P77) -> 7500 | E77: =7500/12 -> 625 | F77: =7500/12 -> 625 | G77: =7500/12 -> 625 | H77: =7500/12 -> 625 | I77: =7500/12 -> 625 | J77: =7500/12 -> 625 | K77: =7500/12 -> 625 | L77: =7500/12 -> 625 | ... P77: =7500/12 -> 625
C78: Jeff - Brokerage | D78: =SUM(E78:P78) -> 7200 | E78: 600 | F78: 600 | G78: 600 | H78: 600 | I78: 600 | J78: 600 | K78: 600 | L78: 600 | M78: 600 | N78: 600 | O78: 600 | P78: 600
C79: HSA | D79: =SUM(E79:P79) -> 8300 | E79: =8300/12 -> 691.66667 | F79: =8300/12 -> 691.66667 | G79: =8300/12 -> 691.66667 | H79: =8300/12 -> 691.66667 | I79: =8300/12 -> 691.66667 | J79: =8300/12 -> 691.66667 | K79: =8300/12 -> 691.66667 | L79: =8300/12 -> 691.66667 | ... P79: =8300/12 -> 691.66667
C80: Dep Care | D80: =SUM(E80:P80) -> 0
C81: Tucker College | D81: =SUM(E81:P81) -> 7800 | E81: 650 | F81: 650 | G81: 650 | H81: 650 | I81: 650 | J81: 650 | K81: 650 | L81: 650 | M81: 650 | N81: 650 | O81: 650 | P81: 650
C82: Cooper College | D82: =SUM(E82:P82) -> 7800 | E82: 650 | F82: 650 | G82: 650 | H82: 650 | I82: 650 | J82: 650 | K82: 650 | L82: 650 | M82: 650 | N82: 650 | O82: 650 | P82: 650
C83: Rainy Day | D83: =SUM(E83:P83) -> 0
C84: Mortgage Principal | D84: =SUM(E84:P84) -> 9972 | E84: 831 | F84: 831 | G84: 831 | H84: 831 | I84: 831 | J84: 831 | K84: 831 | L84: 831 | M84: 831 | N84: 831 | O84: 831 | P84: 831
C85: Mortgage Prepay / Invest | D85: =SUM(E85:P85) -> 0
C86: I Bonds | D86: =SUM(E86:P86) -> 0
C87: Discover | D87: =SUM(E87:P87) -> 9600 | E87: 800 | F87: 800 | G87: 800 | H87: 800 | I87: 800 | J87: 800 | K87: 800 | L87: 800 | M87: 800 | N87: 800 | O87: 800 | P87: 800
C88: Car Saving | D88: =SUM(E88:P88) -> 0
C89: Total | D89: =SUM(D72:D88) -> 117472 | E89: =SUM(E72:E88) -> 9789.3333 | F89: =SUM(F72:F88) -> 9789.3333 | G89: =SUM(G72:G88) -> 9789.3333 | H89: =SUM(H72:H88) -> 9789.3333 | I89: =SUM(I72:I88) -> 9789.3333 | J89: =SUM(J72:J88) -> 9789.3333 | K89: =SUM(K72:K88) -> 9789.3333 | ... P89: =SUM(P72:P88) -> 9789.3333
C91: Total Tax Rate
C92: Tax % | D92: 0.29
C93: Tax $ | D93: =D92*D42 -> 113533.86
C94: Fed on Gross % | D94: =D106 -> 0.16547286
C95: State on Gross % | D95: =D113 -> 0.058037839
C96: SS on Gross % | D96: =D119 -> 0.056364632
C97: Medicare on Gross % | D97: =D120 -> 0.01406823
C98: Total | D98: =SUM(D94:D97) -> 0.29394356
C101: Prev Year Fed Tax
C102: Total Income | D102: =Tax!E153 -> 369879.38
C103: Taxable Income | D103: 302463
C104: Tax Paid | D104: 61205
C105: Tax % on Taxable | D105: =D104/D103 -> 0.20235533
C106: Tax % on Gross | D106: =D104/D102 -> 0.16547286
C108: Prev Year State Tax
C109: Total Income | D109: =Tax!E153 -> 369879.38
C110: Taxable Income | D110: 296741
C111: Tax Paid | D111: 21467
C112: Tax % on Taxable | D112: =D111/D110 -> 0.072342548
C113: Tax % on Gross | D113: =D111/D109 -> 0.058037839
C115: Other Tax | D115: Britney | F115: Jeff
C116: YTD Pay | D116: 169499.63 | F116: =86747.28+28333.32 -> 115080.6
C117: Social Security | D117: 9114 | E117: =D117/D116 -> 0.053770029 | F117: =5223.33+1702.93 -> 6926.26 | G117: =F117/F116 -> 0.060186165
C118: Medicare | D118: 2383.68 | E118: =D118/D116 -> 0.01406304 | F118: =1221.59+398.27 -> 1619.86 | G118: =F118/F116 -> 0.014075874
C119: Total SS % | D119: =SUM(D117,F117)/SUM(D116,F116) -> 0.056364632
C120: Total Medicare % | D120: =SUM(D118,F118)/SUM(D116,F116) -> 0.01406823

Sheet 1 MO
B1: Yrmo | C1: 202512
C2: =DATE(LEFT(C1,4),RIGHT(C1,2),1) -> 45992
B3: Year | C3: =LEFT(C1,4) -> 2025
B9: =TEXT(C2,"MMMM YYYY") -> December 2025 | C9: Actual | D9: Budget | E9: Over/(Under)
B11: Rent | C11: =SUMIFS(Actuals!E:E,Actuals!A:A,'1 MO'!$C$1,Actuals!$F:$F,'1 MO'!B11) -> 3378.51 | D11: =INDEX('2025 Budget'!$B$3:$N$36,MATCH('1 MO'!B11,'2025 Budget'!$B$3:$B$36,0),MATCH('1 MO'!$C$1,'2025 Budget'!$B$3:$N$3,0)) -> 2745 | E11: =C11-D11 -> 633.51
B12: House Maintenance | C12: =SUMIFS(Actuals!E:E,Actuals!A:A,'1 MO'!$C$1,Actuals!$F:$F,'1 MO'!B12) -> 32.64 | D12: =INDEX('2025 Budget'!$B$3:$N$36,MATCH('1 MO'!B12,'2025 Budget'!$B$3:$B$36,0),MATCH('1 MO'!$C$1,'2025 Budget'!$B$3:$N$3,0)) -> 350 | E12: =C12-D12 -> -317.36
B13: Utilities | C13: =SUMIFS(Actuals!E:E,Actuals!A:A,'1 MO'!$C$1,Actuals!$F:$F,'1 MO'!B13) -> 1190.87 | D13: =INDEX('2025 Budget'!$B$3:$N$36,MATCH('1 MO'!B13,'2025 Budget'!$B$3:$B$36,0),MATCH('1 MO'!$C$1,'2025 Budget'!$B$3:$N$3,0)) -> 700 | E13: =C13-D13 -> 490.87
B14: Car Loan | C14: =SUMIFS(Actuals!E:E,Actuals!A:A,'1 MO'!$C$1,Actuals!$F:$F,'1 MO'!B14) -> 0 | D14: =INDEX('2025 Budget'!$B$3:$N$36,MATCH('1 MO'!B14,'2025 Budget'!$B$3:$B$36,0),MATCH('1 MO'!$C$1,'2025 Budget'!$B$3:$N$3,0)) -> 0 | E14: =C14-D14 -> 0
B15: Cleaning | C15: =SUMIFS(Actuals!E:E,Actuals!A:A,'1 MO'!$C$1,Actuals!$F:$F,'1 MO'!B15) -> 0 | D15: =INDEX('2025 Budget'!$B$3:$N$36,MATCH('1 MO'!B15,'2025 Budget'!$B$3:$B$36,0),MATCH('1 MO'!$C$1,'2025 Budget'!$B$3:$N$3,0)) -> 250 | E15: =C15-D15 -> -250
B16: Insurance | C16: =SUMIFS(Actuals!E:E,Actuals!A:A,'1 MO'!$C$1,Actuals!$F:$F,'1 MO'!B16) -> 0 | D16: =INDEX('2025 Budget'!$B$3:$N$36,MATCH('1 MO'!B16,'2025 Budget'!$B$3:$B$36,0),MATCH('1 MO'!$C$1,'2025 Budget'!$B$3:$N$3,0)) -> 135 | E16: =C16-D16 -> -135
B17: Day Care | C17: =SUMIFS(Actuals!E:E,Actuals!A:A,'1 MO'!$C$1,Actuals!$F:$F,'1 MO'!B17) -> 495 | D17: =INDEX('2025 Budget'!$B$3:$N$36,MATCH('1 MO'!B17,'2025 Budget'!$B$3:$B$36,0),MATCH('1 MO'!$C$1,'2025 Budget'!$B$3:$N$3,0)) -> 2275 | E17: =C17-D17 -> -1780
B18: Total Rent & Utilitites | C18: =SUM(C11:C17) -> 5097.02 | D18: =SUM(D11:D17) -> 6455 | E18: =C18-D18 -> -1357.98
B20: Transportation | C20: =SUMIFS(Actuals!E:E,Actuals!A:A,'1 MO'!$C$1,Actuals!$F:$F,'1 MO'!B20) -> 225.45 | D20: =INDEX('2025 Budget'!$B$3:$N$36,MATCH('1 MO'!B20,'2025 Budget'!$B$3:$B$36,0),MATCH('1 MO'!$C$1,'2025 Budget'!$B$3:$N$3,0)) -> 400 | E20: =C20-D20 -> -174.55
B21: Restaurants | C21: =SUMIFS(Actuals!E:E,Actuals!A:A,'1 MO'!$C$1,Actuals!$F:$F,'1 MO'!B21) -> 1564.61 | D21: =INDEX('2025 Budget'!$B$3:$N$36,MATCH('1 MO'!B21,'2025 Budget'!$B$3:$B$36,0),MATCH('1 MO'!$C$1,'2025 Budget'!$B$3:$N$3,0)) -> 1300 | E21: =C21-D21 -> 264.61
B22: Groceries | C22: =SUMIFS(Actuals!E:E,Actuals!A:A,'1 MO'!$C$1,Actuals!$F:$F,'1 MO'!B22) -> 1139.06 | D22: =INDEX('2025 Budget'!$B$3:$N$36,MATCH('1 MO'!B22,'2025 Budget'!$B$3:$B$36,0),MATCH('1 MO'!$C$1,'2025 Budget'!$B$3:$N$3,0)) -> 1000 | E22: =C22-D22 -> 139.06
B23: Target | C23: =SUMIFS(Actuals!E:E,Actuals!A:A,'1 MO'!$C$1,Actuals!$F:$F,'1 MO'!B23) -> 818.16 | D23: =INDEX('2025 Budget'!$B$3:$N$36,MATCH('1 MO'!B23,'2025 Budget'!$B$3:$B$36,0),MATCH('1 MO'!$C$1,'2025 Budget'!$B$3:$N$3,0)) -> 675 | E23: =C23-D23 -> 143.16
B24: Total Food & Car | C24: =SUM(C20:C23) -> 3747.28 | D24: =SUM(D20:D23) -> 3375 | E24: =SUM(E20:E23) -> 372.28
B26: Gym | C26: =SUMIFS(Actuals!E:E,Actuals!A:A,'1 MO'!$C$1,Actuals!$F:$F,'1 MO'!B26) -> 0 | D26: =INDEX('2025 Budget'!$B$3:$N$36,MATCH('1 MO'!B26,'2025 Budget'!$B$3:$B$36,0),MATCH('1 MO'!$C$1,'2025 Budget'!$B$3:$N$3,0)) -> 0 | E26: =C26-D26 -> 0
B27: Shopping | C27: =SUMIFS(Actuals!E:E,Actuals!A:A,'1 MO'!$C$1,Actuals!$F:$F,'1 MO'!B27) -> 1902.83 | D27: =INDEX('2025 Budget'!$B$3:$N$36,MATCH('1 MO'!B27,'2025 Budget'!$B$3:$B$36,0),MATCH('1 MO'!$C$1,'2025 Budget'!$B$3:$N$3,0)) -> 2000 | E27: =C27-D27 -> -97.17
B28: Amazon | C28: =SUMIFS(Actuals!E:E,Actuals!A:A,'1 MO'!$C$1,Actuals!$F:$F,'1 MO'!B28) -> 1212.46 | D28: =INDEX('2025 Budget'!$B$3:$N$36,MATCH('1 MO'!B28,'2025 Budget'!$B$3:$B$36,0),MATCH('1 MO'!$C$1,'2025 Budget'!$B$3:$N$3,0)) -> 580 | E28: =C28-D28 -> 632.46
B29: Entertainment | C29: =SUMIFS(Actuals!E:E,Actuals!A:A,'1 MO'!$C$1,Actuals!$F:$F,'1 MO'!B29) -> 278.84 | D29: =INDEX('2025 Budget'!$B$3:$N$36,MATCH('1 MO'!B29,'2025 Budget'!$B$3:$B$36,0),MATCH('1 MO'!$C$1,'2025 Budget'!$B$3:$N$3,0)) -> 550 | E29: =C29-D29 -> -271.16
B30: Dry Cleaning | C30: =SUMIFS(Actuals!E:E,Actuals!A:A,'1 MO'!$C$1,Actuals!$F:$F,'1 MO'!B30) -> 0 | D30: =INDEX('2025 Budget'!$B$3:$N$36,MATCH('1 MO'!B30,'2025 Budget'!$B$3:$B$36,0),MATCH('1 MO'!$C$1,'2025 Budget'!$B$3:$N$3,0)) -> 45 | E30: =C30-D30 -> -45
B31: Gifts | C31: =SUMIFS(Actuals!E:E,Actuals!A:A,'1 MO'!$C$1,Actuals!$F:$F,'1 MO'!B31) -> 282.75 | D31: =INDEX('2025 Budget'!$B$3:$N$36,MATCH('1 MO'!B31,'2025 Budget'!$B$3:$B$36,0),MATCH('1 MO'!$C$1,'2025 Budget'!$B$3:$N$3,0)) -> 100 | E31: =C31-D31 -> 182.75
B32: Misc | C32: =SUMIFS(Actuals!E:E,Actuals!A:A,'1 MO'!$C$1,Actuals!$F:$F,'1 MO'!B32) -> 8.15 | D32: =INDEX('2025 Budget'!$B$3:$N$36,MATCH('1 MO'!B32,'2025 Budget'!$B$3:$B$36,0),MATCH('1 MO'!$C$1,'2025 Budget'!$B$3:$N$3,0)) -> 45 | E32: =C32-D32 -> -36.85
B33: Total Other | C33: =SUM(C26:C32) -> 3685.03 | D33: =SUM(D26:D32) -> 3320 | E33: =C33-D33 -> 365.03
B35: Total | C35: =SUM(C33,C24,C18) -> 12529.33 | D35: =SUM(D33,D24,D18) -> 13150 | E35: =C35-D35 -> -620.67
B37: Healthcare | C37: =SUMIFS(Actuals!E:E,Actuals!A:A,'1 MO'!$C$1,Actuals!$F:$F,'1 MO'!B37) -> 1285.7
B38: House | C38: =SUMIFS(Actuals!E:E,Actuals!A:A,'1 MO'!$C$1,Actuals!$F:$F,'1 MO'!B38) -> 0
B39: Travel | C39: =SUMIFS(Actuals!E:E,Actuals!A:A,'1 MO'!$C$1,Actuals!$F:$F,'1 MO'!B39) -> 1788.34
B40: Total | C40: =SUM(C37:C39) -> 3074.04
B42: Total Spend | C42: =SUM(C40,C35) -> 15603.37

Sheet YTD
B1: Yrmo | C1: ='1 MO'!C1 -> 202512 | G1: =LEFT(C1,4)-1&RIGHT(C1,2) -> 202412
C2: =DATE(LEFT(C1,4),RIGHT(C1,2),1) -> 45992
B3: Jan | C3: =LEFT(C1,4)&"01" -> 202501 | G3: =LEFT(C3,4)-1&RIGHT(C3,2) -> 202401
B5: ="YTD "&TEXT(C2,"MMMM YYYY") -> YTD December 2025 | C5: Actual | D5: Budget | E5: Over/(Under) | G5: Prev Year | H5: Over/(Under)
B7: Rent | C7: =SUMIFS(Actuals!E:E,Actuals!A:A,"<="&YTD!$C$1,Actuals!A:A,">="&YTD!$C$3,Actuals!$F:$F,YTD!B7) -> 34502.09 | D7: =SUMIFS('2025 Budget'!S:S,'2025 Budget'!Q:Q,YTD!B7,'2025 Budget'!R:R,"<="&YTD!$C$1,'2025 Budget'!R:R,">="&YTD!$C$3) -> 32940 | E7: =C7-D7 -> 1562.09 | G7: =SUMIFS(Actuals!E:E,Actuals!A:A,"<="&YTD!$G$1,Actuals!A:A,">="&YTD!$G$3,Actuals!$F:$F,YTD!B7) -> 32915.64 | H7: =C7-G7 -> 1586.45
B8: House Maintenance | C8: =SUMIFS(Actuals!E:E,Actuals!A:A,"<="&YTD!$C$1,Actuals!A:A,">="&YTD!$C$3,Actuals!$F:$F,YTD!B8) -> 4152.49 | D8: =SUMIFS('2025 Budget'!S:S,'2025 Budget'!Q:Q,YTD!B8,'2025 Budget'!R:R,"<="&YTD!$C$1,'2025 Budget'!R:R,">="&YTD!$C$3) -> 4200 | E8: =C8-D8 -> -47.51 | G8: =SUMIFS(Actuals!E:E,Actuals!A:A,"<="&YTD!$G$1,Actuals!A:A,">="&YTD!$G$3,Actuals!$F:$F,YTD!B8) -> 4195.69 | H8: =C8-G8 -> -43.2
B9: Utilities | C9: =SUMIFS(Actuals!E:E,Actuals!A:A,"<="&YTD!$C$1,Actuals!A:A,">="&YTD!$C$3,Actuals!$F:$F,YTD!B9) -> 20671.47 | D9: =SUMIFS('2025 Budget'!S:S,'2025 Budget'!Q:Q,YTD!B9,'2025 Budget'!R:R,"<="&YTD!$C$1,'2025 Budget'!R:R,">="&YTD!$C$3) -> 8400 | E9: =C9-D9 -> 12271.47 | G9: =SUMIFS(Actuals!E:E,Actuals!A:A,"<="&YTD!$G$1,Actuals!A:A,">="&YTD!$G$3,Actuals!$F:$F,YTD!B9) -> 8490 | H9: =C9-G9 -> 12181.47
B10: Car Loan | C10: =SUMIFS(Actuals!E:E,Actuals!A:A,"<="&YTD!$C$1,Actuals!A:A,">="&YTD!$C$3,Actuals!$F:$F,YTD!B10) -> 0 | D10: =SUMIFS('2025 Budget'!S:S,'2025 Budget'!Q:Q,YTD!B10,'2025 Budget'!R:R,"<="&YTD!$C$1,'2025 Budget'!R:R,">="&YTD!$C$3) -> 0 | E10: =C10-D10 -> 0 | G10: =SUMIFS(Actuals!E:E,Actuals!A:A,"<="&YTD!$G$1,Actuals!A:A,">="&YTD!$G$3,Actuals!$F:$F,YTD!B10) -> 0 | H10: =C10-G10 -> 0
B11: Cleaning | C11: =SUMIFS(Actuals!E:E,Actuals!A:A,"<="&YTD!$C$1,Actuals!A:A,">="&YTD!$C$3,Actuals!$F:$F,YTD!B11) -> 241.71 | D11: =SUMIFS('2025 Budget'!S:S,'2025 Budget'!Q:Q,YTD!B11,'2025 Budget'!R:R,"<="&YTD!$C$1,'2025 Budget'!R:R,">="&YTD!$C$3) -> 3000 | E11: =C11-D11 -> -2758.29 | G11: =SUMIFS(Actuals!E:E,Actuals!A:A,"<="&YTD!$G$1,Actuals!A:A,">="&YTD!$G$3,Actuals!$F:$F,YTD!B11) -> 3000 | H11: =C11-G11 -> -2758.29
B12: Insurance | C12: =SUMIFS(Actuals!E:E,Actuals!A:A,"<="&YTD!$C$1,Actuals!A:A,">="&YTD!$C$3,Actuals!$F:$F,YTD!B12) -> 1089.47 | D12: =SUMIFS('2025 Budget'!S:S,'2025 Budget'!Q:Q,YTD!B12,'2025 Budget'!R:R,"<="&YTD!$C$1,'2025 Budget'!R:R,">="&YTD!$C$3) -> 1620 | E12: =C12-D12 -> -530.53 | G12: =SUMIFS(Actuals!E:E,Actuals!A:A,"<="&YTD!$G$1,Actuals!A:A,">="&YTD!$G$3,Actuals!$F:$F,YTD!B12) -> 1631.65 | H12: =C12-G12 -> -542.18
B13: Day Care | C13: =SUMIFS(Actuals!E:E,Actuals!A:A,"<="&YTD!$C$1,Actuals!A:A,">="&YTD!$C$3,Actuals!$F:$F,YTD!B13) -> 23875.18 | D13: =SUMIFS('2025 Budget'!S:S,'2025 Budget'!Q:Q,YTD!B13,'2025 Budget'!R:R,"<="&YTD!$C$1,'2025 Budget'!R:R,">="&YTD!$C$3) -> 27300 | E13: =C13-D13 -> -3424.82 | G13: =SUMIFS(Actuals!E:E,Actuals!A:A,"<="&YTD!$G$1,Actuals!A:A,">="&YTD!$G$3,Actuals!$F:$F,YTD!B13) -> 27362.99 | H13: =C13-G13 -> -3487.81
B14: Total Rent & Utilitites | C14: =SUM(C7:C13) -> 84532.41 | D14: =SUM(D7:D13) -> 77460 | E14: =C14-D14 -> 7072.41 | G14: =SUM(G7:G13) -> 77595.97 | H14: =C14-G14 -> 6936.44
B16: Transportation | C16: =SUMIFS(Actuals!E:E,Actuals!A:A,"<="&YTD!$C$1,Actuals!A:A,">="&YTD!$C$3,Actuals!$F:$F,YTD!B16) -> 4745.25 | D16: =SUMIFS('2025 Budget'!S:S,'2025 Budget'!Q:Q,YTD!B16,'2025 Budget'!R:R,"<="&YTD!$C$1,'2025 Budget'!R:R,">="&YTD!$C$3) -> 4800 | E16: =C16-D16 -> -54.75 | G16: =SUMIFS(Actuals!E:E,Actuals!A:A,"<="&YTD!$G$1,Actuals!A:A,">="&YTD!$G$3,Actuals!$F:$F,YTD!B16) -> 4295.84 | H16: =C16-G16 -> 449.41
B17: Restaurants | C17: =SUMIFS(Actuals!E:E,Actuals!A:A,"<="&YTD!$C$1,Actuals!A:A,">="&YTD!$C$3,Actuals!$F:$F,YTD!B17) -> 23100.66 | D17: =SUMIFS('2025 Budget'!S:S,'2025 Budget'!Q:Q,YTD!B17,'2025 Budget'!R:R,"<="&YTD!$C$1,'2025 Budget'!R:R,">="&YTD!$C$3) -> 15600 | E17: =C17-D17 -> 7500.66 | G17: =SUMIFS(Actuals!E:E,Actuals!A:A,"<="&YTD!$G$1,Actuals!A:A,">="&YTD!$G$3,Actuals!$F:$F,YTD!B17) -> 16610.65 | H17: =C17-G17 -> 6490.01
B18: Groceries | C18: =SUMIFS(Actuals!E:E,Actuals!A:A,"<="&YTD!$C$1,Actuals!A:A,">="&YTD!$C$3,Actuals!$F:$F,YTD!B18) -> 11355.96 | D18: =SUMIFS('2025 Budget'!S:S,'2025 Budget'!Q:Q,YTD!B18,'2025 Budget'!R:R,"<="&YTD!$C$1,'2025 Budget'!R:R,">="&YTD!$C$3) -> 12000 | E18: =C18-D18 -> -644.04 | G18: =SUMIFS(Actuals!E:E,Actuals!A:A,"<="&YTD!$G$1,Actuals!A:A,">="&YTD!$G$3,Actuals!$F:$F,YTD!B18) -> 11506.02 | H18: =C18-G18 -> -150.06
B19: Target | C19: =SUMIFS(Actuals!E:E,Actuals!A:A,"<="&YTD!$C$1,Actuals!A:A,">="&YTD!$C$3,Actuals!$F:$F,YTD!B19) -> 8438.87 | D19: =SUMIFS('2025 Budget'!S:S,'2025 Budget'!Q:Q,YTD!B19,'2025 Budget'!R:R,"<="&YTD!$C$1,'2025 Budget'!R:R,">="&YTD!$C$3) -> 8100 | E19: =C19-D19 -> 338.87 | G19: =SUMIFS(Actuals!E:E,Actuals!A:A,"<="&YTD!$G$1,Actuals!A:A,">="&YTD!$G$3,Actuals!$F:$F,YTD!B19) -> 8093.31 | H19: =C19-G19 -> 345.56
B20: Total Food & Car | C20: =SUM(C16:C19) -> 47640.74 | D20: =SUM(D16:D19) -> 40500 | E20: =SUM(E16:E19) -> 7140.74 | G20: =SUM(G16:G19) -> 40505.82 | H20: =C20-G20 -> 7134.92
B22: Gym | C22: =SUMIFS(Actuals!E:E,Actuals!A:A,"<="&YTD!$C$1,Actuals!A:A,">="&YTD!$C$3,Actuals!$F:$F,YTD!B22) -> 25 | D22: =SUMIFS('2025 Budget'!S:S,'2025 Budget'!Q:Q,YTD!B22,'2025 Budget'!R:R,"<="&YTD!$C$1,'2025 Budget'!R:R,">="&YTD!$C$3) -> 0 | E22: =C22-D22 -> 25 | G22: =SUMIFS(Actuals!E:E,Actuals!A:A,"<="&YTD!$G$1,Actuals!A:A,">="&YTD!$G$3,Actuals!$F:$F,YTD!B22) -> 381.52 | H22: =C22-G22 -> -356.52
B23: Shopping | C23: =SUMIFS(Actuals!E:E,Actuals!A:A,"<="&YTD!$C$1,Actuals!A:A,">="&YTD!$C$3,Actuals!$F:$F,YTD!B23) -> 21636.39 | D23: =SUMIFS('2025 Budget'!S:S,'2025 Budget'!Q:Q,YTD!B23,'2025 Budget'!R:R,"<="&YTD!$C$1,'2025 Budget'!R:R,">="&YTD!$C$3) -> 24000 | E23: =C23-D23 -> -2363.61 | G23: =SUMIFS(Actuals!E:E,Actuals!A:A,"<="&YTD!$G$1,Actuals!A:A,">="&YTD!$G$3,Actuals!$F:$F,YTD!B23) -> 24464.17 | H23: =C23-G23 -> -2827.78
B24: Amazon | C24: =SUMIFS(Actuals!E:E,Actuals!A:A,"<="&YTD!$C$1,Actuals!A:A,">="&YTD!$C$3,Actuals!$F:$F,YTD!B24) -> 5621.16 | D24: =SUMIFS('2025 Budget'!S:S,'2025 Budget'!Q:Q,YTD!B24,'2025 Budget'!R:R,"<="&YTD!$C$1,'2025 Budget'!R:R,">="&YTD!$C$3) -> 6960 | E24: =C24-D24 -> -1338.84 | G24: =SUMIFS(Actuals!E:E,Actuals!A:A,"<="&YTD!$G$1,Actuals!A:A,">="&YTD!$G$3,Actuals!$F:$F,YTD!B24) -> 7001.74 | H24: =C24-G24 -> -1380.58
B25: Entertainment | C25: =SUMIFS(Actuals!E:E,Actuals!A:A,"<="&YTD!$C$1,Actuals!A:A,">="&YTD!$C$3,Actuals!$F:$F,YTD!B25) -> 3681.42 | D25: =SUMIFS('2025 Budget'!S:S,'2025 Budget'!Q:Q,YTD!B25,'2025 Budget'!R:R,"<="&YTD!$C$1,'2025 Budget'!R:R,">="&YTD!$C$3) -> 6600 | E25: =C25-D25 -> -2918.58 | G25: =SUMIFS(Actuals!E:E,Actuals!A:A,"<="&YTD!$G$1,Actuals!A:A,">="&YTD!$G$3,Actuals!$F:$F,YTD!B25) -> 7135.13 | H25: =C25-G25 -> -3453.71
B26: Dry Cleaning | C26: =SUMIFS(Actuals!E:E,Actuals!A:A,"<="&YTD!$C$1,Actuals!A:A,">="&YTD!$C$3,Actuals!$F:$F,YTD!B26) -> 406.58 | D26: =SUMIFS('2025 Budget'!S:S,'2025 Budget'!Q:Q,YTD!B26,'2025 Budget'!R:R,"<="&YTD!$C$1,'2025 Budget'!R:R,">="&YTD!$C$3) -> 540 | E26: =C26-D26 -> -133.42 | G26: =SUMIFS(Actuals!E:E,Actuals!A:A,"<="&YTD!$G$1,Actuals!A:A,">="&YTD!$G$3,Actuals!$F:$F,YTD!B26) -> 537.86 | H26: =C26-G26 -> -131.28
B27: Gifts | C27: =SUMIFS(Actuals!E:E,Actuals!A:A,"<="&YTD!$C$1,Actuals!A:A,">="&YTD!$C$3,Actuals!$F:$F,YTD!B27) -> 594.78 | D27: =SUMIFS('2025 Budget'!S:S,'2025 Budget'!Q:Q,YTD!B27,'2025 Budget'!R:R,"<="&YTD!$C$1,'2025 Budget'!R:R,">="&YTD!$C$3) -> 1200 | E27: =C27-D27 -> -605.22 | G27: =SUMIFS(Actuals!E:E,Actuals!A:A,"<="&YTD!$G$1,Actuals!A:A,">="&YTD!$G$3,Actuals!$F:$F,YTD!B27) -> 780.65 | H27: =C27-G27 -> -185.87
B28: Misc | C28: =SUMIFS(Actuals!E:E,Actuals!A:A,"<="&YTD!$C$1,Actuals!A:A,">="&YTD!$C$3,Actuals!$F:$F,YTD!B28) -> 421.02 | D28: =SUMIFS('2025 Budget'!S:S,'2025 Budget'!Q:Q,YTD!B28,'2025 Budget'!R:R,"<="&YTD!$C$1,'2025 Budget'!R:R,">="&YTD!$C$3) -> 540 | E28: =C28-D28 -> -118.98 | G28: =SUMIFS(Actuals!E:E,Actuals!A:A,"<="&YTD!$G$1,Actuals!A:A,">="&YTD!$G$3,Actuals!$F:$F,YTD!B28) -> 527.85 | H28: =C28-G28 -> -106.83
B29: Total Other | C29: =SUM(C22:C28) -> 32386.35 | D29: =SUM(D22:D28) -> 39840 | E29: =C29-D29 -> -7453.65 | G29: =SUM(G22:G28) -> 40828.92 | H29: =C29-G29 -> -8442.57
B31: Total | C31: =SUM(C29,C20,C14) -> 164559.5 | D31: =SUM(D29,D20,D14) -> 157800 | E31: =C31-D31 -> 6759.5 | G31: =SUM(G29,G20,G14) -> 158930.71 | H31: =C31-G31 -> 5628.79
B33: Healthcare | C33: =SUMIFS(Actuals!E:E,Actuals!A:A,"<="&YTD!$C$1,Actuals!A:A,">="&YTD!$C$3,Actuals!$F:$F,YTD!B33) -> 3948.01 | G33: =SUMIFS(Actuals!E:E,Actuals!A:A,"<="&YTD!$G$1,Actuals!A:A,">="&YTD!$G$3,Actuals!$F:$F,YTD!B33) -> 2527.44 | H33: =C33-G33 -> 1420.57
B34: House | C34: =SUMIFS(Actuals!E:E,Actuals!A:A,"<="&YTD!$C$1,Actuals!A:A,">="&YTD!$C$3,Actuals!$F:$F,YTD!B34) -> 265799.33 | G34: =SUMIFS(Actuals!E:E,Actuals!A:A,"<="&YTD!$G$1,Actuals!A:A,">="&YTD!$G$3,Actuals!$F:$F,YTD!B34) -> 11572.24 | H34: =C34-G34 -> 254227.09
B35: Travel | C35: =SUMIFS(Actuals!E:E,Actuals!A:A,"<="&YTD!$C$1,Actuals!A:A,">="&YTD!$C$3,Actuals!$F:$F,YTD!B35) -> 16470.36 | G35: =SUMIFS(Actuals!E:E,Actuals!A:A,"<="&YTD!$G$1,Actuals!A:A,">="&YTD!$G$3,Actuals!$F:$F,YTD!B35) -> 18097.97 | H35: =C35-G35 -> -1627.61
B36: Total | C36: =SUM(C33:C35) -> 286217.7 | G36: =SUM(G33:G35) -> 32197.65 | H36: =C36-G36 -> 254020.05
G37: =SUMIFS(Actuals!E:E,Actuals!A:A,"<="&YTD!$G$1,Actuals!A:A,">="&YTD!$G$3,Actuals!$F:$F,YTD!B37) -> 0 | H37: =C37-G37 -> 0
B38: Total Spend | C38: =SUM(C36,C31) -> 450777.2 | G38: =SUM(G36,G31) -> 191128.36 | H38: =C38-G38 -> 259648.84

Sheet 2025 Budget
B1: Values here pull into the monthy reporting for actual vs budget reporting
B3: Budget | C3: 202501 | D3: 202502 | E3: 202503 | F3: 202504 | G3: 202505 | H3: 202506 | I3: 202507 | J3: 202508 | K3: 202509 | L3: 202510 | M3: 202511 | N3: 202512 | O3: Total
B5: Rent | C5: 2745 | D5: 2745 | E5: 2745 | F5: 2745 | G5: 2745 | H5: 2745 | I5: 2745 | J5: 2745 | K5: 2745 | L5: 2745 | M5: 2745 | N5: 2745 | O5: =SUM(C5:N5) -> 32940 | Q5: Rent | R5: =$C$3 -> 202501 | S5: =INDEX($B$3:$O$36,MATCH(Q5,$B$3:$B$36,0),MATCH(R5,$B$3:$O$3,0)) -> 2745
B6: House Maintenance | C6: 350 | D6: 350 | E6: 350 | F6: 350 | G6: 350 | H6: 350 | I6: 350 | J6: 350 | K6: 350 | L6: 350 | M6: 350 | N6: 350 | O6: =SUM(C6:N6) -> 4200 | Q6: House Maintenance | R6: =$C$3 -> 202501 | S6: =INDEX($B$3:$O$36,MATCH(Q6,$B$3:$B$36,0),MATCH(R6,$B$3:$O$3,0)) -> 350
B7: Utilities | C7: 700 | D7: 700 | E7: 700 | F7: 700 | G7: 700 | H7: 700 | I7: 700 | J7: 700 | K7: 700 | L7: 700 | M7: 700 | N7: 700 | O7: =SUM(C7:N7) -> 8400 | Q7: Utilities | R7: =$C$3 -> 202501 | S7: =INDEX($B$3:$O$36,MATCH(Q7,$B$3:$B$36,0),MATCH(R7,$B$3:$O$3,0)) -> 700
B8: Car Loan | O8: =SUM(C8:N8) -> 0 | Q8: Car Loan | R8: =$C$3 -> 202501 | S8: =INDEX($B$3:$O$36,MATCH(Q8,$B$3:$B$36,0),MATCH(R8,$B$3:$O$3,0)) -> 0
B9: Cleaning | C9: =125*2 -> 250 | D9: =125*2 -> 250 | E9: =125*2 -> 250 | F9: =125*2 -> 250 | G9: =125*2 -> 250 | H9: =125*2 -> 250 | I9: =125*2 -> 250 | J9: =125*2 -> 250 | ... N9: =125*2 -> 250 | O9: =SUM(C9:N9) -> 3000 | Q9: Cleaning | R9: =$C$3 -> 202501 | S9: =INDEX($B$3:$O$36,MATCH(Q9,$B$3:$B$36,0),MATCH(R9,$B$3:$O$3,0)) -> 250
B10: Insurance | C10: 135 | D10: 135 | E10: 135 | F10: 135 | G10: 135 | H10: 135 | I10: 135 | J10: 135 | K10: 135 | L10: 135 | M10: 135 | N10: 135 | O10: =SUM(C10:N10) -> 1620 | Q10: Insurance | R10: =$C$3 -> 202501 | S10: =INDEX($B$3:$O$36,MATCH(Q10,$B$3:$B$36,0),MATCH(R10,$B$3:$O$3,0)) -> 135
B11: Day Care | C11: 2275 | D11: 2275 | E11: 2275 | F11: 2275 | G11: 2275 | H11: 2275 | I11: 2275 | J11: 2275 | K11: 2275 | L11: 2275 | M11: 2275 | N11: 2275 | O11: =SUM(C11:N11) -> 27300 | Q11: Day Care | R11: =$C$3 -> 202501 | S11: =INDEX($B$3:$O$36,MATCH(Q11,$B$3:$B$36,0),MATCH(R11,$B$3:$O$3,0)) -> 2275
B12: Total Rent & Utilitites | C12: =SUM(C5:C11) -> 6455 | D12: =SUM(D5:D11) -> 6455 | E12: =SUM(E5:E11) -> 6455 | F12: =SUM(F5:F11) -> 6455 | G12: =SUM(G5:G11) -> 6455 | H12: =SUM(H5:H11) -> 6455 | I12: =SUM(I5:I11) -> 6455 | J12: =SUM(J5:J11) -> 6455 | ... N12: =SUM(N5:N11) -> 6455 | O12: =SUM(C12:N12) -> 77460 | Q12: Total Rent & Utilitites | R12: =$C$3 -> 202501 | S12: =INDEX($B$3:$O$36,MATCH(Q12,$B$3:$B$36,0),MATCH(R12,$B$3:$O$3,0)) -> 6455
R13: =$C$3 -> 202501 | S13: =INDEX($B$3:$O$36,MATCH(Q13,$B$3:$B$36,0),MATCH(R13,$B$3:$O$3,0)) -> #N/A
B14: Transportation | C14: 400 | D14: 400 | E14: 400 | F14: 400 | G14: 400 | H14: 400 | I14: 400 | J14: 400 | K14: 400 | L14: 400 | M14: 400 | N14: 400 | O14: =SUM(C14:N14) -> 4800 | Q14: Transportation | R14: =$C$3 -> 202501 | S14: =INDEX($B$3:$O$36,MATCH(Q14,$B$3:$B$36,0),MATCH(R14,$B$3:$O$3,0)) -> 400
B15: Restaurants | C15: 1300 | D15: 1300 | E15: 1300 | F15: 1300 | G15: 1300 | H15: 1300 | I15: 1300 | J15: 1300 | K15: 1300 | L15: 1300 | M15: 1300 | N15: 1300 | O15: =SUM(C15:N15) -> 15600 | Q15: Restaurants | R15: =$C$3 -> 202501 | S15: =INDEX($B$3:$O$36,MATCH(Q15,$B$3:$B$36,0),MATCH(R15,$B$3:$O$3,0)) -> 1300
B16: Groceries | C16: 1000 | D16: 1000 | E16: 1000 | F16: 1000 | G16: 1000 | H16: 1000 | I16: 1000 | J16: 1000 | K16: 1000 | L16: 1000 | M16: 1000 | N16: 1000 | O16: =SUM(C16:N16) -> 12000 | Q16: Groceries | R16: =$C$3 -> 202501 | S16: =INDEX($B$3:$O$36,MATCH(Q16,$B$3:$B$36,0),MATCH(R16,$B$3:$O$3,0)) -> 1000
B17: Target | C17: 675 | D17: 675 | E17: 675 | F17: 675 | G17: 675 | H17: 675 | I17: 675 | J17: 675 | K17: 675 | L17: 675 | M17: 675 | N17: 675 | O17: =SUM(C17:N17) -> 8100 | Q17: Target | R17: =$C$3 -> 202501 | S17: =INDEX($B$3:$O$36,MATCH(Q17,$B$3:$B$36,0),MATCH(R17,$B$3:$O$3,0)) -> 675
B18: Total Food & Car | C18: =SUM(C14:C17) -> 3375 | D18: =SUM(D14:D17) -> 3375 | E18: =SUM(E14:E17) -> 3375 | F18: =SUM(F14:F17) -> 3375 | G18: =SUM(G14:G17) -> 3375 | H18: =SUM(H14:H17) -> 3375 | I18: =SUM(I14:I17) -> 3375 | J18: =SUM(J14:J17) -> 3375 | ... N18: =SUM(N14:N17) -> 3375 | O18: =SUM(C18:N18) -> 40500 | Q18: Total Food & Car | R18: =$C$3 -> 202501 | S18: =INDEX($B$3:$O$36,MATCH(Q18,$B$3:$B$36,0),MATCH(R18,$B$3:$O$3,0)) -> 3375
R19: =$C$3 -> 202501 | S19: =INDEX($B$3:$O$36,MATCH(Q19,$B$3:$B$36,0),MATCH(R19,$B$3:$O$3,0)) -> #N/A
B20: Gym | C20: 0 | D20: 0 | E20: 0 | F20: 0 | G20: 0 | H20: 0 | I20: 0 | J20: 0 | K20: 0 | L20: 0 | M20: 0 | N20: 0 | O20: =SUM(C20:N20) -> 0 | Q20: Gym | R20: =$C$3 -> 202501 | S20: =INDEX($B$3:$O$36,MATCH(Q20,$B$3:$B$36,0),MATCH(R20,$B$3:$O$3,0)) -> 0
B21: Shopping | C21: 2000 | D21: 2000 | E21: 2000 | F21: 2000 | G21: 2000 | H21: 2000 | I21: 2000 | J21: 2000 | K21: 2000 | L21: 2000 | M21: 2000 | N21: 2000 | O21: =SUM(C21:N21) -> 24000 | Q21: Shopping | R21: =$C$3 -> 202501 | S21: =INDEX($B$3:$O$36,MATCH(Q21,$B$3:$B$36,0),MATCH(R21,$B$3:$O$3,0)) -> 2000
B22: Amazon | C22: 580 | D22: 580 | E22: 580 | F22: 580 | G22: 580 | H22: 580 | I22: 580 | J22: 580 | K22: 580 | L22: 580 | M22: 580 | N22: 580 | O22: =SUM(C22:N22) -> 6960 | Q22: Amazon | R22: =$C$3 -> 202501 | S22: =INDEX($B$3:$O$36,MATCH(Q22,$B$3:$B$36,0),MATCH(R22,$B$3:$O$3,0)) -> 580
B23: Entertainment | C23: 550 | D23: 550 | E23: 550 | F23: 550 | G23: 550 | H23: 550 | I23: 550 | J23: 550 | K23: 550 | L23: 550 | M23: 550 | N23: 550 | O23: =SUM(C23:N23) -> 6600 | Q23: Entertainment | R23: =$C$3 -> 202501 | S23: =INDEX($B$3:$O$36,MATCH(Q23,$B$3:$B$36,0),MATCH(R23,$B$3:$O$3,0)) -> 550
B24: Dry Cleaning | C24: 45 | D24: 45 | E24: 45 | F24: 45 | G24: 45 | H24: 45 | I24: 45 | J24: 45 | K24: 45 | L24: 45 | M24: 45 | N24: 45 | O24: =SUM(C24:N24) -> 540 | Q24: Dry Cleaning | R24: =$C$3 -> 202501 | S24: =INDEX($B$3:$O$36,MATCH(Q24,$B$3:$B$36,0),MATCH(R24,$B$3:$O$3,0)) -> 45
B25: Gifts | C25: 100 | D25: 100 | E25: 100 | F25: 100 | G25: 100 | H25: 100 | I25: 100 | J25: 100 | K25: 100 | L25: 100 | M25: 100 | N25: 100 | O25: =SUM(C25:N25) -> 1200 | Q25: Gifts | R25: =$C$3 -> 202501 | S25: =INDEX($B$3:$O$36,MATCH(Q25,$B$3:$B$36,0),MATCH(R25,$B$3:$O$3,0)) -> 100
B26: Misc | C26: 45 | D26: 45 | E26: 45 | F26: 45 | G26: 45 | H26: 45 | I26: 45 | J26: 45 | K26: 45 | L26: 45 | M26: 45 | N26: 45 | O26: =SUM(C26:N26) -> 540 | Q26: Misc | R26: =$C$3 -> 202501 | S26: =INDEX($B$3:$O$36,MATCH(Q26,$B$3:$B$36,0),MATCH(R26,$B$3:$O$3,0)) -> 45
B27: Total Other | C27: =SUM(C20:C26) -> 3320 | D27: =SUM(D20:D26) -> 3320 | E27: =SUM(E20:E26) -> 3320 | F27: =SUM(F20:F26) -> 3320 | G27: =SUM(G20:G26) -> 3320 | H27: =SUM(H20:H26) -> 3320 | I27: =SUM(I20:I26) -> 3320 | J27: =SUM(J20:J26) -> 3320 | ... N27: =SUM(N20:N26) -> 3320 | O27: =SUM(C27:N27) -> 39840 | Q27: Total Other | R27: =$C$3 -> 202501 | S27: =INDEX($B$3:$O$36,MATCH(Q27,$B$3:$B$36,0),MATCH(R27,$B$3:$O$3,0)) -> 3320
O28: =SUM(C28:N28) -> 0 | R28: =$C$3 -> 202501 | S28: =INDEX($B$3:$O$36,MATCH(Q28,$B$3:$B$36,0),MATCH(R28,$B$3:$O$3,0)) -> #N/A
B29: Total | C29: =SUM(C27,C18,C12) -> 13150 | D29: =SUM(D27,D18,D12) -> 13150 | E29: =SUM(E27,E18,E12) -> 13150 | F29: =SUM(F27,F18,F12) -> 13150 | G29: =SUM(G27,G18,G12) -> 13150 | H29: =SUM(H27,H18,H12) -> 13150 | I29: =SUM(I27,I18,I12) -> 13150 | J29: =SUM(J27,J18,J12) -> 13150 | ... N29: =SUM(N27,N18,N12) -> 13150 | O29: =SUM(C29:N29) -> 157800 | Q29: Total | R29: =$C$3 -> 202501 | S29: =INDEX($B$3:$O$36,MATCH(Q29,$B$3:$B$36,0),MATCH(R29,$B$3:$O$3,0)) -> 13150
R30: =$C$3 -> 202501 | S30: =INDEX($B$3:$O$36,MATCH(Q30,$B$3:$B$36,0),MATCH(R30,$B$3:$O$3,0)) -> #N/A
B31: Healthcare | C31: 200 | D31: 200 | E31: 200 | F31: 200 | G31: 200 | H31: 200 | I31: 200 | J31: 200 | K31: 200 | L31: 200 | M31: 200 | N31: 200 | O31: =SUM(C31:N31) -> 2400 | Q31: Healthcare | R31: =$C$3 -> 202501 | S31: =INDEX($B$3:$O$36,MATCH(Q31,$B$3:$B$36,0),MATCH(R31,$B$3:$O$3,0)) -> 200
B32: House | C32: =30245 -> 30245 | D32: 19919.5 | E32: 13299.5 | F32: 17668 | O32: =SUM(C32:N32) -> 81132 | Q32: House | R32: =$C$3 -> 202501 | S32: =INDEX($B$3:$O$36,MATCH(Q32,$B$3:$B$36,0),MATCH(R32,$B$3:$O$3,0)) -> 30245
B33: Travel | E33: 2000 | F33: 4000 | H33: 1500 | K33: 2000 | L33: 2000 | M33: 2000 | O33: =SUM(C33:N33) -> 13500 | Q33: Travel | R33: =$C$3 -> 202501 | S33: =INDEX($B$3:$O$36,MATCH(Q33,$B$3:$B$36,0),MATCH(R33,$B$3:$O$3,0)) -> 0
B34: Total Yearly | C34: =SUM(C31:C33) -> 30445 | D34: =SUM(D31:D33) -> 20119.5 | E34: =SUM(E31:E33) -> 15499.5 | F34: =SUM(F31:F33) -> 21868 | G34: =SUM(G31:G33) -> 200 | H34: =SUM(H31:H33) -> 1700 | I34: =SUM(I31:I33) -> 200 | J34: =SUM(J31:J33) -> 200 | ... O34: =SUM(O31:O33) -> 97032 | Q34: Total Yearly | R34: =$C$3 -> 202501 | S34: =INDEX($B$3:$O$36,MATCH(Q34,$B$3:$B$36,0),MATCH(R34,$B$3:$O$3,0)) -> 30445
R35: =$C$3 -> 202501 | S35: =INDEX($B$3:$O$36,MATCH(Q35,$B$3:$B$36,0),MATCH(R35,$B$3:$O$3,0)) -> #N/A
B36: Total All Spend | C36: =SUM(C34,C29) -> 43595 | D36: =SUM(D34,D29) -> 33269.5 | E36: =SUM(E34,E29) -> 28649.5 | F36: =SUM(F34,F29) -> 35018 | G36: =SUM(G34,G29) -> 13350 | H36: =SUM(H34,H29) -> 14850 | I36: =SUM(I34,I29) -> 13350 | J36: =SUM(J34,J29) -> 13350 | ... O36: =SUM(O34,O29) -> 254832 | Q36: Total All Spend | R36: =$C$3 -> 202501 | S36: =INDEX($B$3:$O$36,MATCH(Q36,$B$3:$B$36,0),MATCH(R36,$B$3:$O$3,0)) -> 43595
Q37: Rent | R37: =$D$3 -> 202502 | S37: =INDEX($B$3:$O$36,MATCH(Q37,$B$3:$B$36,0),MATCH(R37,$B$3:$O$3,0)) -> 2745
Q38: House Maintenance | R38: =$D$3 -> 202502 | S38: =INDEX($B$3:$O$36,MATCH(Q38,$B$3:$B$36,0),MATCH(R38,$B$3:$O$3,0)) -> 350
B39: Budget | C39: 202401 | D39: 202402 | E39: 202403 | F39: 202404 | G39: 202405 | H39: 202406 | I39: 202407 | J39: 202408 | K39: 202409 | L39: 202410 | M39: 202411 | N39: 202412 | O39: Total | Q39: Utilities | R39: =$D$3 -> 202502 | S39: =INDEX($B$3:$O$36,MATCH(Q39,$B$3:$B$36,0),MATCH(R39,$B$3:$O$3,0)) -> 700
Q40: Car Loan | R40: =$D$3 -> 202502 | S40: =INDEX($B$3:$O$36,MATCH(Q40,$B$3:$B$36,0),MATCH(R40,$B$3:$O$3,0)) -> 0
B41: Rent | C41: 2572.94 | D41: 2572.94 | E41: 2572.94 | F41: 2572.94 | G41: 2572.94 | H41: 2572.94 | I41: 2572.94 | J41: 2572.94 | K41: 2572.94 | L41: 2572.94 | M41: 2572.94 | N41: 2572.94 | O41: =SUM(C41:N41) -> 30875.28 | Q41: Cleaning | R41: =$D$3 -> 202502 | S41: =INDEX($B$3:$O$36,MATCH(Q41,$B$3:$B$36,0),MATCH(R41,$B$3:$O$3,0)) -> 250
B42: House Maintenance | C42: 500 | D42: 500 | E42: 500 | F42: 500 | G42: 500 | H42: 500 | I42: 500 | J42: 500 | K42: 500 | L42: 500 | M42: 500 | N42: 500 | O42: =SUM(C42:N42) -> 6000 | Q42: Insurance | R42: =$D$3 -> 202502 | S42: =INDEX($B$3:$O$36,MATCH(Q42,$B$3:$B$36,0),MATCH(R42,$B$3:$O$3,0)) -> 135
B43: Utilities | C43: 400 | D43: 400 | E43: 400 | F43: 400 | G43: 400 | H43: 400 | I43: 400 | J43: 400 | K43: 400 | L43: 400 | M43: 400 | N43: 400 | O43: =SUM(C43:N43) -> 4800 | Q43: Day Care | R43: =$D$3 -> 202502 | S43: =INDEX($B$3:$O$36,MATCH(Q43,$B$3:$B$36,0),MATCH(R43,$B$3:$O$3,0)) -> 2275
B44: Car Loan | O44: =SUM(C44:N44) -> 0 | Q44: Total Rent & Utilitites | R44: =$D$3 -> 202502 | S44: =INDEX($B$3:$O$36,MATCH(Q44,$B$3:$B$36,0),MATCH(R44,$B$3:$O$3,0)) -> 6455
B45: Cleaning | C45: =125*2 -> 250 | D45: =125*2 -> 250 | E45: =125*2 -> 250 | F45: =125*2 -> 250 | G45: =125*2 -> 250 | H45: =125*2 -> 250 | I45: =125*2 -> 250 | J45: =125*2 -> 250 | ... N45: =125*2 -> 250 | O45: =SUM(C45:N45) -> 3000 | R45: =$D$3 -> 202502 | S45: =INDEX($B$3:$O$36,MATCH(Q45,$B$3:$B$36,0),MATCH(R45,$B$3:$O$3,0)) -> #N/A
B46: Insurance | C46: 117 | D46: 117 | E46: 117 | F46: 117 | G46: 117 | H46: 117 | I46: 117 | J46: 117 | K46: 117 | L46: 117 | M46: 117 | N46: 117 | O46: =SUM(C46:N46) -> 1404 | Q46: Transportation | R46: =$D$3 -> 202502 | S46: =INDEX($B$3:$O$36,MATCH(Q46,$B$3:$B$36,0),MATCH(R46,$B$3:$O$3,0)) -> 400
B47: Day Care | C47: 2000 | D47: 2000 | E47: 2000 | F47: 2000 | G47: 2000 | H47: 2000 | I47: 2000 | J47: 2000 | K47: 2000 | L47: 2000 | M47: 2000 | N47: 2000 | O47: =SUM(C47:N47) -> 24000 | Q47: Restaurants | R47: =$D$3 -> 202502 | S47: =INDEX($B$3:$O$36,MATCH(Q47,$B$3:$B$36,0),MATCH(R47,$B$3:$O$3,0)) -> 1300
B48: Total Rent & Utilitites | C48: =SUM(C41:C47) -> 5839.94 | D48: =SUM(D41:D47) -> 5839.94 | E48: =SUM(E41:E47) -> 5839.94 | F48: =SUM(F41:F47) -> 5839.94 | G48: =SUM(G41:G47) -> 5839.94 | H48: =SUM(H41:H47) -> 5839.94 | I48: =SUM(I41:I47) -> 5839.94 | J48: =SUM(J41:J47) -> 5839.94 | ... N48: =SUM(N41:N47) -> 5839.94 | O48: =SUM(C48:N48) -> 70079.28 | Q48: Groceries | R48: =$D$3 -> 202502 | S48: =INDEX($B$3:$O$36,MATCH(Q48,$B$3:$B$36,0),MATCH(R48,$B$3:$O$3,0)) -> 1000
Q49: Target | R49: =$D$3 -> 202502 | S49: =INDEX($B$3:$O$36,MATCH(Q49,$B$3:$B$36,0),MATCH(R49,$B$3:$O$3,0)) -> 675
B50: Transportation | C50: 800 | D50: 800 | E50: 800 | F50: 800 | G50: 800 | H50: 800 | I50: 800 | J50: 800 | K50: 800 | L50: 800 | M50: 800 | N50: 800 | O50: =SUM(C50:N50) -> 9600 | Q50: Total Food & Car | R50: =$D$3 -> 202502 | S50: =INDEX($B$3:$O$36,MATCH(Q50,$B$3:$B$36,0),MATCH(R50,$B$3:$O$3,0)) -> 3375
B51: Restaurants | C51: 1100 | D51: 1100 | E51: 1100 | F51: 1100 | G51: 1100 | H51: 1100 | I51: 1100 | J51: 1100 | K51: 1100 | L51: 1100 | M51: 1100 | N51: 1100 | O51: =SUM(C51:N51) -> 13200 | R51: =$D$3 -> 202502 | S51: =INDEX($B$3:$O$36,MATCH(Q51,$B$3:$B$36,0),MATCH(R51,$B$3:$O$3,0)) -> #N/A
B52: Groceries | C52: 900 | D52: 900 | E52: 900 | F52: 900 | G52: 900 | H52: 900 | I52: 900 | J52: 900 | K52: 900 | L52: 900 | M52: 900 | N52: 900 | O52: =SUM(C52:N52) -> 10800 | Q52: Gym | R52: =$D$3 -> 202502 | S52: =INDEX($B$3:$O$36,MATCH(Q52,$B$3:$B$36,0),MATCH(R52,$B$3:$O$3,0)) -> 0
B53: Target | C53: 600 | D53: 600 | E53: 600 | F53: 600 | G53: 600 | H53: 600 | I53: 600 | J53: 600 | K53: 600 | L53: 600 | M53: 600 | N53: 600 | O53: =SUM(C53:N53) -> 7200 | Q53: Shopping | R53: =$D$3 -> 202502 | S53: =INDEX($B$3:$O$36,MATCH(Q53,$B$3:$B$36,0),MATCH(R53,$B$3:$O$3,0)) -> 2000
B54: Total Food & Car | C54: =SUM(C50:C53) -> 3400 | D54: =SUM(D50:D53) -> 3400 | E54: =SUM(E50:E53) -> 3400 | F54: =SUM(F50:F53) -> 3400 | G54: =SUM(G50:G53) -> 3400 | H54: =SUM(H50:H53) -> 3400 | I54: =SUM(I50:I53) -> 3400 | J54: =SUM(J50:J53) -> 3400 | ... N54: =SUM(N50:N53) -> 3400 | O54: =SUM(C54:N54) -> 40800 | Q54: Amazon | R54: =$D$3 -> 202502 | S54: =INDEX($B$3:$O$36,MATCH(Q54,$B$3:$B$36,0),MATCH(R54,$B$3:$O$3,0)) -> 580
Q55: Entertainment | R55: =$D$3 -> 202502 | S55: =INDEX($B$3:$O$36,MATCH(Q55,$B$3:$B$36,0),MATCH(R55,$B$3:$O$3,0)) -> 550
B56: Gym | C56: 47 | D56: 47 | E56: 47 | F56: 47 | G56: 47 | H56: 47 | I56: 47 | J56: 47 | K56: 47 | L56: 47 | M56: 47 | N56: 47 | O56: =SUM(C56:N56) -> 564 | Q56: Dry Cleaning | R56: =$D$3 -> 202502 | S56: =INDEX($B$3:$O$36,MATCH(Q56,$B$3:$B$36,0),MATCH(R56,$B$3:$O$3,0)) -> 45
B57: Shopping | C57: 2500 | D57: 2500 | E57: 2500 | F57: 2500 | G57: 2500 | H57: 2500 | I57: 2500 | J57: 2500 | K57: 2500 | L57: 2500 | M57: 2500 | N57: 2500 | O57: =SUM(C57:N57) -> 30000 | Q57: Gifts | R57: =$D$3 -> 202502 | S57: =INDEX($B$3:$O$36,MATCH(Q57,$B$3:$B$36,0),MATCH(R57,$B$3:$O$3,0)) -> 100
B58: Amazon | C58: 500 | D58: 500 | E58: 500 | F58: 500 | G58: 500 | H58: 500 | I58: 500 | J58: 500 | K58: 500 | L58: 500 | M58: 500 | N58: 500 | O58: =SUM(C58:N58) -> 6000 | Q58: Misc | R58: =$D$3 -> 202502 | S58: =INDEX($B$3:$O$36,MATCH(Q58,$B$3:$B$36,0),MATCH(R58,$B$3:$O$3,0)) -> 45
B59: Entertainment | C59: 200 | D59: 200 | E59: 200 | F59: 200 | G59: 200 | H59: 200 | I59: 200 | J59: 200 | K59: 200 | L59: 200 | M59: 200 | N59: 200 | O59: =SUM(C59:N59) -> 2400 | Q59: Total Other | R59: =$D$3 -> 202502 | S59: =INDEX($B$3:$O$36,MATCH(Q59,$B$3:$B$36,0),MATCH(R59,$B$3:$O$3,0)) -> 3320
B60: Dry Cleaning | C60: 30 | D60: 30 | E60: 30 | F60: 30 | G60: 30 | H60: 30 | I60: 30 | J60: 30 | K60: 30 | L60: 30 | M60: 30 | N60: 30 | O60: =SUM(C60:N60) -> 360 | R60: =$D$3 -> 202502 | S60: =INDEX($B$3:$O$36,MATCH(Q60,$B$3:$B$36,0),MATCH(R60,$B$3:$O$3,0)) -> #N/A
B61: Gifts | C61: 130 | D61: 130 | E61: 130 | F61: 130 | G61: 130 | H61: 130 | I61: 130 | J61: 130 | K61: 130 | L61: 130 | M61: 130 | N61: 130 | O61: =SUM(C61:N61) -> 1560 | Q61: Total | R61: =$D$3 -> 202502 | S61: =INDEX($B$3:$O$36,MATCH(Q61,$B$3:$B$36,0),MATCH(R61,$B$3:$O$3,0)) -> 13150
B62: Misc | C62: 65 | D62: 65 | E62: 65 | F62: 65 | G62: 65 | H62: 65 | I62: 65 | J62: 65 | K62: 65 | L62: 65 | M62: 65 | N62: 65 | O62: =SUM(C62:N62) -> 780 | R62: =$D$3 -> 202502 | S62: =INDEX($B$3:$O$36,MATCH(Q62,$B$3:$B$36,0),MATCH(R62,$B$3:$O$3,0)) -> #N/A
B63: Total Other | C63: =SUM(C56:C62) -> 3472 | D63: =SUM(D56:D62) -> 3472 | E63: =SUM(E56:E62) -> 3472 | F63: =SUM(F56:F62) -> 3472 | G63: =SUM(G56:G62) -> 3472 | H63: =SUM(H56:H62) -> 3472 | I63: =SUM(I56:I62) -> 3472 | J63: =SUM(J56:J62) -> 3472 | ... N63: =SUM(N56:N62) -> 3472 | O63: =SUM(C63:N63) -> 41664 | Q63: Healthcare | R63: =$D$3 -> 202502 | S63: =INDEX($B$3:$O$36,MATCH(Q63,$B$3:$B$36,0),MATCH(R63,$B$3:$O$3,0)) -> 200
O64: =SUM(C64:N64) -> 0 | Q64: House | R64: =$D$3 -> 202502 | S64: =INDEX($B$3:$O$36,MATCH(Q64,$B$3:$B$36,0),MATCH(R64,$B$3:$O$3,0)) -> 19919.5
B65: Total | C65: =SUM(C63,C54,C48) -> 12711.94 | D65: =SUM(D63,D54,D48) -> 12711.94 | E65: =SUM(E63,E54,E48) -> 12711.94 | F65: =SUM(F63,F54,F48) -> 12711.94 | G65: =SUM(G63,G54,G48) -> 12711.94 | H65: =SUM(H63,H54,H48) -> 12711.94 | I65: =SUM(I63,I54,I48) -> 12711.94 | J65: =SUM(J63,J54,J48) -> 12711.94 | ... N65: =SUM(N63,N54,N48) -> 12711.94 | O65: =SUM(C65:N65) -> 152543.28 | Q65: Travel | R65: =$D$3 -> 202502 | S65: =INDEX($B$3:$O$36,MATCH(Q65,$B$3:$B$36,0),MATCH(R65,$B$3:$O$3,0)) -> 0
Q66: Total Yearly | R66: =$D$3 -> 202502 | S66: =INDEX($B$3:$O$36,MATCH(Q66,$B$3:$B$36,0),MATCH(R66,$B$3:$O$3,0)) -> 20119.5
B67: Healthcare | I67: 5000 | O67: =SUM(C67:N67) -> 5000 | R67: =$D$3 -> 202502 | S67: =INDEX($B$3:$O$36,MATCH(Q67,$B$3:$B$36,0),MATCH(R67,$B$3:$O$3,0)) -> #N/A
B68: House | I68: 10000 | O68: =SUM(C68:N68) -> 10000 | Q68: Total All Spend | R68: =$D$3 -> 202502 | S68: =INDEX($B$3:$O$36,MATCH(Q68,$B$3:$B$36,0),MATCH(R68,$B$3:$O$3,0)) -> 33269.5
B69: Travel | C69: 1000 | I69: 20000 | O69: =SUM(C69:N69) -> 21000 | Q69: Rent | R69: =$E$3 -> 202503 | S69: =INDEX($B$3:$O$36,MATCH(Q69,$B$3:$B$36,0),MATCH(R69,$B$3:$O$3,0)) -> 2745
B70: Total Yearly | C70: =SUM(C67:C69) -> 1000 | D70: =SUM(D67:D69) -> 0 | E70: =SUM(E67:E69) -> 0 | F70: =SUM(F67:F69) -> 0 | G70: =SUM(G67:G69) -> 0 | H70: =SUM(H67:H69) -> 0 | I70: =SUM(I67:I69) -> 35000 | J70: =SUM(J67:J69) -> 0 | ... O70: =SUM(O67:O69) -> 36000 | Q70: House Maintenance | R70: =$E$3 -> 202503 | S70: =INDEX($B$3:$O$36,MATCH(Q70,$B$3:$B$36,0),MATCH(R70,$B$3:$O$3,0)) -> 350
Q71: Utilities | R71: =$E$3 -> 202503 | S71: =INDEX($B$3:$O$36,MATCH(Q71,$B$3:$B$36,0),MATCH(R71,$B$3:$O$3,0)) -> 700
B72: Total All Spend | C72: =SUM(C70,C65) -> 13711.94 | D72: =SUM(D70,D65) -> 12711.94 | E72: =SUM(E70,E65) -> 12711.94 | F72: =SUM(F70,F65) -> 12711.94 | G72: =SUM(G70,G65) -> 12711.94 | H72: =SUM(H70,H65) -> 12711.94 | I72: =SUM(I70,I65) -> 47711.94 | J72: =SUM(J70,J65) -> 12711.94 | ... O72: =SUM(O70,O65) -> 188543.28 | Q72: Car Loan | R72: =$E$3 -> 202503 | S72: =INDEX($B$3:$O$36,MATCH(Q72,$B$3:$B$36,0),MATCH(R72,$B$3:$O$3,0)) -> 0
Q73: Cleaning | R73: =$E$3 -> 202503 | S73: =INDEX($B$3:$O$36,MATCH(Q73,$B$3:$B$36,0),MATCH(R73,$B$3:$O$3,0)) -> 250
Q74: Insurance | R74: =$E$3 -> 202503 | S74: =INDEX($B$3:$O$36,MATCH(Q74,$B$3:$B$36,0),MATCH(R74,$B$3:$O$3,0)) -> 135
B75: Budget | C75: 202301 | D75: 202302 | E75: 202303 | F75: 202304 | G75: 202305 | H75: 202306 | I75: 202307 | J75: 202308 | K75: 202309 | L75: 202310 | M75: 202311 | N75: 202312 | O75: Total | Q75: Day Care | R75: =$E$3 -> 202503 | S75: =INDEX($B$3:$O$36,MATCH(Q75,$B$3:$B$36,0),MATCH(R75,$B$3:$O$3,0)) -> 2275
Q76: Total Rent & Utilitites | R76: =$E$3 -> 202503 | S76: =INDEX($B$3:$O$36,MATCH(Q76,$B$3:$B$36,0),MATCH(R76,$B$3:$O$3,0)) -> 6455
B77: Rent | C77: 2572.94 | D77: 2572.94 | E77: 2572.94 | F77: 2572.94 | G77: 2572.94 | H77: 2572.94 | I77: 2572.94 | J77: 2572.94 | K77: 2572.94 | L77: 2572.94 | M77: 2572.94 | N77: 2572.94 | O77: =SUM(C77:N77) -> 30875.28 | Q77: Transportation | R77: =$E$3 -> 202503 | S77: =INDEX($B$3:$O$36,MATCH(Q77,$B$3:$B$36,0),MATCH(R77,$B$3:$O$3,0)) -> 400
B78: House Maintenance | C78: 300 | D78: 300 | E78: 300 | F78: 300 | G78: 300 | H78: 300 | I78: 300 | J78: 300 | K78: 300 | L78: 300 | M78: 300 | N78: 300 | O78: =SUM(C78:N78) -> 3600 | Q78: Restaurants | R78: =$E$3 -> 202503 | S78: =INDEX($B$3:$O$36,MATCH(Q78,$B$3:$B$36,0),MATCH(R78,$B$3:$O$3,0)) -> 1300
B79: Utilities | C79: 450 | D79: 450 | E79: 450 | F79: 450 | G79: 450 | H79: 450 | I79: 450 | J79: 450 | K79: 450 | L79: 450 | M79: 450 | N79: 450 | O79: =SUM(C79:N79) -> 5400 | Q79: Groceries | R79: =$E$3 -> 202503 | S79: =INDEX($B$3:$O$36,MATCH(Q79,$B$3:$B$36,0),MATCH(R79,$B$3:$O$3,0)) -> 1000
B80: Car Loan | C80: 619 | D80: 619 | E80: 619 | F80: 619 | G80: 619 | H80: 619 | I80: 619 | J80: 619 | K80: 619 | L80: 619 | M80: 619 | N80: 619 | O80: =SUM(C80:N80) -> 7428 | Q80: Target | R80: =$E$3 -> 202503 | S80: =INDEX($B$3:$O$36,MATCH(Q80,$B$3:$B$36,0),MATCH(R80,$B$3:$O$3,0)) -> 675
B81: Cleaning | C81: =125*2 -> 250 | D81: =125*2 -> 250 | E81: =125*2 -> 250 | F81: =125*2 -> 250 | G81: =125*2 -> 250 | H81: =125*2 -> 250 | I81: =125*2 -> 250 | J81: =125*2 -> 250 | ... N81: =125*2 -> 250 | O81: =SUM(C81:N81) -> 3000 | Q81: Total Food & Car | R81: =$E$3 -> 202503 | S81: =INDEX($B$3:$O$36,MATCH(Q81,$B$3:$B$36,0),MATCH(R81,$B$3:$O$3,0)) -> 3375
B82: Insurance | C82: 90 | D82: 90 | E82: 90 | F82: 90 | G82: 90 | H82: 90 | I82: 90 | J82: 90 | K82: 90 | L82: 90 | M82: 90 | N82: 90 | O82: =SUM(C82:N82) -> 1080 | Q82: Gym | R82: =$E$3 -> 202503 | S82: =INDEX($B$3:$O$36,MATCH(Q82,$B$3:$B$36,0),MATCH(R82,$B$3:$O$3,0)) -> 0
B83: Day Care | C83: 2250 | D83: 2250 | E83: 2250 | F83: 2250 | G83: 2250 | H83: 2250 | I83: 2250 | J83: 2250 | K83: 2250 | L83: 2250 | M83: 2250 | N83: 2250 | O83: =SUM(C83:N83) -> 27000 | Q83: Shopping | R83: =$E$3 -> 202503 | S83: =INDEX($B$3:$O$36,MATCH(Q83,$B$3:$B$36,0),MATCH(R83,$B$3:$O$3,0)) -> 2000
B84: Total Rent & Utilitites | C84: =SUM(C77:C83) -> 6531.94 | D84: =SUM(D77:D83) -> 6531.94 | E84: =SUM(E77:E83) -> 6531.94 | F84: =SUM(F77:F83) -> 6531.94 | G84: =SUM(G77:G83) -> 6531.94 | H84: =SUM(H77:H83) -> 6531.94 | I84: =SUM(I77:I83) -> 6531.94 | J84: =SUM(J77:J83) -> 6531.94 | ... N84: =SUM(N77:N83) -> 6531.94 | O84: =SUM(C84:N84) -> 78383.28 | Q84: Amazon | R84: =$E$3 -> 202503 | S84: =INDEX($B$3:$O$36,MATCH(Q84,$B$3:$B$36,0),MATCH(R84,$B$3:$O$3,0)) -> 580
Q85: Entertainment | R85: =$E$3 -> 202503 | S85: =INDEX($B$3:$O$36,MATCH(Q85,$B$3:$B$36,0),MATCH(R85,$B$3:$O$3,0)) -> 550
B86: Transportation | C86: 600 | D86: 600 | E86: 600 | F86: 600 | G86: 600 | H86: 600 | I86: 600 | J86: 600 | K86: 600 | L86: 600 | M86: 600 | N86: 600 | O86: =SUM(C86:N86) -> 7200 | Q86: Dry Cleaning | R86: =$E$3 -> 202503 | S86: =INDEX($B$3:$O$36,MATCH(Q86,$B$3:$B$36,0),MATCH(R86,$B$3:$O$3,0)) -> 45
B87: Restaurants | C87: 1070 | D87: 1070 | E87: 1070 | F87: 1070 | G87: 1070 | H87: 1070 | I87: 1070 | J87: 1070 | K87: 1070 | L87: 1070 | M87: 1070 | N87: 1070 | O87: =SUM(C87:N87) -> 12840 | Q87: Gifts | R87: =$E$3 -> 202503 | S87: =INDEX($B$3:$O$36,MATCH(Q87,$B$3:$B$36,0),MATCH(R87,$B$3:$O$3,0)) -> 100
B88: Groceries | C88: 900 | D88: 900 | E88: 900 | F88: 900 | G88: 900 | H88: 900 | I88: 900 | J88: 900 | K88: 900 | L88: 900 | M88: 900 | N88: 900 | O88: =SUM(C88:N88) -> 10800 | Q88: Misc | R88: =$E$3 -> 202503 | S88: =INDEX($B$3:$O$36,MATCH(Q88,$B$3:$B$36,0),MATCH(R88,$B$3:$O$3,0)) -> 45
B89: Target | C89: 600 | D89: 600 | E89: 600 | F89: 600 | G89: 600 | H89: 600 | I89: 600 | J89: 600 | K89: 600 | L89: 600 | M89: 600 | N89: 600 | O89: =SUM(C89:N89) -> 7200 | Q89: Total Other | R89: =$E$3 -> 202503 | S89: =INDEX($B$3:$O$36,MATCH(Q89,$B$3:$B$36,0),MATCH(R89,$B$3:$O$3,0)) -> 3320
B90: Total Food & Car | C90: =SUM(C86:C89) -> 3170 | D90: =SUM(D86:D89) -> 3170 | E90: =SUM(E86:E89) -> 3170 | F90: =SUM(F86:F89) -> 3170 | G90: =SUM(G86:G89) -> 3170 | H90: =SUM(H86:H89) -> 3170 | I90: =SUM(I86:I89) -> 3170 | J90: =SUM(J86:J89) -> 3170 | ... N90: =SUM(N86:N89) -> 3170 | O90: =SUM(C90:N90) -> 38040 | Q90: Total | R90: =$E$3 -> 202503 | S90: =INDEX($B$3:$O$36,MATCH(Q90,$B$3:$B$36,0),MATCH(R90,$B$3:$O$3,0)) -> 13150
Q91: Healthcare | R91: =$E$3 -> 202503 | S91: =INDEX($B$3:$O$36,MATCH(Q91,$B$3:$B$36,0),MATCH(R91,$B$3:$O$3,0)) -> 200
B92: Gym | C92: 40 | D92: 40 | E92: 40 | F92: 40 | G92: 40 | H92: 40 | I92: 40 | J92: 40 | K92: 40 | L92: 40 | M92: 40 | N92: 40 | O92: =SUM(C92:N92) -> 480 | Q92: House | R92: =$E$3 -> 202503 | S92: =INDEX($B$3:$O$36,MATCH(Q92,$B$3:$B$36,0),MATCH(R92,$B$3:$O$3,0)) -> 13299.5
B93: Shopping | C93: 2000 | D93: 2000 | E93: 2000 | F93: 2000 | G93: 2000 | H93: 2000 | I93: 2000 | J93: 2000 | K93: 2000 | L93: 2000 | M93: 2000 | N93: 2000 | O93: =SUM(C93:N93) -> 24000 | Q93: Travel | R93: =$E$3 -> 202503 | S93: =INDEX($B$3:$O$36,MATCH(Q93,$B$3:$B$36,0),MATCH(R93,$B$3:$O$3,0)) -> 2000
B94: Amazon | C94: 400 | D94: 400 | E94: 400 | F94: 400 | G94: 400 | H94: 400 | I94: 400 | J94: 400 | K94: 400 | L94: 400 | M94: 400 | N94: 400 | O94: =SUM(C94:N94) -> 4800 | Q94: Total Yearly | R94: =$E$3 -> 202503 | S94: =INDEX($B$3:$O$36,MATCH(Q94,$B$3:$B$36,0),MATCH(R94,$B$3:$O$3,0)) -> 15499.5
B95: Entertainment | C95: 200 | D95: 200 | E95: 200 | F95: 200 | G95: 200 | H95: 200 | I95: 200 | J95: 200 | K95: 200 | L95: 200 | M95: 200 | N95: 200 | O95: =SUM(C95:N95) -> 2400 | Q95: Total All Spend | R95: =$E$3 -> 202503 | S95: =INDEX($B$3:$O$36,MATCH(Q95,$B$3:$B$36,0),MATCH(R95,$B$3:$O$3,0)) -> 28649.5
B96: Dry Cleaning | C96: 30 | D96: 30 | E96: 30 | F96: 30 | G96: 30 | H96: 30 | I96: 30 | J96: 30 | K96: 30 | L96: 30 | M96: 30 | N96: 30 | O96: =SUM(C96:N96) -> 360 | Q96: Rent | R96: =$F$3 -> 202504 | S96: =INDEX($B$3:$O$36,MATCH(Q96,$B$3:$B$36,0),MATCH(R96,$B$3:$O$3,0)) -> 2745
B97: Gifts | C97: 130 | D97: 130 | E97: 130 | F97: 130 | G97: 130 | H97: 130 | I97: 130 | J97: 130 | K97: 130 | L97: 130 | M97: 130 | N97: 130 | O97: =SUM(C97:N97) -> 1560 | Q97: House Maintenance | R97: =$F$3 -> 202504 | S97: =INDEX($B$3:$O$36,MATCH(Q97,$B$3:$B$36,0),MATCH(R97,$B$3:$O$3,0)) -> 350
B98: Misc | C98: 0 | D98: 0 | E98: 0 | F98: 0 | G98: 0 | H98: 0 | I98: 0 | J98: 0 | K98: 0 | L98: 0 | M98: 0 | N98: 0 | O98: =SUM(C98:N98) -> 0 | Q98: Utilities | R98: =$F$3 -> 202504 | S98: =INDEX($B$3:$O$36,MATCH(Q98,$B$3:$B$36,0),MATCH(R98,$B$3:$O$3,0)) -> 700
B99: Total Other | C99: =SUM(C92:C98) -> 2800 | D99: =SUM(D92:D98) -> 2800 | E99: =SUM(E92:E98) -> 2800 | F99: =SUM(F92:F98) -> 2800 | G99: =SUM(G92:G98) -> 2800 | H99: =SUM(H92:H98) -> 2800 | I99: =SUM(I92:I98) -> 2800 | J99: =SUM(J92:J98) -> 2800 | ... N99: =SUM(N92:N98) -> 2800 | O99: =SUM(C99:N99) -> 33600 | Q99: Car Loan | R99: =$F$3 -> 202504 | S99: =INDEX($B$3:$O$36,MATCH(Q99,$B$3:$B$36,0),MATCH(R99,$B$3:$O$3,0)) -> 0
O100: =SUM(C100:N100) -> 0 | Q100: Cleaning | R100: =$F$3 -> 202504 | S100: =INDEX($B$3:$O$36,MATCH(Q100,$B$3:$B$36,0),MATCH(R100,$B$3:$O$3,0)) -> 250
B101: Total | C101: =SUM(C99,C90,C84) -> 12501.94 | D101: =SUM(D99,D90,D84) -> 12501.94 | E101: =SUM(E99,E90,E84) -> 12501.94 | F101: =SUM(F99,F90,F84) -> 12501.94 | G101: =SUM(G99,G90,G84) -> 12501.94 | H101: =SUM(H99,H90,H84) -> 12501.94 | I101: =SUM(I99,I90,I84) -> 12501.94 | J101: =SUM(J99,J90,J84) -> 12501.94 | ... N101: =SUM(N99,N90,N84) -> 12501.94 | O101: =SUM(C101:N101) -> 150023.28 | Q101: Insurance | R101: =$F$3 -> 202504 | S101: =INDEX($B$3:$O$36,MATCH(Q101,$B$3:$B$36,0),MATCH(R101,$B$3:$O$3,0)) -> 135
Q102: Day Care | R102: =$F$3 -> 202504 | S102: =INDEX($B$3:$O$36,MATCH(Q102,$B$3:$B$36,0),MATCH(R102,$B$3:$O$3,0)) -> 2275
...

Sheet Year
D1: =VALUE('1 MO'!$C$3&"01") -> 202501 | E1: =VALUE('1 MO'!$C$3&"02") -> 202502 | F1: =VALUE('1 MO'!$C$3&"03") -> 202503 | G1: =VALUE('1 MO'!$C$3&"04") -> 202504 | H1: =VALUE('1 MO'!$C$3&"05") -> 202505 | I1: =VALUE('1 MO'!$C$3&"06") -> 202506 | J1: =VALUE('1 MO'!$C$3&"07") -> 202507 | K1: =VALUE('1 MO'!$C$3&"08") -> 202508 | L1: =VALUE('1 MO'!$C$3&"09") -> 202509 | M1: =VALUE('1 MO'!$C$3&"10") -> 202510 | N1: =VALUE('1 MO'!$C$3&"11") -> 202511 | O1: =VALUE('1 MO'!$C$3&"12") -> 202512
C7: Actuals | D7: =TEXT(DATE(LEFT(D1,4),RIGHT(D1,2),1),"MMM YYYY") -> Jan 2025 | E7: =TEXT(DATE(LEFT(E1,4),RIGHT(E1,2),1),"MMM YYYY") -> Feb 2025 | F7: =TEXT(DATE(LEFT(F1,4),RIGHT(F1,2),1),"MMM YYYY") -> Mar 2025 | G7: =TEXT(DATE(LEFT(G1,4),RIGHT(G1,2),1),"MMM YYYY") -> Apr 2025 | H7: =TEXT(DATE(LEFT(H1,4),RIGHT(H1,2),1),"MMM YYYY") -> May 2025 | I7: =TEXT(DATE(LEFT(I1,4),RIGHT(I1,2),1),"MMM YYYY") -> Jun 2025 | J7: =TEXT(DATE(LEFT(J1,4),RIGHT(J1,2),1),"MMM YYYY") -> Jul 2025 | K7: =TEXT(DATE(LEFT(K1,4),RIGHT(K1,2),1),"MMM YYYY") -> Aug 2025 | ... O7: =TEXT(DATE(LEFT(O1,4),RIGHT(O1,2),1),"MMM YYYY") -> Dec 2025 | P7: Total | R7: 2024 | S7: 2023 | T7: Dif
C9: Rent | D9: =SUMIFS(Actuals!$E:$E,Actuals!$F:$F,Year!$C9,Actuals!$A:$A,Year!D$1) -> 2745.43 | E9: =SUMIFS(Actuals!$E:$E,Actuals!$F:$F,Year!$C9,Actuals!$A:$A,Year!E$1) -> 2745.43 | F9: =SUMIFS(Actuals!$E:$E,Actuals!$F:$F,Year!$C9,Actuals!$A:$A,Year!F$1) -> 1770.04 | G9: =SUMIFS(Actuals!$E:$E,Actuals!$F:$F,Year!$C9,Actuals!$A:$A,Year!G$1) -> 2745.43 | H9: =SUMIFS(Actuals!$E:$E,Actuals!$F:$F,Year!$C9,Actuals!$A:$A,Year!H$1) -> 2745.43 | I9: =SUMIFS(Actuals!$E:$E,Actuals!$F:$F,Year!$C9,Actuals!$A:$A,Year!I$1) -> 2745.43 | J9: =SUMIFS(Actuals!$E:$E,Actuals!$F:$F,Year!$C9,Actuals!$A:$A,Year!J$1) -> 2745.43 | K9: =SUMIFS(Actuals!$E:$E,Actuals!$F:$F,Year!$C9,Actuals!$A:$A,Year!K$1) -> 2745.43 | ... O9: =SUMIFS(Actuals!$E:$E,Actuals!$F:$F,Year!$C9,Actuals!$A:$A,Year!O$1) -> 3378.51 | P9: =SUM(D9:O9) -> 34502.09 | R9: 32915.64 | S9: 31817.12 | T9: =R9-S9 -> 1098.52
C10: House Maintenance | D10: =SUMIFS(Actuals!$E:$E,Actuals!$F:$F,Year!$C10,Actuals!$A:$A,Year!D$1) -> 158.51 | E10: =SUMIFS(Actuals!$E:$E,Actuals!$F:$F,Year!$C10,Actuals!$A:$A,Year!E$1) -> 72.41 | F10: =SUMIFS(Actuals!$E:$E,Actuals!$F:$F,Year!$C10,Actuals!$A:$A,Year!F$1) -> 432.06 | G10: =SUMIFS(Actuals!$E:$E,Actuals!$F:$F,Year!$C10,Actuals!$A:$A,Year!G$1) -> 532.52 | H10: =SUMIFS(Actuals!$E:$E,Actuals!$F:$F,Year!$C10,Actuals!$A:$A,Year!H$1) -> 296.68 | I10: =SUMIFS(Actuals!$E:$E,Actuals!$F:$F,Year!$C10,Actuals!$A:$A,Year!I$1) -> 719.26 | J10: =SUMIFS(Actuals!$E:$E,Actuals!$F:$F,Year!$C10,Actuals!$A:$A,Year!J$1) -> 373.78 | K10: =SUMIFS(Actuals!$E:$E,Actuals!$F:$F,Year!$C10,Actuals!$A:$A,Year!K$1) -> 127.46 | ... O10: =SUMIFS(Actuals!$E:$E,Actuals!$F:$F,Year!$C10,Actuals!$A:$A,Year!O$1) -> 32.64 | P10: =SUM(D10:O10) -> 4152.49 | R10: 4195.69 | S10: 6575 | T10: =R10-S10 -> -2379.31
C11: Utilities | D11: =SUMIFS(Actuals!$E:$E,Actuals!$F:$F,Year!$C11,Actuals!$A:$A,Year!D$1) -> 512.23 | E11: =SUMIFS(Actuals!$E:$E,Actuals!$F:$F,Year!$C11,Actuals!$A:$A,Year!E$1) -> 1454.37 | F11: =SUMIFS(Actuals!$E:$E,Actuals!$F:$F,Year!$C11,Actuals!$A:$A,Year!F$1) -> 404.52 | G11: =SUMIFS(Actuals!$E:$E,Actuals!$F:$F,Year!$C11,Actuals!$A:$A,Year!G$1) -> 507.12 | H11: =SUMIFS(Actuals!$E:$E,Actuals!$F:$F,Year!$C11,Actuals!$A:$A,Year!H$1) -> 726.93 | I11: =SUMIFS(Actuals!$E:$E,Actuals!$F:$F,Year!$C11,Actuals!$A:$A,Year!I$1) -> 2595.93 | J11: =SUMIFS(Actuals!$E:$E,Actuals!$F:$F,Year!$C11,Actuals!$A:$A,Year!J$1) -> 2949.64 | K11: =SUMIFS(Actuals!$E:$E,Actuals!$F:$F,Year!$C11,Actuals!$A:$A,Year!K$1) -> 744.52 | ... O11: =SUMIFS(Actuals!$E:$E,Actuals!$F:$F,Year!$C11,Actuals!$A:$A,Year!O$1) -> 1190.87 | P11: =SUM(D11:O11) -> 20671.47 | R11: 8490 | S11: 5694.76 | T11: =R11-S11 -> 2795.24
C12: Car Loan | D12: =SUMIFS(Actuals!$E:$E,Actuals!$F:$F,Year!$C12,Actuals!$A:$A,Year!D$1) -> 0 | E12: =SUMIFS(Actuals!$E:$E,Actuals!$F:$F,Year!$C12,Actuals!$A:$A,Year!E$1) -> 0 | F12: =SUMIFS(Actuals!$E:$E,Actuals!$F:$F,Year!$C12,Actuals!$A:$A,Year!F$1) -> 0 | G12: =SUMIFS(Actuals!$E:$E,Actuals!$F:$F,Year!$C12,Actuals!$A:$A,Year!G$1) -> 0 | H12: =SUMIFS(Actuals!$E:$E,Actuals!$F:$F,Year!$C12,Actuals!$A:$A,Year!H$1) -> 0 | I12: =SUMIFS(Actuals!$E:$E,Actuals!$F:$F,Year!$C12,Actuals!$A:$A,Year!I$1) -> 0 | J12: =SUMIFS(Actuals!$E:$E,Actuals!$F:$F,Year!$C12,Actuals!$A:$A,Year!J$1) -> 0 | K12: =SUMIFS(Actuals!$E:$E,Actuals!$F:$F,Year!$C12,Actuals!$A:$A,Year!K$1) -> 0 | ... O12: =SUMIFS(Actuals!$E:$E,Actuals!$F:$F,Year!$C12,Actuals!$A:$A,Year!O$1) -> 0 | P12: =SUM(D12:O12) -> 0 | R12: 0 | S12: 6186.5 | T12: =R12-S12 -> -6186.5
C13: Cleaning | D13: =SUMIFS(Actuals!$E:$E,Actuals!$F:$F,Year!$C13,Actuals!$A:$A,Year!D$1) -> 0 | E13: =SUMIFS(Actuals!$E:$E,Actuals!$F:$F,Year!$C13,Actuals!$A:$A,Year!E$1) -> 0 | F13: =SUMIFS(Actuals!$E:$E,Actuals!$F:$F,Year!$C13,Actuals!$A:$A,Year!F$1) -> 0 | G13: =SUMIFS(Actuals!$E:$E,Actuals!$F:$F,Year!$C13,Actuals!$A:$A,Year!G$1) -> 0 | H13: =SUMIFS(Actuals!$E:$E,Actuals!$F:$F,Year!$C13,Actuals!$A:$A,Year!H$1) -> 0 | I13: =SUMIFS(Actuals!$E:$E,Actuals!$F:$F,Year!$C13,Actuals!$A:$A,Year!I$1) -> 0 | J13: =SUMIFS(Actuals!$E:$E,Actuals!$F:$F,Year!$C13,Actuals!$A:$A,Year!J$1) -> 0 | K13: =SUMIFS(Actuals!$E:$E,Actuals!$F:$F,Year!$C13,Actuals!$A:$A,Year!K$1) -> 0 | ... O13: =SUMIFS(Actuals!$E:$E,Actuals!$F:$F,Year!$C13,Actuals!$A:$A,Year!O$1) -> 0 | P13: =SUM(D13:O13) -> 241.71 | R13: 3000 | S13: 1750 | T13: =R13-S13 -> 1250
C14: Insurance | D14: =SUMIFS(Actuals!$E:$E,Actuals!$F:$F,Year!$C14,Actuals!$A:$A,Year!D$1) -> 163.66 | E14: =SUMIFS(Actuals!$E:$E,Actuals!$F:$F,Year!$C14,Actuals!$A:$A,Year!E$1) -> 163.66 | F14: =SUMIFS(Actuals!$E:$E,Actuals!$F:$F,Year!$C14,Actuals!$A:$A,Year!F$1) -> 158.66 | G14: =SUMIFS(Actuals!$E:$E,Actuals!$F:$F,Year!$C14,Actuals!$A:$A,Year!G$1) -> 165.12 | H14: =SUMIFS(Actuals!$E:$E,Actuals!$F:$F,Year!$C14,Actuals!$A:$A,Year!H$1) -> 165.08 | I14: =SUMIFS(Actuals!$E:$E,Actuals!$F:$F,Year!$C14,Actuals!$A:$A,Year!I$1) -> 54.33 | J14: =SUMIFS(Actuals!$E:$E,Actuals!$F:$F,Year!$C14,Actuals!$A:$A,Year!J$1) -> 55.97 | K14: =SUMIFS(Actuals!$E:$E,Actuals!$F:$F,Year!$C14,Actuals!$A:$A,Year!K$1) -> 54.33 | ... O14: =SUMIFS(Actuals!$E:$E,Actuals!$F:$F,Year!$C14,Actuals!$A:$A,Year!O$1) -> 0 | P14: =SUM(D14:O14) -> 1089.47 | R14: 1631.65 | S14: 1620.98 | T14: =R14-S14 -> 10.67
C15: Day Care | D15: =SUMIFS(Actuals!$E:$E,Actuals!$F:$F,Year!$C15,Actuals!$A:$A,Year!D$1) -> 4201.12 | E15: =SUMIFS(Actuals!$E:$E,Actuals!$F:$F,Year!$C15,Actuals!$A:$A,Year!E$1) -> 2625.59 | F15: =SUMIFS(Actuals!$E:$E,Actuals!$F:$F,Year!$C15,Actuals!$A:$A,Year!F$1) -> 2505.21 | G15: =SUMIFS(Actuals!$E:$E,Actuals!$F:$F,Year!$C15,Actuals!$A:$A,Year!G$1) -> 2173.36 | H15: =SUMIFS(Actuals!$E:$E,Actuals!$F:$F,Year!$C15,Actuals!$A:$A,Year!H$1) -> 797.3 | I15: =SUMIFS(Actuals!$E:$E,Actuals!$F:$F,Year!$C15,Actuals!$A:$A,Year!I$1) -> 1371.1 | J15: =SUMIFS(Actuals!$E:$E,Actuals!$F:$F,Year!$C15,Actuals!$A:$A,Year!J$1) -> 2393 | K15: =SUMIFS(Actuals!$E:$E,Actuals!$F:$F,Year!$C15,Actuals!$A:$A,Year!K$1) -> 2344.51 | ... O15: =SUMIFS(Actuals!$E:$E,Actuals!$F:$F,Year!$C15,Actuals!$A:$A,Year!O$1) -> 495 | P15: =SUM(D15:O15) -> 23875.18 | R15: 27362.99 | S15: 24892.85 | T15: =R15-S15 -> 2470.14
C16: Total Rent & Utilitites | D16: =SUM(D9:D15) -> 7780.95 | E16: =SUM(E9:E15) -> 7061.46 | F16: =SUM(F9:F15) -> 5270.49 | G16: =SUM(G9:G15) -> 6123.55 | H16: =SUM(H9:H15) -> 4731.42 | I16: =SUM(I9:I15) -> 7486.05 | J16: =SUM(J9:J15) -> 8517.82 | K16: =SUM(K9:K15) -> 6016.25 | ... O16: =SUM(O9:O15) -> 5097.02 | P16: =SUM(D16:O16) -> 84532.41 | R16: 77595.97 | S16: 78537.21 | T16: =R16-S16 -> -941.24
T17: =R17-S17 -> 0
C18: Transportation | D18: =SUMIFS(Actuals!$E:$E,Actuals!$F:$F,Year!$C18,Actuals!$A:$A,Year!D$1) -> 36.35 | E18: =SUMIFS(Actuals!$E:$E,Actuals!$F:$F,Year!$C18,Actuals!$A:$A,Year!E$1) -> 1290.29 | F18: =SUMIFS(Actuals!$E:$E,Actuals!$F:$F,Year!$C18,Actuals!$A:$A,Year!F$1) -> 133.96 | G18: =SUMIFS(Actuals!$E:$E,Actuals!$F:$F,Year!$C18,Actuals!$A:$A,Year!G$1) -> 60.28 | H18: =SUMIFS(Actuals!$E:$E,Actuals!$F:$F,Year!$C18,Actuals!$A:$A,Year!H$1) -> 1459.98 | I18: =SUMIFS(Actuals!$E:$E,Actuals!$F:$F,Year!$C18,Actuals!$A:$A,Year!I$1) -> 86.91 | J18: =SUMIFS(Actuals!$E:$E,Actuals!$F:$F,Year!$C18,Actuals!$A:$A,Year!J$1) -> 993.97 | K18: =SUMIFS(Actuals!$E:$E,Actuals!$F:$F,Year!$C18,Actuals!$A:$A,Year!K$1) -> 47.12 | ... O18: =SUMIFS(Actuals!$E:$E,Actuals!$F:$F,Year!$C18,Actuals!$A:$A,Year!O$1) -> 225.45 | P18: =SUM(D18:O18) -> 4745.25 | R18: 4295.84 | S18: 9951.77 | T18: =R18-S18 -> -5655.93
C19: Restaurants | D19: =SUMIFS(Actuals!$E:$E,Actuals!$F:$F,Year!$C19,Actuals!$A:$A,Year!D$1) -> 1256.52 | E19: =SUMIFS(Actuals!$E:$E,Actuals!$F:$F,Year!$C19,Actuals!$A:$A,Year!E$1) -> 1258.33 | F19: =SUMIFS(Actuals!$E:$E,Actuals!$F:$F,Year!$C19,Actuals!$A:$A,Year!F$1) -> 2190.37 | G19: =SUMIFS(Actuals!$E:$E,Actuals!$F:$F,Year!$C19,Actuals!$A:$A,Year!G$1) -> 1732.92 | H19: =SUMIFS(Actuals!$E:$E,Actuals!$F:$F,Year!$C19,Actuals!$A:$A,Year!H$1) -> 1195.79 | I19: =SUMIFS(Actuals!$E:$E,Actuals!$F:$F,Year!$C19,Actuals!$A:$A,Year!I$1) -> 2520.29 | J19: =SUMIFS(Actuals!$E:$E,Actuals!$F:$F,Year!$C19,Actuals!$A:$A,Year!J$1) -> 2280.76 | K19: =SUMIFS(Actuals!$E:$E,Actuals!$F:$F,Year!$C19,Actuals!$A:$A,Year!K$1) -> 1833.45 | ... O19: =SUMIFS(Actuals!$E:$E,Actuals!$F:$F,Year!$C19,Actuals!$A:$A,Year!O$1) -> 1564.61 | P19: =SUM(D19:O19) -> 23100.66 | R19: 16610.65 | S19: 14017.98 | T19: =R19-S19 -> 2592.67
C20: Groceries | D20: =SUMIFS(Actuals!$E:$E,Actuals!$F:$F,Year!$C20,Actuals!$A:$A,Year!D$1) -> 1032.54 | E20: =SUMIFS(Actuals!$E:$E,Actuals!$F:$F,Year!$C20,Actuals!$A:$A,Year!E$1) -> 813.71 | F20: =SUMIFS(Actuals!$E:$E,Actuals!$F:$F,Year!$C20,Actuals!$A:$A,Year!F$1) -> 579.15 | G20: =SUMIFS(Actuals!$E:$E,Actuals!$F:$F,Year!$C20,Actuals!$A:$A,Year!G$1) -> 1295 | H20: =SUMIFS(Actuals!$E:$E,Actuals!$F:$F,Year!$C20,Actuals!$A:$A,Year!H$1) -> 1047.99 | I20: =SUMIFS(Actuals!$E:$E,Actuals!$F:$F,Year!$C20,Actuals!$A:$A,Year!I$1) -> 1176.28 | J20: =SUMIFS(Actuals!$E:$E,Actuals!$F:$F,Year!$C20,Actuals!$A:$A,Year!J$1) -> 341.28 | K20: =SUMIFS(Actuals!$E:$E,Actuals!$F:$F,Year!$C20,Actuals!$A:$A,Year!K$1) -> 1051.64 | ... O20: =SUMIFS(Actuals!$E:$E,Actuals!$F:$F,Year!$C20,Actuals!$A:$A,Year!O$1) -> 1139.06 | P20: =SUM(D20:O20) -> 11355.96 | R20: 11506.02 | S20: 10268.6 | T20: =R20-S20 -> 1237.42
C21: Target | D21: =SUMIFS(Actuals!$E:$E,Actuals!$F:$F,Year!$C21,Actuals!$A:$A,Year!D$1) -> 0 | E21: =SUMIFS(Actuals!$E:$E,Actuals!$F:$F,Year!$C21,Actuals!$A:$A,Year!E$1) -> 1466.2 | F21: =SUMIFS(Actuals!$E:$E,Actuals!$F:$F,Year!$C21,Actuals!$A:$A,Year!F$1) -> 1203.61 | G21: =SUMIFS(Actuals!$E:$E,Actuals!$F:$F,Year!$C21,Actuals!$A:$A,Year!G$1) -> 859 | H21: =SUMIFS(Actuals!$E:$E,Actuals!$F:$F,Year!$C21,Actuals!$A:$A,Year!H$1) -> 141.71 | I21: =SUMIFS(Actuals!$E:$E,Actuals!$F:$F,Year!$C21,Actuals!$A:$A,Year!I$1) -> 863.6 | J21: =SUMIFS(Actuals!$E:$E,Actuals!$F:$F,Year!$C21,Actuals!$A:$A,Year!J$1) -> 138.78 | K21: =SUMIFS(Actuals!$E:$E,Actuals!$F:$F,Year!$C21,Actuals!$A:$A,Year!K$1) -> 519.11 | ... O21: =SUMIFS(Actuals!$E:$E,Actuals!$F:$F,Year!$C21,Actuals!$A:$A,Year!O$1) -> 818.16 | P21: =SUM(D21:O21) -> 8438.87 | R21: 8093.31 | S21: 4850.69 | T21: =R21-S21 -> 3242.62
C22: Total Food & Car | D22: =SUM(D18:D21) -> 2325.41 | E22: =SUM(E18:E21) -> 4828.53 | F22: =SUM(F18:F21) -> 4107.09 | G22: =SUM(G18:G21) -> 3947.2 | H22: =SUM(H18:H21) -> 3845.47 | I22: =SUM(I18:I21) -> 4647.08 | J22: =SUM(J18:J21) -> 3754.79 | K22: =SUM(K18:K21) -> 3451.32 | ... O22: =SUM(O18:O21) -> 3747.28 | P22: =SUM(D22:O22) -> 47640.74 | R22: 40505.82 | S22: 39089.04 | T22: =R22-S22 -> 1416.78
T23: =R23-S23 -> 0
C24: Gym | D24: =SUMIFS(Actuals!$E:$E,Actuals!$F:$F,Year!$C24,Actuals!$A:$A,Year!D$1) -> 0 | E24: =SUMIFS(Actuals!$E:$E,Actuals!$F:$F,Year!$C24,Actuals!$A:$A,Year!E$1) -> 0 | F24: =SUMIFS(Actuals!$E:$E,Actuals!$F:$F,Year!$C24,Actuals!$A:$A,Year!F$1) -> 0 | G24: =SUMIFS(Actuals!$E:$E,Actuals!$F:$F,Year!$C24,Actuals!$A:$A,Year!G$1) -> 0 | H24: =SUMIFS(Actuals!$E:$E,Actuals!$F:$F,Year!$C24,Actuals!$A:$A,Year!H$1) -> 0 | I24: =SUMIFS(Actuals!$E:$E,Actuals!$F:$F,Year!$C24,Actuals!$A:$A,Year!I$1) -> 25 | J24: =SUMIFS(Actuals!$E:$E,Actuals!$F:$F,Year!$C24,Actuals!$A:$A,Year!J$1) -> 0 | K24: =SUMIFS(Actuals!$E:$E,Actuals!$F:$F,Year!$C24,Actuals!$A:$A,Year!K$1) -> 0 | ... O24: =SUMIFS(Actuals!$E:$E,Actuals!$F:$F,Year!$C24,Actuals!$A:$A,Year!O$1) -> 0 | P24: =SUM(D24:O24) -> 25 | R24: 381.52 | S24: 568.32 | T24: =R24-S24 -> -186.8
C25: Shopping | D25: =SUMIFS(Actuals!$E:$E,Actuals!$F:$F,Year!$C25,Actuals!$A:$A,Year!D$1) -> 1297.56 | E25: =SUMIFS(Actuals!$E:$E,Actuals!$F:$F,Year!$C25,Actuals!$A:$A,Year!E$1) -> 2152.23 | F25: =SUMIFS(Actuals!$E:$E,Actuals!$F:$F,Year!$C25,Actuals!$A:$A,Year!F$1) -> 2367.63 | G25: =SUMIFS(Actuals!$E:$E,Actuals!$F:$F,Year!$C25,Actuals!$A:$A,Year!G$1) -> 944.14 | H25: =SUMIFS(Actuals!$E:$E,Actuals!$F:$F,Year!$C25,Actuals!$A:$A,Year!H$1) -> 2601 | I25: =SUMIFS(Actuals!$E:$E,Actuals!$F:$F,Year!$C25,Actuals!$A:$A,Year!I$1) -> 1527.95 | J25: =SUMIFS(Actuals!$E:$E,Actuals!$F:$F,Year!$C25,Actuals!$A:$A,Year!J$1) -> -26.29 | K25: =SUMIFS(Actuals!$E:$E,Actuals!$F:$F,Year!$C25,Actuals!$A:$A,Year!K$1) -> 2243.56 | ... O25: =SUMIFS(Actuals!$E:$E,Actuals!$F:$F,Year!$C25,Actuals!$A:$A,Year!O$1) -> 1902.83 | P25: =SUM(D25:O25) -> 21636.39 | R25: 24464.17 | S25: 36968.91 | T25: =R25-S25 -> -12504.74
C26: Amazon | D26: =SUMIFS(Actuals!$E:$E,Actuals!$F:$F,Year!$C26,Actuals!$A:$A,Year!D$1) -> 1330.21 | E26: =SUMIFS(Actuals!$E:$E,Actuals!$F:$F,Year!$C26,Actuals!$A:$A,Year!E$1) -> 628.87 | F26: =SUMIFS(Actuals!$E:$E,Actuals!$F:$F,Year!$C26,Actuals!$A:$A,Year!F$1) -> 468.29 | G26: =SUMIFS(Actuals!$E:$E,Actuals!$F:$F,Year!$C26,Actuals!$A:$A,Year!G$1) -> 883.33 | H26: =SUMIFS(Actuals!$E:$E,Actuals!$F:$F,Year!$C26,Actuals!$A:$A,Year!H$1) -> 361.54 | I26: =SUMIFS(Actuals!$E:$E,Actuals!$F:$F,Year!$C26,Actuals!$A:$A,Year!I$1) -> 4.01 | J26: =SUMIFS(Actuals!$E:$E,Actuals!$F:$F,Year!$C26,Actuals!$A:$A,Year!J$1) -> -0.15 | K26: =SUMIFS(Actuals!$E:$E,Actuals!$F:$F,Year!$C26,Actuals!$A:$A,Year!K$1) -> 26.49 | ... O26: =SUMIFS(Actuals!$E:$E,Actuals!$F:$F,Year!$C26,Actuals!$A:$A,Year!O$1) -> 1212.46 | P26: =SUM(D26:O26) -> 5621.16 | R26: 7001.74 | S26: 6149.75 | T26: =R26-S26 -> 851.99
C27: Entertainment | D27: =SUMIFS(Actuals!$E:$E,Actuals!$F:$F,Year!$C27,Actuals!$A:$A,Year!D$1) -> 452.17 | E27: =SUMIFS(Actuals!$E:$E,Actuals!$F:$F,Year!$C27,Actuals!$A:$A,Year!E$1) -> 213.46 | F27: =SUMIFS(Actuals!$E:$E,Actuals!$F:$F,Year!$C27,Actuals!$A:$A,Year!F$1) -> 547.24 | G27: =SUMIFS(Actuals!$E:$E,Actuals!$F:$F,Year!$C27,Actuals!$A:$A,Year!G$1) -> 214.29 | H27: =SUMIFS(Actuals!$E:$E,Actuals!$F:$F,Year!$C27,Actuals!$A:$A,Year!H$1) -> 151.35 | I27: =SUMIFS(Actuals!$E:$E,Actuals!$F:$F,Year!$C27,Actuals!$A:$A,Year!I$1) -> 365.79 | J27: =SUMIFS(Actuals!$E:$E,Actuals!$F:$F,Year!$C27,Actuals!$A:$A,Year!J$1) -> 447.19 | K27: =SUMIFS(Actuals!$E:$E,Actuals!$F:$F,Year!$C27,Actuals!$A:$A,Year!K$1) -> 522.8 | ... O27: =SUMIFS(Actuals!$E:$E,Actuals!$F:$F,Year!$C27,Actuals!$A:$A,Year!O$1) -> 278.84 | P27: =SUM(D27:O27) -> 3681.42 | R27: 7135.13 | S27: 3003.38 | T27: =R27-S27 -> 4131.75
C28: Dry Cleaning | D28: =SUMIFS(Actuals!$E:$E,Actuals!$F:$F,Year!$C28,Actuals!$A:$A,Year!D$1) -> 0 | E28: =SUMIFS(Actuals!$E:$E,Actuals!$F:$F,Year!$C28,Actuals!$A:$A,Year!E$1) -> 0 | F28: =SUMIFS(Actuals!$E:$E,Actuals!$F:$F,Year!$C28,Actuals!$A:$A,Year!F$1) -> 0 | G28: =SUMIFS(Actuals!$E:$E,Actuals!$F:$F,Year!$C28,Actuals!$A:$A,Year!G$1) -> 36.6 | H28: =SUMIFS(Actuals!$E:$E,Actuals!$F:$F,Year!$C28,Actuals!$A:$A,Year!H$1) -> 0 | I28: =SUMIFS(Actuals!$E:$E,Actuals!$F:$F,Year!$C28,Actuals!$A:$A,Year!I$1) -> 35.93 | J28: =SUMIFS(Actuals!$E:$E,Actuals!$F:$F,Year!$C28,Actuals!$A:$A,Year!J$1) -> 113.36 | K28: =SUMIFS(Actuals!$E:$E,Actuals!$F:$F,Year!$C28,Actuals!$A:$A,Year!K$1) -> 59.35 | ... O28: =SUMIFS(Actuals!$E:$E,Actuals!$F:$F,Year!$C28,Actuals!$A:$A,Year!O$1) -> 0 | P28: =SUM(D28:O28) -> 406.58 | R28: 537.86 | S28: 346.41 | T28: =R28-S28 -> 191.45
C29: Gifts | D29: =SUMIFS(Actuals!$E:$E,Actuals!$F:$F,Year!$C29,Actuals!$A:$A,Year!D$1) -> 0 | E29: =SUMIFS(Actuals!$E:$E,Actuals!$F:$F,Year!$C29,Actuals!$A:$A,Year!E$1) -> 0 | F29: =SUMIFS(Actuals!$E:$E,Actuals!$F:$F,Year!$C29,Actuals!$A:$A,Year!F$1) -> 0 | G29: =SUMIFS(Actuals!$E:$E,Actuals!$F:$F,Year!$C29,Actuals!$A:$A,Year!G$1) -> 0 | H29: =SUMIFS(Actuals!$E:$E,Actuals!$F:$F,Year!$C29,Actuals!$A:$A,Year!H$1) -> 0 | I29: =SUMIFS(Actuals!$E:$E,Actuals!$F:$F,Year!$C29,Actuals!$A:$A,Year!I$1) -> 0 | J29: =SUMIFS(Actuals!$E:$E,Actuals!$F:$F,Year!$C29,Actuals!$A:$A,Year!J$1) -> 0 | K29: =SUMIFS(Actuals!$E:$E,Actuals!$F:$F,Year!$C29,Actuals!$A:$A,Year!K$1) -> 0 | ... O29: =SUMIFS(Actuals!$E:$E,Actuals!$F:$F,Year!$C29,Actuals!$A:$A,Year!O$1) -> 282.75 | P29: =SUM(D29:O29) -> 594.78 | R29: 780.65 | S29: 1066.78 | T29: =R29-S29 -> -286.13
C30: Misc | D30: =SUMIFS(Actuals!$E:$E,Actuals!$F:$F,Year!$C30,Actuals!$A:$A,Year!D$1) -> 110 | E30: =SUMIFS(Actuals!$E:$E,Actuals!$F:$F,Year!$C30,Actuals!$A:$A,Year!E$1) -> 0 | F30: =SUMIFS(Actuals!$E:$E,Actuals!$F:$F,Year!$C30,Actuals!$A:$A,Year!F$1) -> 0 | G30: =SUMIFS(Actuals!$E:$E,Actuals!$F:$F,Year!$C30,Actuals!$A:$A,Year!G$1) -> 124 | H30: =SUMIFS(Actuals!$E:$E,Actuals!$F:$F,Year!$C30,Actuals!$A:$A,Year!H$1) -> 0 | I30: =SUMIFS(Actuals!$E:$E,Actuals!$F:$F,Year!$C30,Actuals!$A:$A,Year!I$1) -> 5 | J30: =SUMIFS(Actuals!$E:$E,Actuals!$F:$F,Year!$C30,Actuals!$A:$A,Year!J$1) -> 0 | K30: =SUMIFS(Actuals!$E:$E,Actuals!$F:$F,Year!$C30,Actuals!$A:$A,Year!K$1) -> 0 | ... O30: =SUMIFS(Actuals!$E:$E,Actuals!$F:$F,Year!$C30,Actuals!$A:$A,Year!O$1) -> 8.15 | P30: =SUM(D30:O30) -> 421.02 | R30: 527.85 | S30: 793.34 | T30: =R30-S30 -> -265.49
C31: Total Other | D31: =SUM(D24:D30) -> 3189.94 | E31: =SUM(E24:E30) -> 2994.56 | F31: =SUM(F24:F30) -> 3383.16 | G31: =SUM(G24:G30) -> 2202.36 | H31: =SUM(H24:H30) -> 3113.89 | I31: =SUM(I24:I30) -> 1963.68 | J31: =SUM(J24:J30) -> 534.11 | K31: =SUM(K24:K30) -> 2852.2 | ... O31: =SUM(O24:O30) -> 3685.03 | P31: =SUM(D31:O31) -> 32386.35 | R31: 40828.92 | S31: 48896.89 | T31: =R31-S31 -> -8067.97
P32: =SUM(D32:O32) -> 0 | R32: 0 | S32: 0 | T32: =R32-S32 -> 0
C33: Total | D33: =SUM(D31,D22,D16) -> 13296.3 | E33: =SUM(E31,E22,E16) -> 14884.55 | F33: =SUM(F31,F22,F16) -> 12760.74 | G33: =SUM(G31,G22,G16) -> 12273.11 | H33: =SUM(H31,H22,H16) -> 11690.78 | I33: =SUM(I31,I22,I16) -> 14096.81 | J33: =SUM(J31,J22,J16) -> 12806.72 | K33: =SUM(K31,K22,K16) -> 12319.77 | ... O33: =SUM(O31,O22,O16) -> 12529.33 | P33: =SUM(D33:O33) -> 164559.5 | R33: 158930.71 | S33: 166523.14 | T33: =R33-S33 -> -7592.43
T34: =R34-S34 -> 0
C35: Healthcare | D35: =SUMIFS(Actuals!$E:$E,Actuals!$F:$F,Year!$C35,Actuals!$A:$A,Year!D$1) -> 555.18 | E35: =SUMIFS(Actuals!$E:$E,Actuals!$F:$F,Year!$C35,Actuals!$A:$A,Year!E$1) -> 246.17 | F35: =SUMIFS(Actuals!$E:$E,Actuals!$F:$F,Year!$C35,Actuals!$A:$A,Year!F$1) -> 227.94 | G35: =SUMIFS(Actuals!$E:$E,Actuals!$F:$F,Year!$C35,Actuals!$A:$A,Year!G$1) -> 0 | H35: =SUMIFS(Actuals!$E:$E,Actuals!$F:$F,Year!$C35,Actuals!$A:$A,Year!H$1) -> 253.53 | I35: =SUMIFS(Actuals!$E:$E,Actuals!$F:$F,Year!$C35,Actuals!$A:$A,Year!I$1) -> -14.1 | J35: =SUMIFS(Actuals!$E:$E,Actuals!$F:$F,Year!$C35,Actuals!$A:$A,Year!J$1) -> 124.06 | K35: =SUMIFS(Actuals!$E:$E,Actuals!$F:$F,Year!$C35,Actuals!$A:$A,Year!K$1) -> 0 | ... O35: =SUMIFS(Actuals!$E:$E,Actuals!$F:$F,Year!$C35,Actuals!$A:$A,Year!O$1) -> 1285.7 | P35: =SUM(D35:O35) -> 3948.01 | R35: 2527.44 | S35: 4800.59 | T35: =R35-S35 -> -2273.15
C36: House | D36: =SUMIFS(Actuals!$E:$E,Actuals!$F:$F,Year!$C36,Actuals!$A:$A,Year!D$1) -> 30245.75 | E36: =SUMIFS(Actuals!$E:$E,Actuals!$F:$F,Year!$C36,Actuals!$A:$A,Year!E$1) -> 8816.97 | F36: =SUMIFS(Actuals!$E:$E,Actuals!$F:$F,Year!$C36,Actuals!$A:$A,Year!F$1) -> 24509 | G36: =SUMIFS(Actuals!$E:$E,Actuals!$F:$F,Year!$C36,Actuals!$A:$A,Year!G$1) -> 18027 | H36: =SUMIFS(Actuals!$E:$E,Actuals!$F:$F,Year!$C36,Actuals!$A:$A,Year!H$1) -> 5053.11 | I36: =SUMIFS(Actuals!$E:$E,Actuals!$F:$F,Year!$C36,Actuals!$A:$A,Year!I$1) -> 43385.5 | J36: =SUMIFS(Actuals!$E:$E,Actuals!$F:$F,Year!$C36,Actuals!$A:$A,Year!J$1) -> 48339 | K36: =SUMIFS(Actuals!$E:$E,Actuals!$F:$F,Year!$C36,Actuals!$A:$A,Year!K$1) -> 52 | ... O36: =SUMIFS(Actuals!$E:$E,Actuals!$F:$F,Year!$C36,Actuals!$A:$A,Year!O$1) -> 0 | P36: =SUM(D36:O36) -> 265799.33 | R36: 11572.24 | S36: 2970.47 | T36: =R36-S36 -> 8601.77
C37: Travel | D37: =SUMIFS(Actuals!$E:$E,Actuals!$F:$F,Year!$C37,Actuals!$A:$A,Year!D$1) -> 2336.15 | E37: =SUMIFS(Actuals!$E:$E,Actuals!$F:$F,Year!$C37,Actuals!$A:$A,Year!E$1) -> 213.11 | F37: =SUMIFS(Actuals!$E:$E,Actuals!$F:$F,Year!$C37,Actuals!$A:$A,Year!F$1) -> 908.1 | G37: =SUMIFS(Actuals!$E:$E,Actuals!$F:$F,Year!$C37,Actuals!$A:$A,Year!G$1) -> 513.21 | H37: =SUMIFS(Actuals!$E:$E,Actuals!$F:$F,Year!$C37,Actuals!$A:$A,Year!H$1) -> 997.66 | I37: =SUMIFS(Actuals!$E:$E,Actuals!$F:$F,Year!$C37,Actuals!$A:$A,Year!I$1) -> 468.69 | J37: =SUMIFS(Actuals!$E:$E,Actuals!$F:$F,Year!$C37,Actuals!$A:$A,Year!J$1) -> 744.33 | K37: =SUMIFS(Actuals!$E:$E,Actuals!$F:$F,Year!$C37,Actuals!$A:$A,Year!K$1) -> 2249.71 | ... O37: =SUMIFS(Actuals!$E:$E,Actuals!$F:$F,Year!$C37,Actuals!$A:$A,Year!O$1) -> 1788.34 | P37: =SUM(D37:O37) -> 16470.36 | R37: 18097.97 | S37: 29958.75 | T37: =R37-S37 -> -11860.78
C38: Total Yearly | D38: =SUM(D35:D37) -> 33137.08 | E38: =SUM(E35:E37) -> 9276.25 | F38: =SUM(F35:F37) -> 25645.04 | G38: =SUM(G35:G37) -> 18540.21 | H38: =SUM(H35:H37) -> 6304.3 | I38: =SUM(I35:I37) -> 43840.09 | J38: =SUM(J35:J37) -> 49207.39 | K38: =SUM(K35:K37) -> 2301.71 | ... P38: =SUM(P35:P37) -> 286217.7 | R38: 32197.65 | S38: 37729.81 | T38: =R38-S38 -> -5532.16
T39: =R39-S39 -> 0
C40: Total All Spend | D40: =SUM(D38,D33) -> 46433.38 | E40: =SUM(E38,E33) -> 24160.8 | F40: =SUM(F38,F33) -> 38405.78 | G40: =SUM(G38,G33) -> 30813.32 | H40: =SUM(H38,H33) -> 17995.08 | I40: =SUM(I38,I33) -> 57936.9 | J40: =SUM(J38,J33) -> 62014.11 | K40: =SUM(K38,K33) -> 14621.48 | ... P40: =SUM(P38,P33) -> 450777.2 | R40: 191128.36 | S40: 204252.95 | T40: =R40-S40 -> -13124.59

Sheet Revised
D1: =VALUE('1 MO'!$C$3&"01") -> 202501 | E1: =VALUE('1 MO'!$C$3&"02") -> 202502 | F1: =VALUE('1 MO'!$C$3&"03") -> 202503 | G1: =VALUE('1 MO'!$C$3&"04") -> 202504 | H1: =VALUE('1 MO'!$C$3&"05") -> 202505 | I1: =VALUE('1 MO'!$C$3&"06") -> 202506 | J1: =VALUE('1 MO'!$C$3&"07") -> 202507 | K1: =VALUE('1 MO'!$C$3&"08") -> 202508 | L1: =VALUE('1 MO'!$C$3&"09") -> 202509 | M1: =VALUE('1 MO'!$C$3&"10") -> 202510 | N1: =VALUE('1 MO'!$C$3&"11") -> 202511 | O1: =VALUE('1 MO'!$C$3&"12") -> 202512
C6: Revised Budget | D6: SUMIFS(Actuals!$E:$E,Actuals!$F:$F,Revised!$C11,Actuals!$A:$A,Revised!D$1)
D7: Actual
D8: =TEXT(DATE(LEFT(D1,4),RIGHT(D1,2),1),"MMM YYYY") -> Jan 2025 | E8: =TEXT(DATE(LEFT(E1,4),RIGHT(E1,2),1),"MMM YYYY") -> Feb 2025 | F8: =TEXT(DATE(LEFT(F1,4),RIGHT(F1,2),1),"MMM YYYY") -> Mar 2025 | G8: =TEXT(DATE(LEFT(G1,4),RIGHT(G1,2),1),"MMM YYYY") -> Apr 2025 | H8: =TEXT(DATE(LEFT(H1,4),RIGHT(H1,2),1),"MMM YYYY") -> May 2025 | I8: =TEXT(DATE(LEFT(I1,4),RIGHT(I1,2),1),"MMM YYYY") -> Jun 2025 | J8: =TEXT(DATE(LEFT(J1,4),RIGHT(J1,2),1),"MMM YYYY") -> Jul 2025 | K8: =TEXT(DATE(LEFT(K1,4),RIGHT(K1,2),1),"MMM YYYY") -> Aug 2025 | ... O8: =TEXT(DATE(LEFT(O1,4),RIGHT(O1,2),1),"MMM YYYY") -> Dec 2025 | P8: Total
C10: Rent | D10: =Year!D9 -> 2745.43 | E10: =Year!E9 -> 2745.43 | F10: =Year!F9 -> 1770.04 | G10: =Year!G9 -> 2745.43 | H10: =Year!H9 -> 2745.43 | I10: =Year!I9 -> 2745.43 | J10: =Year!J9 -> 2745.43 | K10: =Year!K9 -> 2745.43 | ... O10: =Year!O9 -> 3378.51 | P10: =SUM(D10:O10) -> 34502.09
C11: House Maintenance | D11: =Year!D10 -> 158.51 | E11: =Year!E10 -> 72.41 | F11: =Year!F10 -> 432.06 | G11: =Year!G10 -> 532.52 | H11: =Year!H10 -> 296.68 | I11: =Year!I10 -> 719.26 | J11: =Year!J10 -> 373.78 | K11: =Year!K10 -> 127.46 | ... O11: =Year!O10 -> 32.64 | P11: =SUM(D11:O11) -> 4152.49
C12: Utilities | D12: =Year!D11 -> 512.23 | E12: =Year!E11 -> 1454.37 | F12: =Year!F11 -> 404.52 | G12: =Year!G11 -> 507.12 | H12: =Year!H11 -> 726.93 | I12: =Year!I11 -> 2595.93 | J12: =Year!J11 -> 2949.64 | K12: =Year!K11 -> 744.52 | ... O12: =Year!O11 -> 1190.87 | P12: =SUM(D12:O12) -> 20671.47
C13: Car Loan | D13: =Year!D12 -> 0 | E13: =Year!E12 -> 0 | F13: =Year!F12 -> 0 | G13: =Year!G12 -> 0 | H13: =Year!H12 -> 0 | I13: =Year!I12 -> 0 | J13: =Year!J12 -> 0 | K13: =Year!K12 -> 0 | ... O13: =Year!O12 -> 0 | P13: =SUM(D13:O13) -> 0
C14: Cleaning | D14: =Year!D13 -> 0 | E14: =Year!E13 -> 0 | F14: =Year!F13 -> 0 | G14: =Year!G13 -> 0 | H14: =Year!H13 -> 0 | I14: =Year!I13 -> 0 | J14: =Year!J13 -> 0 | K14: =Year!K13 -> 0 | ... O14: =Year!O13 -> 0 | P14: =SUM(D14:O14) -> 241.71
C15: Insurance | D15: =Year!D14 -> 163.66 | E15: =Year!E14 -> 163.66 | F15: =Year!F14 -> 158.66 | G15: =Year!G14 -> 165.12 | H15: =Year!H14 -> 165.08 | I15: =Year!I14 -> 54.33 | J15: =Year!J14 -> 55.97 | K15: =Year!K14 -> 54.33 | ... O15: =Year!O14 -> 0 | P15: =SUM(D15:O15) -> 1089.47
C16: Day Care | D16: =Year!D15 -> 4201.12 | E16: =Year!E15 -> 2625.59 | F16: =Year!F15 -> 2505.21 | G16: =Year!G15 -> 2173.36 | H16: =Year!H15 -> 797.3 | I16: =Year!I15 -> 1371.1 | J16: =Year!J15 -> 2393 | K16: =Year!K15 -> 2344.51 | ... O16: =Year!O15 -> 495 | P16: =SUM(D16:O16) -> 23875.18
C17: Total Rent & Utilitites | D17: =SUM(D10:D16) -> 7780.95 | E17: =SUM(E10:E16) -> 7061.46 | F17: =SUM(F10:F16) -> 5270.49 | G17: =SUM(G10:G16) -> 6123.55 | H17: =SUM(H10:H16) -> 4731.42 | I17: =SUM(I10:I16) -> 7486.05 | J17: =SUM(J10:J16) -> 8517.82 | K17: =SUM(K10:K16) -> 6016.25 | ... O17: =SUM(O10:O16) -> 5097.02 | P17: =SUM(D17:O17) -> 84532.41
C19: Transportation | D19: =Year!D18 -> 36.35 | E19: =Year!E18 -> 1290.29 | F19: =Year!F18 -> 133.96 | G19: =Year!G18 -> 60.28 | H19: =Year!H18 -> 1459.98 | I19: =Year!I18 -> 86.91 | J19: =Year!J18 -> 993.97 | K19: =Year!K18 -> 47.12 | ... O19: =Year!O18 -> 225.45 | P19: =SUM(D19:O19) -> 4745.25
C20: Restaurants | D20: =Year!D19 -> 1256.52 | E20: =Year!E19 -> 1258.33 | F20: =Year!F19 -> 2190.37 | G20: =Year!G19 -> 1732.92 | H20: =Year!H19 -> 1195.79 | I20: =Year!I19 -> 2520.29 | J20: =Year!J19 -> 2280.76 | K20: =Year!K19 -> 1833.45 | ... O20: =Year!O19 -> 1564.61 | P20: =SUM(D20:O20) -> 23100.66
C21: Groceries | D21: =Year!D20 -> 1032.54 | E21: =Year!E20 -> 813.71 | F21: =Year!F20 -> 579.15 | G21: =Year!G20 -> 1295 | H21: =Year!H20 -> 1047.99 | I21: =Year!I20 -> 1176.28 | J21: =Year!J20 -> 341.28 | K21: =Year!K20 -> 1051.64 | ... O21: =Year!O20 -> 1139.06 | P21: =SUM(D21:O21) -> 11355.96
C22: Target | D22: =Year!D21 -> 0 | E22: =Year!E21 -> 1466.2 | F22: =Year!F21 -> 1203.61 | G22: =Year!G21 -> 859 | H22: =Year!H21 -> 141.71 | I22: =Year!I21 -> 863.6 | J22: =Year!J21 -> 138.78 | K22: =Year!K21 -> 519.11 | ... O22: =Year!O21 -> 818.16 | P22: =SUM(D22:O22) -> 8438.87
C23: Total Food & Car | D23: =SUM(D19:D22) -> 2325.41 | E23: =SUM(E19:E22) -> 4828.53 | F23: =SUM(F19:F22) -> 4107.09 | G23: =SUM(G19:G22) -> 3947.2 | H23: =SUM(H19:H22) -> 3845.47 | I23: =SUM(I19:I22) -> 4647.08 | J23: =SUM(J19:J22) -> 3754.79 | K23: =SUM(K19:K22) -> 3451.32 | ... O23: =SUM(O19:O22) -> 3747.28 | P23: =SUM(D23:O23) -> 47640.74
C25: Gym | D25: =Year!D24 -> 0 | E25: =Year!E24 -> 0 | F25: =Year!F24 -> 0 | G25: =Year!G24 -> 0 | H25: =Year!H24 -> 0 | I25: =Year!I24 -> 25 | J25: =Year!J24 -> 0 | K25: =Year!K24 -> 0 | ... O25: =Year!O24 -> 0 | P25: =SUM(D25:O25) -> 25
C26: Shopping | D26: =Year!D25 -> 1297.56 | E26: =Year!E25 -> 2152.23 | F26: =Year!F25 -> 2367.63 | G26: =Year!G25 -> 944.14 | H26: =Year!H25 -> 2601 | I26: =Year!I25 -> 1527.95 | J26: =Year!J25 -> -26.29 | K26: =Year!K25 -> 2243.56 | ... O26: =Year!O25 -> 1902.83 | P26: =SUM(D26:O26) -> 21636.39
C27: Amazon | D27: =Year!D26 -> 1330.21 | E27: =Year!E26 -> 628.87 | F27: =Year!F26 -> 468.29 | G27: =Year!G26 -> 883.33 | H27: =Year!H26 -> 361.54 | I27: =Year!I26 -> 4.01 | J27: =Year!J26 -> -0.15 | K27: =Year!K26 -> 26.49 | ... O27: =Year!O26 -> 1212.46 | P27: =SUM(D27:O27) -> 5621.16
C28: Entertainment | D28: =Year!D27 -> 452.17 | E28: =Year!E27 -> 213.46 | F28: =Year!F27 -> 547.24 | G28: =Year!G27 -> 214.29 | H28: =Year!H27 -> 151.35 | I28: =Year!I27 -> 365.79 | J28: =Year!J27 -> 447.19 | K28: =Year!K27 -> 522.8 | ... O28: =Year!O27 -> 278.84 | P28: =SUM(D28:O28) -> 3681.42
C29: Dry Cleaning | D29: =Year!D28 -> 0 | E29: =Year!E28 -> 0 | F29: =Year!F28 -> 0 | G29: =Year!G28 -> 36.6 | H29: =Year!H28 -> 0 | I29: =Year!I28 -> 35.93 | J29: =Year!J28 -> 113.36 | K29: =Year!K28 -> 59.35 | ... O29: =Year!O28 -> 0 | P29: =SUM(D29:O29) -> 406.58
C30: Gifts | D30: =Year!D29 -> 0 | E30: =Year!E29 -> 0 | F30: =Year!F29 -> 0 | G30: =Year!G29 -> 0 | H30: =Year!H29 -> 0 | I30: =Year!I29 -> 0 | J30: =Year!J29 -> 0 | K30: =Year!K29 -> 0 | ... O30: =Year!O29 -> 282.75 | P30: =SUM(D30:O30) -> 594.78
C31: Misc | D31: =Year!D30 -> 110 | E31: =Year!E30 -> 0 | F31: =Year!F30 -> 0 | G31: =Year!G30 -> 124 | H31: =Year!H30 -> 0 | I31: =Year!I30 -> 5 | J31: =Year!J30 -> 0 | K31: =Year!K30 -> 0 | ... O31: =Year!O30 -> 8.15 | P31: =SUM(D31:O31) -> 421.02
C32: Total Other | D32: =SUM(D25:D31) -> 3189.94 | E32: =SUM(E25:E31) -> 2994.56 | F32: =SUM(F25:F31) -> 3383.16 | G32: =SUM(G25:G31) -> 2202.36 | H32: =SUM(H25:H31) -> 3113.89 | I32: =SUM(I25:I31) -> 1963.68 | J32: =SUM(J25:J31) -> 534.11 | K32: =SUM(K25:K31) -> 2852.2 | ... O32: =SUM(O25:O31) -> 3685.03 | P32: =SUM(D32:O32) -> 32386.35
P33: =SUM(D33:O33) -> 0
C34: Total | D34: =SUM(D32,D23,D17) -> 13296.3 | E34: =SUM(E32,E23,E17) -> 14884.55 | F34: =SUM(F32,F23,F17) -> 12760.74 | G34: =SUM(G32,G23,G17) -> 12273.11 | H34: =SUM(H32,H23,H17) -> 11690.78 | I34: =SUM(I32,I23,I17) -> 14096.81 | J34: =SUM(J32,J23,J17) -> 12806.72 | K34: =SUM(K32,K23,K17) -> 12319.77 | ... O34: =SUM(O32,O23,O17) -> 12529.33 | P34: =SUM(D34:O34) -> 164559.5
C36: Healthcare | D36: =Year!D35 -> 555.18 | E36: =Year!E35 -> 246.17 | F36: =Year!F35 -> 227.94 | G36: =Year!G35 -> 0 | H36: =Year!H35 -> 253.53 | I36: =Year!I35 -> -14.1 | J36: =Year!J35 -> 124.06 | K36: =Year!K35 -> 0 | ... O36: =Year!O35 -> 1285.7 | P36: =SUM(D36:O36) -> 3948.01
C37: House | D37: =Year!D36 -> 30245.75 | E37: =Year!E36 -> 8816.97 | F37: =Year!F36 -> 24509 | G37: =Year!G36 -> 18027 | H37: =Year!H36 -> 5053.11 | I37: =Year!I36 -> 43385.5 | J37: =Year!J36 -> 48339 | K37: =Year!K36 -> 52 | ... O37: =Year!O36 -> 0 | P37: =SUM(D37:O37) -> 265799.33
C38: Travel | D38: =Year!D37 -> 2336.15 | E38: =Year!E37 -> 213.11 | F38: =Year!F37 -> 908.1 | G38: =Year!G37 -> 513.21 | H38: =Year!H37 -> 997.66 | I38: =Year!I37 -> 468.69 | J38: =Year!J37 -> 744.33 | K38: =Year!K37 -> 2249.71 | ... O38: =Year!O37 -> 1788.34 | P38: =SUM(D38:O38) -> 16470.36
C39: Total Yearly | D39: =SUM(D36:D38) -> 33137.08 | E39: =SUM(E36:E38) -> 9276.25 | F39: =SUM(F36:F38) -> 25645.04 | G39: =SUM(G36:G38) -> 18540.21 | H39: =SUM(H36:H38) -> 6304.3 | I39: =SUM(I36:I38) -> 43840.09 | J39: =SUM(J36:J38) -> 49207.39 | K39: =SUM(K36:K38) -> 2301.71 | ... P39: =SUM(P36:P38) -> 286217.7
P41: =SUM(D41:O41) -> 0
P42: =SUM(D42:O42) -> 0
P43: =SUM(D43:O43) -> 0
P44: =SUM(D44:O44) -> 0
C45: Additional | D45: =SUM(D41:D44) -> 0 | E45: =SUM(E41:E44) -> 0 | F45: =SUM(F41:F44) -> 0 | G45: =SUM(G41:G44) -> 0 | H45: =SUM(H41:H44) -> 0 | I45: =SUM(I41:I44) -> 0 | J45: =SUM(J41:J44) -> 0 | K45: =SUM(K41:K44) -> 0 | ... O45: =SUM(O41:O44) -> 0 | P45: =SUM(D45:O45) -> 0
C47: Total All Spend | D47: =SUM(D39,D34) -> 46433.38 | E47: =SUM(E39,E34) -> 24160.8 | F47: =SUM(F39,F34) -> 38405.78 | G47: =SUM(G39,G34) -> 30813.32 | H47: =SUM(H39,H34) -> 17995.08 | I47: =SUM(I39,I34) -> 57936.9 | J47: =SUM(J39,J34) -> 62014.11 | K47: =SUM(K39,K34) -> 14621.48 | ... O47: =SUM(O39,O34) -> 15603.37 | P47: =SUM(P39,P34,P45) -> 450777.2
C48: Rent is monthy interest payment (principle payment included in savings)
C56: Actuals formula:
C57: SUMIFS(Actuals!$E:$E,Actuals!$F:$F,Revised!$C11,Actuals!$A:$A,Revised!D$1)

Sheet Detail
B3: ='1 MO'!B9&" Detail" -> December 2025 Detail
B5: Category | C5: Short Desc | D5: Sum of Amount
B6: Amazon | D6: 3672.24
C7: AMAZON MARKETPLACE NAMZN.COM/BILL WA | D7: -297.35
C8: PRIME VIDEO CHANNELSAMZN.COM/BILL WA | D8: 33.41
C9: General Store | D9: 30.17
C10: AMAZON MARK* ZG3V552U0 HTTPSAMAZON.CWA REF #XX1340R0000EFHA | D10: 31.33
C11: AMAZON MARKEPLACE NA PA | D11: 1515.41
C12: PRIME VIDEO *NW4S811888-802-3080 WA | D12: 4.13
C13: AMAZON KIDS+*NI8P52R888-802-3080 WA | D13: 6.52
C14: AMAZON MUSIC*NB7C187888-802-3080 WA | D14: 6.52
C15: AMAZON.COM AMZN.COM/BILL WA | D15: 193.37
C16: AMAZON KIDS+*9E3JD3D888-802-3080 WA | D16: 6.52
C17: AMAZON MUSIC*8O0RE0N888-802-3080 WA | D17: 6.49
C18: AMAZON KIDS+*2L6015E888-802-3080 WA | D18: 6.49
... C60: AMAZON MKTPL*NI2ZB0KN2 AMZN.COM/BILLWA2BJNHRZVA6N | D60: 8.6
B61: College Savings | D61: 6500
C62: Withdrawal ACH MN DIR ACH TYPE: CONTRIB ID: XX7162 CO: MN DIR ACH NAME: XX2 | D62: 3250
C63: Withdrawal ACH ILD529 DIR ACH TYPE: CONTRIB ID: XX2584 CO: ILD529 DIR ACH E | D63: 3250
B64: Day Care | D64: 12302.58
C65: Withdrawal ACH VENMO TYPE: PAYMENT ID: 326XXXXXXX CO: VENMO NAME: BRITNEY T | D65: 125
C66: Withdrawal ACH CITY OF CHANHASS TYPE: UTIL BILL ID: XX5331 CO: CITY OF CHAN | D66: 347.99
C67: Withdrawal ACH MN DIR ACH TYPE: CONTRIB ID: XX7162 CO: MN DIR ACH NAME: XX2 | D67: 100
C68: Withdrawal ACH CPENERGY MNGCO TYPE: MGC ACH EB ID: 1XX1140S CO: CPENERGY MN | D68: 335.87
C69: BCS*MINNETONKA COMMUEXCELSIOR MN | D69: 846.2
C70: Withdrawal ACH Mis Amigos Presc TYPE: ID: XX7393 NAME: BCU CO: Mis Amigos P | D70: 7210
C71: Withdrawal ACH mtkalax.org TYPE: mtkalax.or ID: XX8598 CO: mtkalax.org NAME | D71: 400
C72: Withdrawal ACH HICKEYBANDO CO: HICKEYBANDO TYPE: IAT PAYPAL ID: 7XX0487C En | D72: 21
C73: Withdrawal ACH mtkalax.org TYPE: mtkalax.or ID: XX5600 CO: mtkalax.org NAME | D73: 250
C74: SCHOOL SPECIALTY LLC XX-5823 WI REF #XX4141LTFLA7BQ | D74: 148.52
C75: BCS*MINNETONKA COMMUNITY XX-6800 MN REF #XX7462N01GAZX2B | D75: 430
C76: MCW 1602-Minnetonka MINNETONKA MN | D76: 53.1
... C80: TONKA TD CLUB 8883791035 MN | D80: 52.5
B81: Delete | D81: -46187.65
C82: Aramark | D82: 40.3
C83: Credit Card Payment Received | D83: -7275.64
C84: Delta Air Lines | D84: 4432.39
C85: Deposit by Check Deposit Anywhere check deposit | D85: -1094
C86: INTERNET PAYMENT - THANK YOU | D86: -1811.81
C87: Payment to American Express | D87: 43223.63
C88: Payment to Discover Bank | D88: 2775.6
C89: Uber | D89: 61.67
C90: Withdrawal ACH AMEX EPAYMENT TYPE: ACH PMT ID: 0005000008 CO: AMEX EPAYMENT | D90: 2405.09
C91: Online Payment - Thank You | D91: -44416.72
C92: Cargill | D92: 2.16
C93: Payment to Jeffrey B | D93: 977.51
... C175: TST*OASIS AT VALENCIA BONITA SPRINGFLAPPLE PAY ENDING IN 762900195484024067 | D175: 58.2
B176: Dry Cleaning | D176: 36.6
C177: AplPay TIDE DRY CLEAEXCELSIOR MN | D177: 36.6
B178: Entertainment | D178: 1578.51
C179: Minnesota State Parks | D179: 31
C180: Hallmark | D180: 43.55
C181: CHASKA CLUB FOODS CHASKA MN | D181: 21.26
C182: HYLAND HILLS SKI AREPYMOUTH MN | D182: 93
C183: LAWRENCE ACUPUNCTURE XX1141 KS REF #XX1343M2X7BPNWP | D183: 165
C184: Salty Sams Marina | D184: 3.29
C185: SHAKOPEE BOWL SHAKOPEE MN REF #XX3100MS66LGF2P | D185: 48.72
C186: FSP*CHASKA TOWN COURCHASKA MN | D186: 121.38
C187: GOLF ZONE 5455000013877-8144102 MN | D187: 37.29
C188: ORDWAY CENTER FOR THSAINT PAUL MN | D188: 480
C189: AplPay AMC EDEN PRAIEDEN PRAIRIE MN | D189: 27.53
C190: AplPay LUNA NAILS Deephaven MN | D190: 103
... C193: BUCK HILL WEBSITE 65BURNSVILLE MN | D193: 164.36
B194: Groceries | D194: 4768.39
C195: Costco | D195: 1196.34
C196: Dollar Tree | D196: 1.36
C197: Holiday Stationstores | D197: 42.6
C198: Walgreens | D198: 28.13
C199: Costco Gas Stations | D199: 344.64
C200: HOME CHEF CHICAGO IL | D200: 1637.98
C201: CUB FOODS #1636 0000SHOREWOOD MN | D201: 340.64
C202: AplPay CUB FOODS #16SHOREWOOD MN | D202: 85.29
C203: LUNDS&BYERLYS CHANHACHANHASSEN MN | D203: 82.5
C204: LAKESHORE MARKET & MEXCELSIOR MN | D204: 232.97
C205: TOTAL WINE AND MORE CHANHASSEN MN | D205: 108.39
C206: KOWALSKI'S EXCELSIOREXCELSIOR MN | D206: 3.22
... C215: CUB FOODS #1636 SHOREWOOD MNAPPLE PAY ENDING IN 7968 | D215: 16.53
B216: Healthcare | D216: 1282.82
C217: Advocare | D217: 425.91
C218: BONOBOS, NEW YORK NEW YORK | D218: 119
C219: SOUTH LAKE PEDIATRICMINNETONKA MN | D219: 451.57
C220: MODMEDUS_MP*PINNACLEPHOENIX AZ | D220: 10.76
C221: MINUTECLINIC DIAGNOSWOONSOCKET RI | D221: 60.19
C222: AplPay SOUTH LAKE PEMINNETONKA MN | D222: 55.89
C223: EXCELSIOR FAMILY DENEXCELSIOR MN | D223: 159.5
B224: House | D224: 86651.83
C225: Draft 2357 Tracer XX0903 | D225: 1953.5
C226: Draft 2311 Tracer XX0410 | D226: 17568
C227: Draft 2310 Tracer XX1368 | D227: 459
C228: Draft 2306 Tracer XX3475 | D228: 11229.5
C229: Draft 2308 Tracer XX6479 | D229: 13279.5
C230: Draft 2307 Tracer XX0903 | D230: 8690
C231: Draft 2304 Tracer XX0454 | D231: 30245.75
C232: THE GARDEN PATCH EXCELSIOR MN REF #XX4001HJZX81 | D232: 53.01
C233: IN *SUPERIOR LAWN ANSAINT BONIFACIUS MN | D233: 3000
C234: AplPay THE HOME DEPOEDEN PRAIRIE MN | D234: 46.6
C235: AplPay THE SHERWIN-WCLEVELAND OH | D235: 126.97
B236: House Maintenance | D236: 1492.18
C237: The Home Depot | D237: 143.58
C238: SHOREWOOD TRUE VALUEEXCELSIOR MN | D238: 310.36
...

Sheet Single Detail
B1: Category | C1: Exp - House
B3: Sum of Amount | C3: Yrmo
B4: Description
B5: Grand Total

Sheet Avg
H1: =IF(H2="",'1 MO'!C1,H2) -> 202412 | I1: =IF(RIGHT(H1,2)="01",VALUE(LEFT(H1,4)-1&"12"),VALUE(LEFT(H1,4)&TEXT(RIGHT(H1,2)-1,"00"))) -> 202411 | J1: =IF(RIGHT(I1,2)="01",VALUE(LEFT(I1,4)-1&"12"),VALUE(LEFT(I1,4)&TEXT(RIGHT(I1,2)-1,"00"))) -> 202410 | K1: =IF(RIGHT(J1,2)="01",VALUE(LEFT(J1,4)-1&"12"),VALUE(LEFT(J1,4)&TEXT(RIGHT(J1,2)-1,"00"))) -> 202409 | L1: =IF(RIGHT(K1,2)="01",VALUE(LEFT(K1,4)-1&"12"),VALUE(LEFT(K1,4)&TEXT(RIGHT(K1,2)-1,"00"))) -> 202408 | M1: =IF(RIGHT(L1,2)="01",VALUE(LEFT(L1,4)-1&"12"),VALUE(LEFT(L1,4)&TEXT(RIGHT(L1,2)-1,"00"))) -> 202407 | N1: =IF(RIGHT(M1,2)="01",VALUE(LEFT(M1,4)-1&"12"),VALUE(LEFT(M1,4)&TEXT(RIGHT(M1,2)-1,"00"))) -> 202406 | O1: =IF(RIGHT(N1,2)="01",VALUE(LEFT(N1,4)-1&"12"),VALUE(LEFT(N1,4)&TEXT(RIGHT(N1,2)-1,"00"))) -> 202405 | P1: =IF(RIGHT(O1,2)="01",VALUE(LEFT(O1,4)-1&"12"),VALUE(LEFT(O1,4)&TEXT(RIGHT(O1,2)-1,"00"))) -> 202404 | ... S1: =IF(RIGHT(R1,2)="01",VALUE(LEFT(R1,4)-1&"12"),VALUE(LEFT(R1,4)&TEXT(RIGHT(R1,2)-1,"00"))) -> 202401
H2: 202412
C6: Actuals Averages | V6: Emergency Fund
D7: Prev 3 Mo | E7: Prev 6 Mo | F7: Prev 12 Mo | H7: =TEXT(DATE(LEFT(H1,4),RIGHT(H1,2),1),"MMM YYYY") -> Dec 2024 | I7: =TEXT(DATE(LEFT(I1,4),RIGHT(I1,2),1),"MMM YYYY") -> Nov 2024 | J7: =TEXT(DATE(LEFT(J1,4),RIGHT(J1,2),1),"MMM YYYY") -> Oct 2024 | K7: =TEXT(DATE(LEFT(K1,4),RIGHT(K1,2),1),"MMM YYYY") -> Sep 2024 | L7: =TEXT(DATE(LEFT(L1,4),RIGHT(L1,2),1),"MMM YYYY") -> Aug 2024 | M7: =TEXT(DATE(LEFT(M1,4),RIGHT(M1,2),1),"MMM YYYY") -> Jul 2024 | N7: =TEXT(DATE(LEFT(N1,4),RIGHT(N1,2),1),"MMM YYYY") -> Jun 2024 | O7: =TEXT(DATE(LEFT(O1,4),RIGHT(O1,2),1),"MMM YYYY") -> May 2024 | ... S7: =TEXT(DATE(LEFT(S1,4),RIGHT(S1,2),1),"MMM YYYY") -> Jan 2024 | T7: Total 12 mo | W7: 3 mo | X7: 6 mo
C9: Rent | D9: =AVERAGE(H9:J9) -> 2745.43 | E9: =AVERAGE(H9:M9) -> 2744.2 | F9: =AVERAGE(H9:S9) -> 2742.97 | H9: =SUMIFS(Actuals!$E:$E,Actuals!$F:$F,Avg!$C9,Actuals!$A:$A,Avg!H$1) -> 2745.43 | I9: =SUMIFS(Actuals!$E:$E,Actuals!$F:$F,Avg!$C9,Actuals!$A:$A,Avg!I$1) -> 2745.43 | J9: =SUMIFS(Actuals!$E:$E,Actuals!$F:$F,Avg!$C9,Actuals!$A:$A,Avg!J$1) -> 2745.43 | K9: =SUMIFS(Actuals!$E:$E,Actuals!$F:$F,Avg!$C9,Actuals!$A:$A,Avg!K$1) -> 2745.43 | L9: =SUMIFS(Actuals!$E:$E,Actuals!$F:$F,Avg!$C9,Actuals!$A:$A,Avg!L$1) -> 2741.74 | M9: =SUMIFS(Actuals!$E:$E,Actuals!$F:$F,Avg!$C9,Actuals!$A:$A,Avg!M$1) -> 2741.74 | N9: =SUMIFS(Actuals!$E:$E,Actuals!$F:$F,Avg!$C9,Actuals!$A:$A,Avg!N$1) -> 2741.74 | O9: =SUMIFS(Actuals!$E:$E,Actuals!$F:$F,Avg!$C9,Actuals!$A:$A,Avg!O$1) -> 2741.74 | ... S9: =SUMIFS(Actuals!$E:$E,Actuals!$F:$F,Avg!$C9,Actuals!$A:$A,Avg!S$1) -> 2741.74 | T9: =SUM(H9:S9) -> 32915.64 | V9: Essiential | W9: =SUM(H16:J16,H22:J22) -> 28192.18 | X9: =SUM(H16:M16,H22:M22) -> 58391.99
C10: House Maintenance | D10: =AVERAGE(H10:J10) -> 158.58 | E10: =AVERAGE(H10:M10) -> 245.50833 | F10: =AVERAGE(H10:S10) -> 349.64083 | H10: =SUMIFS(Actuals!$E:$E,Actuals!$F:$F,Avg!$C10,Actuals!$A:$A,Avg!H$1) -> 11 | I10: =SUMIFS(Actuals!$E:$E,Actuals!$F:$F,Avg!$C10,Actuals!$A:$A,Avg!I$1) -> 11 | J10: =SUMIFS(Actuals!$E:$E,Actuals!$F:$F,Avg!$C10,Actuals!$A:$A,Avg!J$1) -> 453.74 | K10: =SUMIFS(Actuals!$E:$E,Actuals!$F:$F,Avg!$C10,Actuals!$A:$A,Avg!K$1) -> 486.97 | L10: =SUMIFS(Actuals!$E:$E,Actuals!$F:$F,Avg!$C10,Actuals!$A:$A,Avg!L$1) -> 44.59 | M10: =SUMIFS(Actuals!$E:$E,Actuals!$F:$F,Avg!$C10,Actuals!$A:$A,Avg!M$1) -> 465.75 | N10: =SUMIFS(Actuals!$E:$E,Actuals!$F:$F,Avg!$C10,Actuals!$A:$A,Avg!N$1) -> 738.02 | O10: =SUMIFS(Actuals!$E:$E,Actuals!$F:$F,Avg!$C10,Actuals!$A:$A,Avg!O$1) -> 769.43 | ... S10: =SUMIFS(Actuals!$E:$E,Actuals!$F:$F,Avg!$C10,Actuals!$A:$A,Avg!S$1) -> 271.35 | T10: =SUM(H10:S10) -> 4195.69 | V10: All Spend | W10: =SUM(H16:J16,H22:J22,H31:J31) -> 41300.57 | X10: =SUM(H16:M16,H22:M22,H31:M31) -> 78378.18
C11: Utilities | D11: =AVERAGE(H11:J11) -> 771.99 | E11: =AVERAGE(H11:M11) -> 670.78667 | F11: =AVERAGE(H11:S11) -> 707.5 | H11: =SUMIFS(Actuals!$E:$E,Actuals!$F:$F,Avg!$C11,Actuals!$A:$A,Avg!H$1) -> 877.36 | I11: =SUMIFS(Actuals!$E:$E,Actuals!$F:$F,Avg!$C11,Actuals!$A:$A,Avg!I$1) -> 584.33 | J11: =SUMIFS(Actuals!$E:$E,Actuals!$F:$F,Avg!$C11,Actuals!$A:$A,Avg!J$1) -> 854.28 | K11: =SUMIFS(Actuals!$E:$E,Actuals!$F:$F,Avg!$C11,Actuals!$A:$A,Avg!K$1) -> 639.18 | L11: =SUMIFS(Actuals!$E:$E,Actuals!$F:$F,Avg!$C11,Actuals!$A:$A,Avg!L$1) -> 335.09 | M11: =SUMIFS(Actuals!$E:$E,Actuals!$F:$F,Avg!$C11,Actuals!$A:$A,Avg!M$1) -> 734.48 | N11: =SUMIFS(Actuals!$E:$E,Actuals!$F:$F,Avg!$C11,Actuals!$A:$A,Avg!N$1) -> 502.44 | O11: =SUMIFS(Actuals!$E:$E,Actuals!$F:$F,Avg!$C11,Actuals!$A:$A,Avg!O$1) -> 1017.52 | ... S11: =SUMIFS(Actuals!$E:$E,Actuals!$F:$F,Avg!$C11,Actuals!$A:$A,Avg!S$1) -> 612.25 | T11: =SUM(H11:S11) -> 8490
C12: Car Loan | D12: =AVERAGE(H12:J12) -> 0 | E12: =AVERAGE(H12:M12) -> 0 | F12: =AVERAGE(H12:S12) -> 0 | H12: =SUMIFS(Actuals!$E:$E,Actuals!$F:$F,Avg!$C12,Actuals!$A:$A,Avg!H$1) -> 0 | I12: =SUMIFS(Actuals!$E:$E,Actuals!$F:$F,Avg!$C12,Actuals!$A:$A,Avg!I$1) -> 0 | J12: =SUMIFS(Actuals!$E:$E,Actuals!$F:$F,Avg!$C12,Actuals!$A:$A,Avg!J$1) -> 0 | K12: =SUMIFS(Actuals!$E:$E,Actuals!$F:$F,Avg!$C12,Actuals!$A:$A,Avg!K$1) -> 0 | L12: =SUMIFS(Actuals!$E:$E,Actuals!$F:$F,Avg!$C12,Actuals!$A:$A,Avg!L$1) -> 0 | M12: =SUMIFS(Actuals!$E:$E,Actuals!$F:$F,Avg!$C12,Actuals!$A:$A,Avg!M$1) -> 0 | N12: =SUMIFS(Actuals!$E:$E,Actuals!$F:$F,Avg!$C12,Actuals!$A:$A,Avg!N$1) -> 0 | O12: =SUMIFS(Actuals!$E:$E,Actuals!$F:$F,Avg!$C12,Actuals!$A:$A,Avg!O$1) -> 0 | ... S12: =SUMIFS(Actuals!$E:$E,Actuals!$F:$F,Avg!$C12,Actuals!$A:$A,Avg!S$1) -> 0 | T12: =SUM(H12:S12) -> 0
C13: Cleaning | D13: =AVERAGE(H13:J13) -> 250 | E13: =AVERAGE(H13:M13) -> 250 | F13: =AVERAGE(H13:S13) -> 250 | H13: =SUMIFS(Actuals!$E:$E,Actuals!$F:$F,Avg!$C13,Actuals!$A:$A,Avg!H$1) -> 250 | I13: =SUMIFS(Actuals!$E:$E,Actuals!$F:$F,Avg!$C13,Actuals!$A:$A,Avg!I$1) -> 250 | J13: =SUMIFS(Actuals!$E:$E,Actuals!$F:$F,Avg!$C13,Actuals!$A:$A,Avg!J$1) -> 250 | K13: =SUMIFS(Actuals!$E:$E,Actuals!$F:$F,Avg!$C13,Actuals!$A:$A,Avg!K$1) -> 250 | L13: =SUMIFS(Actuals!$E:$E,Actuals!$F:$F,Avg!$C13,Actuals!$A:$A,Avg!L$1) -> 250 | M13: =SUMIFS(Actuals!$E:$E,Actuals!$F:$F,Avg!$C13,Actuals!$A:$A,Avg!M$1) -> 250 | N13: =SUMIFS(Actuals!$E:$E,Actuals!$F:$F,Avg!$C13,Actuals!$A:$A,Avg!N$1) -> 250 | O13: =SUMIFS(Actuals!$E:$E,Actuals!$F:$F,Avg!$C13,Actuals!$A:$A,Avg!O$1) -> 250 | ... S13: =SUMIFS(Actuals!$E:$E,Actuals!$F:$F,Avg!$C13,Actuals!$A:$A,Avg!S$1) -> 250 | T13: =SUM(H13:S13) -> 3000 | V13: Actual
C14: Insurance | D14: =AVERAGE(H14:J14) -> 163.9 | E14: =AVERAGE(H14:M14) -> 168.63667 | F14: =AVERAGE(H14:S14) -> 135.97083 | H14: =SUMIFS(Actuals!$E:$E,Actuals!$F:$F,Avg!$C14,Actuals!$A:$A,Avg!H$1) -> 144.94 | I14: =SUMIFS(Actuals!$E:$E,Actuals!$F:$F,Avg!$C14,Actuals!$A:$A,Avg!I$1) -> 173.38 | J14: =SUMIFS(Actuals!$E:$E,Actuals!$F:$F,Avg!$C14,Actuals!$A:$A,Avg!J$1) -> 173.38 | K14: =SUMIFS(Actuals!$E:$E,Actuals!$F:$F,Avg!$C14,Actuals!$A:$A,Avg!K$1) -> 173.38 | L14: =SUMIFS(Actuals!$E:$E,Actuals!$F:$F,Avg!$C14,Actuals!$A:$A,Avg!L$1) -> 173.37 | M14: =SUMIFS(Actuals!$E:$E,Actuals!$F:$F,Avg!$C14,Actuals!$A:$A,Avg!M$1) -> 173.37 | N14: =SUMIFS(Actuals!$E:$E,Actuals!$F:$F,Avg!$C14,Actuals!$A:$A,Avg!N$1) -> 201.42 | O14: =SUMIFS(Actuals!$E:$E,Actuals!$F:$F,Avg!$C14,Actuals!$A:$A,Avg!O$1) -> 0 | ... S14: =SUMIFS(Actuals!$E:$E,Actuals!$F:$F,Avg!$C14,Actuals!$A:$A,Avg!S$1) -> 127.3 | T14: =SUM(H14:S14) -> 1631.65 | V14: BCU Rainy Day | W14: 0
C15: Day Care | D15: =AVERAGE(H15:J15) -> 2274.1567 | E15: =AVERAGE(H15:M15) -> 1948.2 | F15: =AVERAGE(H15:S15) -> 2280.2492 | H15: =SUMIFS(Actuals!$E:$E,Actuals!$F:$F,Avg!$C15,Actuals!$A:$A,Avg!H$1) -> 2034 | I15: =SUMIFS(Actuals!$E:$E,Actuals!$F:$F,Avg!$C15,Actuals!$A:$A,Avg!I$1) -> 2263.85 | J15: =SUMIFS(Actuals!$E:$E,Actuals!$F:$F,Avg!$C15,Actuals!$A:$A,Avg!J$1) -> 2524.62 | K15: =SUMIFS(Actuals!$E:$E,Actuals!$F:$F,Avg!$C15,Actuals!$A:$A,Avg!K$1) -> 2281.2 | L15: =SUMIFS(Actuals!$E:$E,Actuals!$F:$F,Avg!$C15,Actuals!$A:$A,Avg!L$1) -> 732.53 | M15: =SUMIFS(Actuals!$E:$E,Actuals!$F:$F,Avg!$C15,Actuals!$A:$A,Avg!M$1) -> 1853 | N15: =SUMIFS(Actuals!$E:$E,Actuals!$F:$F,Avg!$C15,Actuals!$A:$A,Avg!N$1) -> 2889.07 | O15: =SUMIFS(Actuals!$E:$E,Actuals!$F:$F,Avg!$C15,Actuals!$A:$A,Avg!O$1) -> 2058.99 | ... S15: =SUMIFS(Actuals!$E:$E,Actuals!$F:$F,Avg!$C15,Actuals!$A:$A,Avg!S$1) -> 3132.11 | T15: =SUM(H15:S15) -> 27362.99 | V15: I Bonds | W15: =0 -> 0
C16: Total Rent & Utilitites | D16: =SUM(D9:D15) -> 6364.0567 | E16: =SUM(E9:E15) -> 6027.3317 | F16: =SUM(F9:F15) -> 6466.3308 | H16: =SUM(H9:H15) -> 6062.73 | I16: =SUM(I9:I15) -> 6027.99 | J16: =SUM(J9:J15) -> 7001.45 | K16: =SUM(K9:K15) -> 6576.16 | L16: =SUM(L9:L15) -> 4277.32 | M16: =SUM(M9:M15) -> 6218.34 | N16: =SUM(N9:N15) -> 7322.69 | O16: =SUM(O9:O15) -> 6837.68 | ... S16: =SUM(S9:S15) -> 7134.75 | T16: =SUM(H16:S16) -> 77595.97 | V16: Discover Savings | W16: ='Main 2'!D90-20000 -> -14317.5
V17: Total | W17: =SUM(W14:W16) -> -14317.5
C18: Transportation | D18: =AVERAGE(H18:J18) -> 231.88333 | E18: =AVERAGE(H18:M18) -> 419.93667 | F18: =AVERAGE(H18:S18) -> 357.98667 | H18: =SUMIFS(Actuals!$E:$E,Actuals!$F:$F,Avg!$C18,Actuals!$A:$A,Avg!H$1) -> 230.47 | I18: =SUMIFS(Actuals!$E:$E,Actuals!$F:$F,Avg!$C18,Actuals!$A:$A,Avg!I$1) -> 199.96 | J18: =SUMIFS(Actuals!$E:$E,Actuals!$F:$F,Avg!$C18,Actuals!$A:$A,Avg!J$1) -> 265.22 | K18: =SUMIFS(Actuals!$E:$E,Actuals!$F:$F,Avg!$C18,Actuals!$A:$A,Avg!K$1) -> 471.59 | L18: =SUMIFS(Actuals!$E:$E,Actuals!$F:$F,Avg!$C18,Actuals!$A:$A,Avg!L$1) -> 969.74 | M18: =SUMIFS(Actuals!$E:$E,Actuals!$F:$F,Avg!$C18,Actuals!$A:$A,Avg!M$1) -> 382.64 | N18: =SUMIFS(Actuals!$E:$E,Actuals!$F:$F,Avg!$C18,Actuals!$A:$A,Avg!N$1) -> 392.69 | O18: =SUMIFS(Actuals!$E:$E,Actuals!$F:$F,Avg!$C18,Actuals!$A:$A,Avg!O$1) -> 374.09 | ... S18: =SUMIFS(Actuals!$E:$E,Actuals!$F:$F,Avg!$C18,Actuals!$A:$A,Avg!S$1) -> 182.12 | T18: =SUM(H18:S18) -> 4295.84
C19: Restaurants | D19: =AVERAGE(H19:J19) -> 1158.94 | E19: =AVERAGE(H19:M19) -> 1703.1867 | F19: =AVERAGE(H19:S19) -> 1384.2208 | H19: =SUMIFS(Actuals!$E:$E,Actuals!$F:$F,Avg!$C19,Actuals!$A:$A,Avg!H$1) -> 1822.8 | I19: =SUMIFS(Actuals!$E:$E,Actuals!$F:$F,Avg!$C19,Actuals!$A:$A,Avg!I$1) -> 510.14 | J19: =SUMIFS(Actuals!$E:$E,Actuals!$F:$F,Avg!$C19,Actuals!$A:$A,Avg!J$1) -> 1143.88 | K19: =SUMIFS(Actuals!$E:$E,Actuals!$F:$F,Avg!$C19,Actuals!$A:$A,Avg!K$1) -> 1847.66 | L19: =SUMIFS(Actuals!$E:$E,Actuals!$F:$F,Avg!$C19,Actuals!$A:$A,Avg!L$1) -> 3551.05 | M19: =SUMIFS(Actuals!$E:$E,Actuals!$F:$F,Avg!$C19,Actuals!$A:$A,Avg!M$1) -> 1343.59 | N19: =SUMIFS(Actuals!$E:$E,Actuals!$F:$F,Avg!$C19,Actuals!$A:$A,Avg!N$1) -> 1425.91 | O19: =SUMIFS(Actuals!$E:$E,Actuals!$F:$F,Avg!$C19,Actuals!$A:$A,Avg!O$1) -> 892.74 | ... S19: =SUMIFS(Actuals!$E:$E,Actuals!$F:$F,Avg!$C19,Actuals!$A:$A,Avg!S$1) -> 513.91 | T19: =SUM(H19:S19) -> 16610.65
C20: Groceries | D20: =AVERAGE(H20:J20) -> 1177.3833 | E20: =AVERAGE(H20:M20) -> 1116.3883 | F20: =AVERAGE(H20:S20) -> 958.835 | H20: =SUMIFS(Actuals!$E:$E,Actuals!$F:$F,Avg!$C20,Actuals!$A:$A,Avg!H$1) -> 1134.6 | I20: =SUMIFS(Actuals!$E:$E,Actuals!$F:$F,Avg!$C20,Actuals!$A:$A,Avg!I$1) -> 1344.48 | J20: =SUMIFS(Actuals!$E:$E,Actuals!$F:$F,Avg!$C20,Actuals!$A:$A,Avg!J$1) -> 1053.07 | K20: =SUMIFS(Actuals!$E:$E,Actuals!$F:$F,Avg!$C20,Actuals!$A:$A,Avg!K$1) -> 1201.08 | L20: =SUMIFS(Actuals!$E:$E,Actuals!$F:$F,Avg!$C20,Actuals!$A:$A,Avg!L$1) -> 1043.32 | M20: =SUMIFS(Actuals!$E:$E,Actuals!$F:$F,Avg!$C20,Actuals!$A:$A,Avg!M$1) -> 921.78 | N20: =SUMIFS(Actuals!$E:$E,Actuals!$F:$F,Avg!$C20,Actuals!$A:$A,Avg!N$1) -> 1004.03 | O20: =SUMIFS(Actuals!$E:$E,Actuals!$F:$F,Avg!$C20,Actuals!$A:$A,Avg!O$1) -> 714.52 | ... S20: =SUMIFS(Actuals!$E:$E,Actuals!$F:$F,Avg!$C20,Actuals!$A:$A,Avg!S$1) -> 797.17 | T20: =SUM(H20:S20) -> 11506.02
C21: Target | D21: =AVERAGE(H21:J21) -> 465.13 | E21: =AVERAGE(H21:M21) -> 465.155 | F21: =AVERAGE(H21:S21) -> 674.4425 | H21: =SUMIFS(Actuals!$E:$E,Actuals!$F:$F,Avg!$C21,Actuals!$A:$A,Avg!H$1) -> 529.78 | I21: =SUMIFS(Actuals!$E:$E,Actuals!$F:$F,Avg!$C21,Actuals!$A:$A,Avg!I$1) -> 269.02 | J21: =SUMIFS(Actuals!$E:$E,Actuals!$F:$F,Avg!$C21,Actuals!$A:$A,Avg!J$1) -> 596.59 | K21: =SUMIFS(Actuals!$E:$E,Actuals!$F:$F,Avg!$C21,Actuals!$A:$A,Avg!K$1) -> 472.05 | L21: =SUMIFS(Actuals!$E:$E,Actuals!$F:$F,Avg!$C21,Actuals!$A:$A,Avg!L$1) -> 485.45 | M21: =SUMIFS(Actuals!$E:$E,Actuals!$F:$F,Avg!$C21,Actuals!$A:$A,Avg!M$1) -> 438.04 | N21: =SUMIFS(Actuals!$E:$E,Actuals!$F:$F,Avg!$C21,Actuals!$A:$A,Avg!N$1) -> 860.05 | O21: =SUMIFS(Actuals!$E:$E,Actuals!$F:$F,Avg!$C21,Actuals!$A:$A,Avg!O$1) -> 543.81 | ... S21: =SUMIFS(Actuals!$E:$E,Actuals!$F:$F,Avg!$C21,Actuals!$A:$A,Avg!S$1) -> 933.14 | T21: =SUM(H21:S21) -> 8093.31
C22: Total Food & Car | D22: =SUM(D18:D21) -> 3033.3367 | E22: =SUM(E18:E21) -> 3704.6667 | F22: =SUM(F18:F21) -> 3375.485 | H22: =SUM(H18:H21) -> 3717.65 | I22: =SUM(I18:I21) -> 2323.6 | J22: =SUM(J18:J21) -> 3058.76 | K22: =SUM(K18:K21) -> 3992.38 | L22: =SUM(L18:L21) -> 6049.56 | M22: =SUM(M18:M21) -> 3086.05 | N22: =SUM(N18:N21) -> 3682.68 | O22: =SUM(O18:O21) -> 2525.16 | ... S22: =SUM(S18:S21) -> 2426.34 | T22: =SUM(H22:S22) -> 40505.82
C24: Gym | D24: =AVERAGE(H24:J24) -> 0 | E24: =AVERAGE(H24:M24) -> 15.896667 | F24: =AVERAGE(H24:S24) -> 31.793333 | H24: =SUMIFS(Actuals!$E:$E,Actuals!$F:$F,Avg!$C24,Actuals!$A:$A,Avg!H$1) -> 0 | I24: =SUMIFS(Actuals!$E:$E,Actuals!$F:$F,Avg!$C24,Actuals!$A:$A,Avg!I$1) -> 0 | J24: =SUMIFS(Actuals!$E:$E,Actuals!$F:$F,Avg!$C24,Actuals!$A:$A,Avg!J$1) -> 0 | K24: =SUMIFS(Actuals!$E:$E,Actuals!$F:$F,Avg!$C24,Actuals!$A:$A,Avg!K$1) -> 0 | L24: =SUMIFS(Actuals!$E:$E,Actuals!$F:$F,Avg!$C24,Actuals!$A:$A,Avg!L$1) -> 47.69 | M24: =SUMIFS(Actuals!$E:$E,Actuals!$F:$F,Avg!$C24,Actuals!$A:$A,Avg!M$1) -> 47.69 | N24: =SUMIFS(Actuals!$E:$E,Actuals!$F:$F,Avg!$C24,Actuals!$A:$A,Avg!N$1) -> 47.69 | O24: =SUMIFS(Actuals!$E:$E,Actuals!$F:$F,Avg!$C24,Actuals!$A:$A,Avg!O$1) -> 47.69 | ... S24: =SUMIFS(Actuals!$E:$E,Actuals!$F:$F,Avg!$C24,Actuals!$A:$A,Avg!S$1) -> 47.69 | T24: =SUM(H24:S24) -> 381.52
C25: Shopping | D25: =AVERAGE(H25:J25) -> 2839.6933 | E25: =AVERAGE(H25:M25) -> 2228.5667 | F25: =AVERAGE(H25:S25) -> 2038.6808 | H25: =SUMIFS(Actuals!$E:$E,Actuals!$F:$F,Avg!$C25,Actuals!$A:$A,Avg!H$1) -> 3247.44 | I25: =SUMIFS(Actuals!$E:$E,Actuals!$F:$F,Avg!$C25,Actuals!$A:$A,Avg!I$1) -> 2288.11 | J25: =SUMIFS(Actuals!$E:$E,Actuals!$F:$F,Avg!$C25,Actuals!$A:$A,Avg!J$1) -> 2983.53 | K25: =SUMIFS(Actuals!$E:$E,Actuals!$F:$F,Avg!$C25,Actuals!$A:$A,Avg!K$1) -> 1003.11 | L25: =SUMIFS(Actuals!$E:$E,Actuals!$F:$F,Avg!$C25,Actuals!$A:$A,Avg!L$1) -> 881.13 | M25: =SUMIFS(Actuals!$E:$E,Actuals!$F:$F,Avg!$C25,Actuals!$A:$A,Avg!M$1) -> 2968.08 | N25: =SUMIFS(Actuals!$E:$E,Actuals!$F:$F,Avg!$C25,Actuals!$A:$A,Avg!N$1) -> 1317.9 | O25: =SUMIFS(Actuals!$E:$E,Actuals!$F:$F,Avg!$C25,Actuals!$A:$A,Avg!O$1) -> 2255.68 | ... S25: =SUMIFS(Actuals!$E:$E,Actuals!$F:$F,Avg!$C25,Actuals!$A:$A,Avg!S$1) -> 1586.55 | T25: =SUM(H25:S25) -> 24464.17
C26: Amazon | D26: =AVERAGE(H26:J26) -> 547.41 | E26: =AVERAGE(H26:M26) -> 403.35833 | F26: =AVERAGE(H26:S26) -> 583.47833 | H26: =SUMIFS(Actuals!$E:$E,Actuals!$F:$F,Avg!$C26,Actuals!$A:$A,Avg!H$1) -> -126.78 | I26: =SUMIFS(Actuals!$E:$E,Actuals!$F:$F,Avg!$C26,Actuals!$A:$A,Avg!I$1) -> 1075.81 | J26: =SUMIFS(Actuals!$E:$E,Actuals!$F:$F,Avg!$C26,Actuals!$A:$A,Avg!J$1) -> 693.2 | K26: =SUMIFS(Actuals!$E:$E,Actuals!$F:$F,Avg!$C26,Actuals!$A:$A,Avg!K$1) -> 60.17 | L26: =SUMIFS(Actuals!$E:$E,Actuals!$F:$F,Avg!$C26,Actuals!$A:$A,Avg!L$1) -> 259.6 | M26: =SUMIFS(Actuals!$E:$E,Actuals!$F:$F,Avg!$C26,Actuals!$A:$A,Avg!M$1) -> 458.15 | N26: =SUMIFS(Actuals!$E:$E,Actuals!$F:$F,Avg!$C26,Actuals!$A:$A,Avg!N$1) -> 605.96 | O26: =SUMIFS(Actuals!$E:$E,Actuals!$F:$F,Avg!$C26,Actuals!$A:$A,Avg!O$1) -> 547.84 | ... S26: =SUMIFS(Actuals!$E:$E,Actuals!$F:$F,Avg!$C26,Actuals!$A:$A,Avg!S$1) -> 665.1 | T26: =SUM(H26:S26) -> 7001.74
C27: Entertainment | D27: =AVERAGE(H27:J27) -> 712.46333 | E27: =AVERAGE(H27:M27) -> 502.00833 | F27: =AVERAGE(H27:S27) -> 594.59417 | H27: =SUMIFS(Actuals!$E:$E,Actuals!$F:$F,Avg!$C27,Actuals!$A:$A,Avg!H$1) -> 557.01 | I27: =SUMIFS(Actuals!$E:$E,Actuals!$F:$F,Avg!$C27,Actuals!$A:$A,Avg!I$1) -> 866.36 | J27: =SUMIFS(Actuals!$E:$E,Actuals!$F:$F,Avg!$C27,Actuals!$A:$A,Avg!J$1) -> 714.02 | K27: =SUMIFS(Actuals!$E:$E,Actuals!$F:$F,Avg!$C27,Actuals!$A:$A,Avg!K$1) -> 334.69 | L27: =SUMIFS(Actuals!$E:$E,Actuals!$F:$F,Avg!$C27,Actuals!$A:$A,Avg!L$1) -> 287.22 | M27: =SUMIFS(Actuals!$E:$E,Actuals!$F:$F,Avg!$C27,Actuals!$A:$A,Avg!M$1) -> 252.75 | N27: =SUMIFS(Actuals!$E:$E,Actuals!$F:$F,Avg!$C27,Actuals!$A:$A,Avg!N$1) -> 759.53 | O27: =SUMIFS(Actuals!$E:$E,Actuals!$F:$F,Avg!$C27,Actuals!$A:$A,Avg!O$1) -> 348.54 | ... S27: =SUMIFS(Actuals!$E:$E,Actuals!$F:$F,Avg!$C27,Actuals!$A:$A,Avg!S$1) -> 995.52 | T27: =SUM(H27:S27) -> 7135.13
C28: Dry Cleaning | D28: =AVERAGE(H28:J28) -> 19.976667 | E28: =AVERAGE(H28:M28) -> 32.568333 | F28: =AVERAGE(H28:S28) -> 44.821667 | H28: =SUMIFS(Actuals!$E:$E,Actuals!$F:$F,Avg!$C28,Actuals!$A:$A,Avg!H$1) -> 0 | I28: =SUMIFS(Actuals!$E:$E,Actuals!$F:$F,Avg!$C28,Actuals!$A:$A,Avg!I$1) -> 59.93 | J28: =SUMIFS(Actuals!$E:$E,Actuals!$F:$F,Avg!$C28,Actuals!$A:$A,Avg!J$1) -> 0 | K28: =SUMIFS(Actuals!$E:$E,Actuals!$F:$F,Avg!$C28,Actuals!$A:$A,Avg!K$1) -> 23.86 | L28: =SUMIFS(Actuals!$E:$E,Actuals!$F:$F,Avg!$C28,Actuals!$A:$A,Avg!L$1) -> 0 | M28: =SUMIFS(Actuals!$E:$E,Actuals!$F:$F,Avg!$C28,Actuals!$A:$A,Avg!M$1) -> 111.62 | N28: =SUMIFS(Actuals!$E:$E,Actuals!$F:$F,Avg!$C28,Actuals!$A:$A,Avg!N$1) -> 109.81 | O28: =SUMIFS(Actuals!$E:$E,Actuals!$F:$F,Avg!$C28,Actuals!$A:$A,Avg!O$1) -> 181.53 | ... S28: =SUMIFS(Actuals!$E:$E,Actuals!$F:$F,Avg!$C28,Actuals!$A:$A,Avg!S$1) -> 33.76 | T28: =SUM(H28:S28) -> 537.86
C29: Gifts | D29: =AVERAGE(H29:J29) -> 225.85333 | E29: =AVERAGE(H29:M29) -> 130.10833 | F29: =AVERAGE(H29:S29) -> 65.054167 | H29: =SUMIFS(Actuals!$E:$E,Actuals!$F:$F,Avg!$C29,Actuals!$A:$A,Avg!H$1) -> 97.41 | I29: =SUMIFS(Actuals!$E:$E,Actuals!$F:$F,Avg!$C29,Actuals!$A:$A,Avg!I$1) -> 162.4 | J29: =SUMIFS(Actuals!$E:$E,Actuals!$F:$F,Avg!$C29,Actuals!$A:$A,Avg!J$1) -> 417.75 | K29: =SUMIFS(Actuals!$E:$E,Actuals!$F:$F,Avg!$C29,Actuals!$A:$A,Avg!K$1) -> 0 | L29: =SUMIFS(Actuals!$E:$E,Actuals!$F:$F,Avg!$C29,Actuals!$A:$A,Avg!L$1) -> 103.09 | M29: =SUMIFS(Actuals!$E:$E,Actuals!$F:$F,Avg!$C29,Actuals!$A:$A,Avg!M$1) -> 0 | N29: =SUMIFS(Actuals!$E:$E,Actuals!$F:$F,Avg!$C29,Actuals!$A:$A,Avg!N$1) -> 0 | O29: =SUMIFS(Actuals!$E:$E,Actuals!$F:$F,Avg!$C29,Actuals!$A:$A,Avg!O$1) -> 0 | ... S29: =SUMIFS(Actuals!$E:$E,Actuals!$F:$F,Avg!$C29,Actuals!$A:$A,Avg!S$1) -> 0 | T29: =SUM(H29:S29) -> 780.65
C30: Misc | D30: =AVERAGE(H30:J30) -> 24.066667 | E30: =AVERAGE(H30:M30) -> 18.525 | F30: =AVERAGE(H30:S30) -> 43.9875 | H30: =SUMIFS(Actuals!$E:$E,Actuals!$F:$F,Avg!$C30,Actuals!$A:$A,Avg!H$1) -> 10.5 | I30: =SUMIFS(Actuals!$E:$E,Actuals!$F:$F,Avg!$C30,Actuals!$A:$A,Avg!I$1) -> 61.7 | J30: =SUMIFS(Actuals!$E:$E,Actuals!$F:$F,Avg!$C30,Actuals!$A:$A,Avg!J$1) -> 0 | K30: =SUMIFS(Actuals!$E:$E,Actuals!$F:$F,Avg!$C30,Actuals!$A:$A,Avg!K$1) -> 0 | L30: =SUMIFS(Actuals!$E:$E,Actuals!$F:$F,Avg!$C30,Actuals!$A:$A,Avg!L$1) -> 38.95 | M30: =SUMIFS(Actuals!$E:$E,Actuals!$F:$F,Avg!$C30,Actuals!$A:$A,Avg!M$1) -> 0 | N30: =SUMIFS(Actuals!$E:$E,Actuals!$F:$F,Avg!$C30,Actuals!$A:$A,Avg!N$1) -> 339.8 | O30: =SUMIFS(Actuals!$E:$E,Actuals!$F:$F,Avg!$C30,Actuals!$A:$A,Avg!O$1) -> 27.2 | ... S30: =SUMIFS(Actuals!$E:$E,Actuals!$F:$F,Avg!$C30,Actuals!$A:$A,Avg!S$1) -> 2.37 | T30: =SUM(H30:S30) -> 527.85
C31: Total Other | D31: =SUM(D24:D30) -> 4369.4633 | E31: =SUM(E24:E30) -> 3331.0317 | F31: =SUM(F24:F30) -> 3402.41 | H31: =SUM(H24:H30) -> 3785.58 | I31: =SUM(I24:I30) -> 4514.31 | J31: =SUM(J24:J30) -> 4808.5 | K31: =SUM(K24:K30) -> 1421.83 | L31: =SUM(L24:L30) -> 1617.68 | M31: =SUM(M24:M30) -> 3838.29 | N31: =SUM(N24:N30) -> 3180.69 | O31: =SUM(O24:O30) -> 3408.48 | ... S31: =SUM(S24:S30) -> 3330.99 | T31: =SUM(H31:S31) -> 40828.92
C33: Total | D33: =SUM(D31,D22,D16) -> 13766.857 | E33: =SUM(E31,E22,E16) -> 13063.03 | F33: =SUM(F31,F22,F16) -> 13244.226 | H33: =SUM(H31,H22,H16) -> 13565.96 | I33: =SUM(I31,I22,I16) -> 12865.9 | J33: =SUM(J31,J22,J16) -> 14868.71 | K33: =SUM(K31,K22,K16) -> 11990.37 | L33: =SUM(L31,L22,L16) -> 11944.56 | M33: =SUM(M31,M22,M16) -> 13142.68 | N33: =SUM(N31,N22,N16) -> 14186.06 | O33: =SUM(O31,O22,O16) -> 12771.32 | ... S33: =SUM(S31,S22,S16) -> 12892.08 | T33: =SUM(H33:S33) -> 158930.71
V34: *does not include yearly items in 3 & 6mo avg
C35: Healthcare | D35: =AVERAGE(H35:J35) -> 82.096667 | E35: =AVERAGE(H35:M35) -> 167.13333 | F35: =AVERAGE(H35:S35) -> 210.62 | H35: =SUMIFS(Actuals!$E:$E,Actuals!$F:$F,Avg!$C35,Actuals!$A:$A,Avg!H$1) -> 0 | I35: =SUMIFS(Actuals!$E:$E,Actuals!$F:$F,Avg!$C35,Actuals!$A:$A,Avg!I$1) -> 246.29 | J35: =SUMIFS(Actuals!$E:$E,Actuals!$F:$F,Avg!$C35,Actuals!$A:$A,Avg!J$1) -> 0 | K35: =SUMIFS(Actuals!$E:$E,Actuals!$F:$F,Avg!$C35,Actuals!$A:$A,Avg!K$1) -> 0 | L35: =SUMIFS(Actuals!$E:$E,Actuals!$F:$F,Avg!$C35,Actuals!$A:$A,Avg!L$1) -> 756.51 | M35: =SUMIFS(Actuals!$E:$E,Actuals!$F:$F,Avg!$C35,Actuals!$A:$A,Avg!M$1) -> 0 | N35: =SUMIFS(Actuals!$E:$E,Actuals!$F:$F,Avg!$C35,Actuals!$A:$A,Avg!N$1) -> 225.58 | O35: =SUMIFS(Actuals!$E:$E,Actuals!$F:$F,Avg!$C35,Actuals!$A:$A,Avg!O$1) -> 33.5 | ... S35: =SUMIFS(Actuals!$E:$E,Actuals!$F:$F,Avg!$C35,Actuals!$A:$A,Avg!S$1) -> -95.42 | T35: =SUM(H35:S35) -> 2527.44
C36: House | D36: =AVERAGE(H36:J36) -> 0 | E36: =AVERAGE(H36:M36) -> 0 | F36: =AVERAGE(H36:S36) -> 964.35333 | H36: =SUMIFS(Actuals!$E:$E,Actuals!$F:$F,Avg!$C36,Actuals!$A:$A,Avg!H$1) -> 0 | I36: =SUMIFS(Actuals!$E:$E,Actuals!$F:$F,Avg!$C36,Actuals!$A:$A,Avg!I$1) -> 0 | J36: =SUMIFS(Actuals!$E:$E,Actuals!$F:$F,Avg!$C36,Actuals!$A:$A,Avg!J$1) -> 0 | K36: =SUMIFS(Actuals!$E:$E,Actuals!$F:$F,Avg!$C36,Actuals!$A:$A,Avg!K$1) -> 0 | L36: =SUMIFS(Actuals!$E:$E,Actuals!$F:$F,Avg!$C36,Actuals!$A:$A,Avg!L$1) -> 0 | M36: =SUMIFS(Actuals!$E:$E,Actuals!$F:$F,Avg!$C36,Actuals!$A:$A,Avg!M$1) -> 0 | N36: =SUMIFS(Actuals!$E:$E,Actuals!$F:$F,Avg!$C36,Actuals!$A:$A,Avg!N$1) -> 0 | O36: =SUMIFS(Actuals!$E:$E,Actuals!$F:$F,Avg!$C36,Actuals!$A:$A,Avg!O$1) -> 367 | ... S36: =SUMIFS(Actuals!$E:$E,Actuals!$F:$F,Avg!$C36,Actuals!$A:$A,Avg!S$1) -> 853.97 | T36: =SUM(H36:S36) -> 11572.24 | V36: To get to 6mo fund (months):
C37: Travel | D37: =AVERAGE(H37:J37) -> 1311.41 | E37: =AVERAGE(H37:M37) -> 2017.1217 | F37: =AVERAGE(H37:S37) -> 1508.1642 | H37: =SUMIFS(Actuals!$E:$E,Actuals!$F:$F,Avg!$C37,Actuals!$A:$A,Avg!H$1) -> 593.64 | I37: =SUMIFS(Actuals!$E:$E,Actuals!$F:$F,Avg!$C37,Actuals!$A:$A,Avg!I$1) -> 1848.31 | J37: =SUMIFS(Actuals!$E:$E,Actuals!$F:$F,Avg!$C37,Actuals!$A:$A,Avg!J$1) -> 1492.28 | K37: =SUMIFS(Actuals!$E:$E,Actuals!$F:$F,Avg!$C37,Actuals!$A:$A,Avg!K$1) -> 4167.04 | L37: =SUMIFS(Actuals!$E:$E,Actuals!$F:$F,Avg!$C37,Actuals!$A:$A,Avg!L$1) -> 2189.94 | M37: =SUMIFS(Actuals!$E:$E,Actuals!$F:$F,Avg!$C37,Actuals!$A:$A,Avg!M$1) -> 1811.52 | N37: =SUMIFS(Actuals!$E:$E,Actuals!$F:$F,Avg!$C37,Actuals!$A:$A,Avg!N$1) -> 2312.84 | O37: =SUMIFS(Actuals!$E:$E,Actuals!$F:$F,Avg!$C37,Actuals!$A:$A,Avg!O$1) -> 21.68 | ... S37: =SUMIFS(Actuals!$E:$E,Actuals!$F:$F,Avg!$C37,Actuals!$A:$A,Avg!S$1) -> 2066.25 | T37: =SUM(H37:S37) -> 18097.97 | V37: =(X10-W17) -> 92695.68
C38: Total Yearly | D38: =SUM(D35:D37) -> 1393.5067 | E38: =SUM(E35:E37) -> 2184.255 | F38: =SUM(F35:F37) -> 2683.1375 | G38: =SUM(G35:G37) -> 0 | H38: =SUM(H35:H37) -> 593.64 | I38: =SUM(I35:I37) -> 2094.6 | J38: =SUM(J35:J37) -> 1492.28 | K38: =SUM(K35:K37) -> 4167.04 | ... S38: =SUM(S35:S37) -> 2824.8 | T38: =SUM(H38:S38) -> 32197.65
C40: Total All Spend | D40: =SUM(D38,D33) -> 15160.363 | E40: =SUM(E38,E33) -> 15247.285 | F40: =SUM(F38,F33) -> 15927.363 | H40: =SUM(H38,H33) -> 14159.6 | I40: =SUM(I38,I33) -> 14960.5 | J40: =SUM(J38,J33) -> 16360.99 | K40: =SUM(K38,K33) -> 16157.41 | L40: =SUM(L38,L33) -> 14891.01 | M40: =SUM(M38,M33) -> 14954.2 | N40: =SUM(N38,N33) -> 16724.48 | O40: =SUM(O38,O33) -> 13193.5 | ... S40: =SUM(S38,S33) -> 15716.88 | T40: =SUM(H40:S40) -> 191128.36
V45: Graph
V46: Actual | W46: =W17 -> -14317.5
V47: 3 mo | W47: =W10 -> 41300.57
V48: 6 mo | W48: =X10 -> 78378.18

Sheet Proj 9.22
D1: =VALUE('1 MO'!$C$3&"01") -> 202501 | E1: =VALUE('1 MO'!$C$3&"02") -> 202502 | F1: =VALUE('1 MO'!$C$3&"03") -> 202503 | G1: =VALUE('1 MO'!$C$3&"04") -> 202504 | H1: =VALUE('1 MO'!$C$3&"05") -> 202505 | I1: =VALUE('1 MO'!$C$3&"06") -> 202506 | J1: =VALUE('1 MO'!$C$3&"07") -> 202507 | K1: =VALUE('1 MO'!$C$3&"08") -> 202508 | L1: =VALUE('1 MO'!$C$3&"09") -> 202509 | M1: =VALUE('1 MO'!$C$3&"10") -> 202510 | N1: =VALUE('1 MO'!$C$3&"11") -> 202511 | O1: =VALUE('1 MO'!$C$3&"12") -> 202512
C6: Revised Budget 9/2022
D7: =TEXT(DATE(LEFT(D1,4),RIGHT(D1,2),1),"MMM YYYY") -> Jan 2025 | E7: =TEXT(DATE(LEFT(E1,4),RIGHT(E1,2),1),"MMM YYYY") -> Feb 2025 | F7: =TEXT(DATE(LEFT(F1,4),RIGHT(F1,2),1),"MMM YYYY") -> Mar 2025 | G7: =TEXT(DATE(LEFT(G1,4),RIGHT(G1,2),1),"MMM YYYY") -> Apr 2025 | H7: =TEXT(DATE(LEFT(H1,4),RIGHT(H1,2),1),"MMM YYYY") -> May 2025 | I7: =TEXT(DATE(LEFT(I1,4),RIGHT(I1,2),1),"MMM YYYY") -> Jun 2025 | J7: =TEXT(DATE(LEFT(J1,4),RIGHT(J1,2),1),"MMM YYYY") -> Jul 2025 | K7: =TEXT(DATE(LEFT(K1,4),RIGHT(K1,2),1),"MMM YYYY") -> Aug 2025 | ... O7: =TEXT(DATE(LEFT(O1,4),RIGHT(O1,2),1),"MMM YYYY") -> Dec 2025 | P7: Total
C9: Rent | D9: 1816 | E9: 1816 | F9: 1816 | G9: 1816 | H9: 1816 | I9: 1816 | J9: 1817 | K9: 1816 | L9: 1816 | M9: 1816 | N9: 1816 | O9: 1816 | P9: =SUM(D9:O9) -> 21793
C10: House Maintenance | D10: =SUMIFS(Actuals!$E:$E,Actuals!$F:$F,'Proj 9.22'!$C10,Actuals!$A:$A,'Proj 9.22'!D$1) -> 158.51 | E10: =SUMIFS(Actuals!$E:$E,Actuals!$F:$F,'Proj 9.22'!$C10,Actuals!$A:$A,'Proj 9.22'!E$1) -> 72.41 | F10: =SUMIFS(Actuals!$E:$E,Actuals!$F:$F,'Proj 9.22'!$C10,Actuals!$A:$A,'Proj 9.22'!F$1) -> 432.06 | G10: =SUMIFS(Actuals!$E:$E,Actuals!$F:$F,'Proj 9.22'!$C10,Actuals!$A:$A,'Proj 9.22'!G$1) -> 532.52 | H10: =SUMIFS(Actuals!$E:$E,Actuals!$F:$F,'Proj 9.22'!$C10,Actuals!$A:$A,'Proj 9.22'!H$1) -> 296.68 | I10: =SUMIFS(Actuals!$E:$E,Actuals!$F:$F,'Proj 9.22'!$C10,Actuals!$A:$A,'Proj 9.22'!I$1) -> 719.26 | J10: =SUMIFS(Actuals!$E:$E,Actuals!$F:$F,'Proj 9.22'!$C10,Actuals!$A:$A,'Proj 9.22'!J$1) -> 373.78 | K10: =SUMIFS(Actuals!$E:$E,Actuals!$F:$F,'Proj 9.22'!$C10,Actuals!$A:$A,'Proj 9.22'!K$1) -> 127.46 | L10: =SUMIFS(Actuals!$E:$E,Actuals!$F:$F,'Proj 9.22'!$C10,Actuals!$A:$A,'Proj 9.22'!L$1) -> 812.79 | M10: 433.32333 | N10: 433.32333 | O10: 433.32333 | P10: =SUM(D10:O10) -> 4825.44
C11: Utilities | D11: =SUMIFS(Actuals!$E:$E,Actuals!$F:$F,'Proj 9.22'!$C11,Actuals!$A:$A,'Proj 9.22'!D$1) -> 512.23 | E11: =SUMIFS(Actuals!$E:$E,Actuals!$F:$F,'Proj 9.22'!$C11,Actuals!$A:$A,'Proj 9.22'!E$1) -> 1454.37 | F11: =SUMIFS(Actuals!$E:$E,Actuals!$F:$F,'Proj 9.22'!$C11,Actuals!$A:$A,'Proj 9.22'!F$1) -> 404.52 | G11: =SUMIFS(Actuals!$E:$E,Actuals!$F:$F,'Proj 9.22'!$C11,Actuals!$A:$A,'Proj 9.22'!G$1) -> 507.12 | H11: =SUMIFS(Actuals!$E:$E,Actuals!$F:$F,'Proj 9.22'!$C11,Actuals!$A:$A,'Proj 9.22'!H$1) -> 726.93 | I11: =SUMIFS(Actuals!$E:$E,Actuals!$F:$F,'Proj 9.22'!$C11,Actuals!$A:$A,'Proj 9.22'!I$1) -> 2595.93 | J11: =SUMIFS(Actuals!$E:$E,Actuals!$F:$F,'Proj 9.22'!$C11,Actuals!$A:$A,'Proj 9.22'!J$1) -> 2949.64 | K11: =SUMIFS(Actuals!$E:$E,Actuals!$F:$F,'Proj 9.22'!$C11,Actuals!$A:$A,'Proj 9.22'!K$1) -> 744.52 | L11: =SUMIFS(Actuals!$E:$E,Actuals!$F:$F,'Proj 9.22'!$C11,Actuals!$A:$A,'Proj 9.22'!L$1) -> 1113.16 | M11: 615.33 | N11: 615.33 | O11: 615.33 | P11: =SUM(D11:O11) -> 12854.41
C12: Car Loan | D12: =SUMIFS(Actuals!$E:$E,Actuals!$F:$F,'Proj 9.22'!$C12,Actuals!$A:$A,'Proj 9.22'!D$1) -> 0 | E12: =SUMIFS(Actuals!$E:$E,Actuals!$F:$F,'Proj 9.22'!$C12,Actuals!$A:$A,'Proj 9.22'!E$1) -> 0 | F12: =SUMIFS(Actuals!$E:$E,Actuals!$F:$F,'Proj 9.22'!$C12,Actuals!$A:$A,'Proj 9.22'!F$1) -> 0 | G12: =SUMIFS(Actuals!$E:$E,Actuals!$F:$F,'Proj 9.22'!$C12,Actuals!$A:$A,'Proj 9.22'!G$1) -> 0 | H12: =SUMIFS(Actuals!$E:$E,Actuals!$F:$F,'Proj 9.22'!$C12,Actuals!$A:$A,'Proj 9.22'!H$1) -> 0 | I12: =SUMIFS(Actuals!$E:$E,Actuals!$F:$F,'Proj 9.22'!$C12,Actuals!$A:$A,'Proj 9.22'!I$1) -> 0 | J12: =SUMIFS(Actuals!$E:$E,Actuals!$F:$F,'Proj 9.22'!$C12,Actuals!$A:$A,'Proj 9.22'!J$1) -> 0 | K12: =SUMIFS(Actuals!$E:$E,Actuals!$F:$F,'Proj 9.22'!$C12,Actuals!$A:$A,'Proj 9.22'!K$1) -> 0 | L12: =SUMIFS(Actuals!$E:$E,Actuals!$F:$F,'Proj 9.22'!$C12,Actuals!$A:$A,'Proj 9.22'!L$1) -> 0 | M12: 585.31667 | N12: 585.31667 | O12: 585.31667 | P12: =SUM(D12:O12) -> 1755.95
C13: Cleaning | D13: =SUMIFS(Actuals!$E:$E,Actuals!$F:$F,'Proj 9.22'!$C13,Actuals!$A:$A,'Proj 9.22'!D$1) -> 0 | E13: =SUMIFS(Actuals!$E:$E,Actuals!$F:$F,'Proj 9.22'!$C13,Actuals!$A:$A,'Proj 9.22'!E$1) -> 0 | F13: =SUMIFS(Actuals!$E:$E,Actuals!$F:$F,'Proj 9.22'!$C13,Actuals!$A:$A,'Proj 9.22'!F$1) -> 0 | G13: =SUMIFS(Actuals!$E:$E,Actuals!$F:$F,'Proj 9.22'!$C13,Actuals!$A:$A,'Proj 9.22'!G$1) -> 0 | H13: =SUMIFS(Actuals!$E:$E,Actuals!$F:$F,'Proj 9.22'!$C13,Actuals!$A:$A,'Proj 9.22'!H$1) -> 0 | I13: =SUMIFS(Actuals!$E:$E,Actuals!$F:$F,'Proj 9.22'!$C13,Actuals!$A:$A,'Proj 9.22'!I$1) -> 0 | J13: =SUMIFS(Actuals!$E:$E,Actuals!$F:$F,'Proj 9.22'!$C13,Actuals!$A:$A,'Proj 9.22'!J$1) -> 0 | K13: =SUMIFS(Actuals!$E:$E,Actuals!$F:$F,'Proj 9.22'!$C13,Actuals!$A:$A,'Proj 9.22'!K$1) -> 0 | L13: =SUMIFS(Actuals!$E:$E,Actuals!$F:$F,'Proj 9.22'!$C13,Actuals!$A:$A,'Proj 9.22'!L$1) -> 0 | M13: 250 | N13: 250 | O13: 250 | P13: =SUM(D13:O13) -> 750
C14: Insurance | D14: =SUMIFS(Actuals!$E:$E,Actuals!$F:$F,'Proj 9.22'!$C14,Actuals!$A:$A,'Proj 9.22'!D$1) -> 163.66 | E14: =SUMIFS(Actuals!$E:$E,Actuals!$F:$F,'Proj 9.22'!$C14,Actuals!$A:$A,'Proj 9.22'!E$1) -> 163.66 | F14: =SUMIFS(Actuals!$E:$E,Actuals!$F:$F,'Proj 9.22'!$C14,Actuals!$A:$A,'Proj 9.22'!F$1) -> 158.66 | G14: =SUMIFS(Actuals!$E:$E,Actuals!$F:$F,'Proj 9.22'!$C14,Actuals!$A:$A,'Proj 9.22'!G$1) -> 165.12 | H14: =SUMIFS(Actuals!$E:$E,Actuals!$F:$F,'Proj 9.22'!$C14,Actuals!$A:$A,'Proj 9.22'!H$1) -> 165.08 | I14: =SUMIFS(Actuals!$E:$E,Actuals!$F:$F,'Proj 9.22'!$C14,Actuals!$A:$A,'Proj 9.22'!I$1) -> 54.33 | J14: =SUMIFS(Actuals!$E:$E,Actuals!$F:$F,'Proj 9.22'!$C14,Actuals!$A:$A,'Proj 9.22'!J$1) -> 55.97 | K14: =SUMIFS(Actuals!$E:$E,Actuals!$F:$F,'Proj 9.22'!$C14,Actuals!$A:$A,'Proj 9.22'!K$1) -> 54.33 | L14: =SUMIFS(Actuals!$E:$E,Actuals!$F:$F,'Proj 9.22'!$C14,Actuals!$A:$A,'Proj 9.22'!L$1) -> 54.33 | M14: 102.48667 | N14: 102.48667 | O14: 102.48667 | P14: =SUM(D14:O14) -> 1342.6
C15: Day Care | D15: =SUMIFS(Actuals!$E:$E,Actuals!$F:$F,'Proj 9.22'!$C15,Actuals!$A:$A,'Proj 9.22'!D$1) -> 4201.12 | E15: =SUMIFS(Actuals!$E:$E,Actuals!$F:$F,'Proj 9.22'!$C15,Actuals!$A:$A,'Proj 9.22'!E$1) -> 2625.59 | F15: =SUMIFS(Actuals!$E:$E,Actuals!$F:$F,'Proj 9.22'!$C15,Actuals!$A:$A,'Proj 9.22'!F$1) -> 2505.21 | G15: =SUMIFS(Actuals!$E:$E,Actuals!$F:$F,'Proj 9.22'!$C15,Actuals!$A:$A,'Proj 9.22'!G$1) -> 2173.36 | H15: =SUMIFS(Actuals!$E:$E,Actuals!$F:$F,'Proj 9.22'!$C15,Actuals!$A:$A,'Proj 9.22'!H$1) -> 797.3 | I15: =SUMIFS(Actuals!$E:$E,Actuals!$F:$F,'Proj 9.22'!$C15,Actuals!$A:$A,'Proj 9.22'!I$1) -> 1371.1 | J15: =SUMIFS(Actuals!$E:$E,Actuals!$F:$F,'Proj 9.22'!$C15,Actuals!$A:$A,'Proj 9.22'!J$1) -> 2393 | K15: =SUMIFS(Actuals!$E:$E,Actuals!$F:$F,'Proj 9.22'!$C15,Actuals!$A:$A,'Proj 9.22'!K$1) -> 2344.51 | L15: =SUMIFS(Actuals!$E:$E,Actuals!$F:$F,'Proj 9.22'!$C15,Actuals!$A:$A,'Proj 9.22'!L$1) -> 1720.3 | M15: 1111.5 | N15: 1111.5 | O15: 1111.5 | P15: =SUM(D15:O15) -> 23465.99
C16: Total Rent & Utilitites | D16: =SUM(D9:D15) -> 6851.52 | E16: =SUM(E9:E15) -> 6132.03 | F16: =SUM(F9:F15) -> 5316.45 | G16: =SUM(G9:G15) -> 5194.12 | H16: =SUM(H9:H15) -> 3801.99 | I16: =SUM(I9:I15) -> 6556.62 | J16: =SUM(J9:J15) -> 7589.39 | K16: =SUM(K9:K15) -> 5086.82 | ... O16: =SUM(O9:O15) -> 4913.9567 | P16: =SUM(D16:O16) -> 66787.39
C18: Transportation | D18: =SUMIFS(Actuals!$E:$E,Actuals!$F:$F,'Proj 9.22'!$C18,Actuals!$A:$A,'Proj 9.22'!D$1) -> 36.35 | E18: =SUMIFS(Actuals!$E:$E,Actuals!$F:$F,'Proj 9.22'!$C18,Actuals!$A:$A,'Proj 9.22'!E$1) -> 1290.29 | F18: =SUMIFS(Actuals!$E:$E,Actuals!$F:$F,'Proj 9.22'!$C18,Actuals!$A:$A,'Proj 9.22'!F$1) -> 133.96 | G18: =SUMIFS(Actuals!$E:$E,Actuals!$F:$F,'Proj 9.22'!$C18,Actuals!$A:$A,'Proj 9.22'!G$1) -> 60.28 | H18: =SUMIFS(Actuals!$E:$E,Actuals!$F:$F,'Proj 9.22'!$C18,Actuals!$A:$A,'Proj 9.22'!H$1) -> 1459.98 | I18: =SUMIFS(Actuals!$E:$E,Actuals!$F:$F,'Proj 9.22'!$C18,Actuals!$A:$A,'Proj 9.22'!I$1) -> 86.91 | J18: =SUMIFS(Actuals!$E:$E,Actuals!$F:$F,'Proj 9.22'!$C18,Actuals!$A:$A,'Proj 9.22'!J$1) -> 993.97 | K18: =SUMIFS(Actuals!$E:$E,Actuals!$F:$F,'Proj 9.22'!$C18,Actuals!$A:$A,'Proj 9.22'!K$1) -> 47.12 | L18: =SUMIFS(Actuals!$E:$E,Actuals!$F:$F,'Proj 9.22'!$C18,Actuals!$A:$A,'Proj 9.22'!L$1) -> 61 | M18: 836.31667 | N18: 836.31667 | O18: 836.31667 | P18: =SUM(D18:O18) -> 6678.81
C19: Restaurants | D19: =SUMIFS(Actuals!$E:$E,Actuals!$F:$F,'Proj 9.22'!$C19,Actuals!$A:$A,'Proj 9.22'!D$1) -> 1256.52 | E19: =SUMIFS(Actuals!$E:$E,Actuals!$F:$F,'Proj 9.22'!$C19,Actuals!$A:$A,'Proj 9.22'!E$1) -> 1258.33 | F19: =SUMIFS(Actuals!$E:$E,Actuals!$F:$F,'Proj 9.22'!$C19,Actuals!$A:$A,'Proj 9.22'!F$1) -> 2190.37 | G19: =SUMIFS(Actuals!$E:$E,Actuals!$F:$F,'Proj 9.22'!$C19,Actuals!$A:$A,'Proj 9.22'!G$1) -> 1732.92 | H19: =SUMIFS(Actuals!$E:$E,Actuals!$F:$F,'Proj 9.22'!$C19,Actuals!$A:$A,'Proj 9.22'!H$1) -> 1195.79 | I19: =SUMIFS(Actuals!$E:$E,Actuals!$F:$F,'Proj 9.22'!$C19,Actuals!$A:$A,'Proj 9.22'!I$1) -> 2520.29 | J19: =SUMIFS(Actuals!$E:$E,Actuals!$F:$F,'Proj 9.22'!$C19,Actuals!$A:$A,'Proj 9.22'!J$1) -> 2280.76 | K19: =SUMIFS(Actuals!$E:$E,Actuals!$F:$F,'Proj 9.22'!$C19,Actuals!$A:$A,'Proj 9.22'!K$1) -> 1833.45 | L19: =SUMIFS(Actuals!$E:$E,Actuals!$F:$F,'Proj 9.22'!$C19,Actuals!$A:$A,'Proj 9.22'!L$1) -> 2412.67 | M19: 1275.2467 | N19: 1275.2467 | O19: 1275.2467 | P19: =SUM(D19:O19) -> 20506.84
C20: Groceries | D20: =SUMIFS(Actuals!$E:$E,Actuals!$F:$F,'Proj 9.22'!$C20,Actuals!$A:$A,'Proj 9.22'!D$1) -> 1032.54 | E20: =SUMIFS(Actuals!$E:$E,Actuals!$F:$F,'Proj 9.22'!$C20,Actuals!$A:$A,'Proj 9.22'!E$1) -> 813.71 | F20: =SUMIFS(Actuals!$E:$E,Actuals!$F:$F,'Proj 9.22'!$C20,Actuals!$A:$A,'Proj 9.22'!F$1) -> 579.15 | G20: =SUMIFS(Actuals!$E:$E,Actuals!$F:$F,'Proj 9.22'!$C20,Actuals!$A:$A,'Proj 9.22'!G$1) -> 1295 | H20: =SUMIFS(Actuals!$E:$E,Actuals!$F:$F,'Proj 9.22'!$C20,Actuals!$A:$A,'Proj 9.22'!H$1) -> 1047.99 | I20: =SUMIFS(Actuals!$E:$E,Actuals!$F:$F,'Proj 9.22'!$C20,Actuals!$A:$A,'Proj 9.22'!I$1) -> 1176.28 | J20: =SUMIFS(Actuals!$E:$E,Actuals!$F:$F,'Proj 9.22'!$C20,Actuals!$A:$A,'Proj 9.22'!J$1) -> 341.28 | K20: =SUMIFS(Actuals!$E:$E,Actuals!$F:$F,'Proj 9.22'!$C20,Actuals!$A:$A,'Proj 9.22'!K$1) -> 1051.64 | L20: =SUMIFS(Actuals!$E:$E,Actuals!$F:$F,'Proj 9.22'!$C20,Actuals!$A:$A,'Proj 9.22'!L$1) -> 865.15 | M20: 888.73333 | N20: 888.73333 | O20: 888.73333 | P20: =SUM(D20:O20) -> 10868.94
C21: Target | D21: =SUMIFS(Actuals!$E:$E,Actuals!$F:$F,'Proj 9.22'!$C21,Actuals!$A:$A,'Proj 9.22'!D$1) -> 0 | E21: =SUMIFS(Actuals!$E:$E,Actuals!$F:$F,'Proj 9.22'!$C21,Actuals!$A:$A,'Proj 9.22'!E$1) -> 1466.2 | F21: =SUMIFS(Actuals!$E:$E,Actuals!$F:$F,'Proj 9.22'!$C21,Actuals!$A:$A,'Proj 9.22'!F$1) -> 1203.61 | G21: =SUMIFS(Actuals!$E:$E,Actuals!$F:$F,'Proj 9.22'!$C21,Actuals!$A:$A,'Proj 9.22'!G$1) -> 859 | H21: =SUMIFS(Actuals!$E:$E,Actuals!$F:$F,'Proj 9.22'!$C21,Actuals!$A:$A,'Proj 9.22'!H$1) -> 141.71 | I21: =SUMIFS(Actuals!$E:$E,Actuals!$F:$F,'Proj 9.22'!$C21,Actuals!$A:$A,'Proj 9.22'!I$1) -> 863.6 | J21: =SUMIFS(Actuals!$E:$E,Actuals!$F:$F,'Proj 9.22'!$C21,Actuals!$A:$A,'Proj 9.22'!J$1) -> 138.78 | K21: =SUMIFS(Actuals!$E:$E,Actuals!$F:$F,'Proj 9.22'!$C21,Actuals!$A:$A,'Proj 9.22'!K$1) -> 519.11 | L21: =SUMIFS(Actuals!$E:$E,Actuals!$F:$F,'Proj 9.22'!$C21,Actuals!$A:$A,'Proj 9.22'!L$1) -> 664.94 | M21: 459.88333 | N21: 459.88333 | O21: 459.88333 | P21: =SUM(D21:O21) -> 7236.6
C22: Total Food & Car | D22: =SUM(D18:D21) -> 2325.41 | E22: =SUM(E18:E21) -> 4828.53 | F22: =SUM(F18:F21) -> 4107.09 | G22: =SUM(G18:G21) -> 3947.2 | H22: =SUM(H18:H21) -> 3845.47 | I22: =SUM(I18:I21) -> 4647.08 | J22: =SUM(J18:J21) -> 3754.79 | K22: =SUM(K18:K21) -> 3451.32 | ... O22: =SUM(O18:O21) -> 3460.18 | P22: =SUM(D22:O22) -> 45291.19
C24: Gym | D24: =SUMIFS(Actuals!$E:$E,Actuals!$F:$F,'Proj 9.22'!$C24,Actuals!$A:$A,'Proj 9.22'!D$1) -> 0 | E24: =SUMIFS(Actuals!$E:$E,Actuals!$F:$F,'Proj 9.22'!$C24,Actuals!$A:$A,'Proj 9.22'!E$1) -> 0 | F24: =SUMIFS(Actuals!$E:$E,Actuals!$F:$F,'Proj 9.22'!$C24,Actuals!$A:$A,'Proj 9.22'!F$1) -> 0 | G24: =SUMIFS(Actuals!$E:$E,Actuals!$F:$F,'Proj 9.22'!$C24,Actuals!$A:$A,'Proj 9.22'!G$1) -> 0 | H24: =SUMIFS(Actuals!$E:$E,Actuals!$F:$F,'Proj 9.22'!$C24,Actuals!$A:$A,'Proj 9.22'!H$1) -> 0 | I24: =SUMIFS(Actuals!$E:$E,Actuals!$F:$F,'Proj 9.22'!$C24,Actuals!$A:$A,'Proj 9.22'!I$1) -> 25 | J24: =SUMIFS(Actuals!$E:$E,Actuals!$F:$F,'Proj 9.22'!$C24,Actuals!$A:$A,'Proj 9.22'!J$1) -> 0 | K24: =SUMIFS(Actuals!$E:$E,Actuals!$F:$F,'Proj 9.22'!$C24,Actuals!$A:$A,'Proj 9.22'!K$1) -> 0 | L24: =SUMIFS(Actuals!$E:$E,Actuals!$F:$F,'Proj 9.22'!$C24,Actuals!$A:$A,'Proj 9.22'!L$1) -> 0 | M24: 34.94 | N24: 34.94 | O24: 34.94 | P24: =SUM(D24:O24) -> 129.82
C25: Shopping | D25: =SUMIFS(Actuals!$E:$E,Actuals!$F:$F,'Proj 9.22'!$C25,Actuals!$A:$A,'Proj 9.22'!D$1) -> 1297.56 | E25: =SUMIFS(Actuals!$E:$E,Actuals!$F:$F,'Proj 9.22'!$C25,Actuals!$A:$A,'Proj 9.22'!E$1) -> 2152.23 | F25: =SUMIFS(Actuals!$E:$E,Actuals!$F:$F,'Proj 9.22'!$C25,Actuals!$A:$A,'Proj 9.22'!F$1) -> 2367.63 | G25: =SUMIFS(Actuals!$E:$E,Actuals!$F:$F,'Proj 9.22'!$C25,Actuals!$A:$A,'Proj 9.22'!G$1) -> 944.14 | H25: =SUMIFS(Actuals!$E:$E,Actuals!$F:$F,'Proj 9.22'!$C25,Actuals!$A:$A,'Proj 9.22'!H$1) -> 2601 | I25: =SUMIFS(Actuals!$E:$E,Actuals!$F:$F,'Proj 9.22'!$C25,Actuals!$A:$A,'Proj 9.22'!I$1) -> 1527.95 | J25: =SUMIFS(Actuals!$E:$E,Actuals!$F:$F,'Proj 9.22'!$C25,Actuals!$A:$A,'Proj 9.22'!J$1) -> -26.29 | K25: =SUMIFS(Actuals!$E:$E,Actuals!$F:$F,'Proj 9.22'!$C25,Actuals!$A:$A,'Proj 9.22'!K$1) -> 2243.56 | L25: =SUMIFS(Actuals!$E:$E,Actuals!$F:$F,'Proj 9.22'!$C25,Actuals!$A:$A,'Proj 9.22'!L$1) -> 2632.31 | M25: 2000 | N25: 2000 | O25: 2000 | P25: =SUM(D25:O25) -> 21740.09
C26: Amazon | D26: =SUMIFS(Actuals!$E:$E,Actuals!$F:$F,'Proj 9.22'!$C26,Actuals!$A:$A,'Proj 9.22'!D$1) -> 1330.21 | E26: =SUMIFS(Actuals!$E:$E,Actuals!$F:$F,'Proj 9.22'!$C26,Actuals!$A:$A,'Proj 9.22'!E$1) -> 628.87 | F26: =SUMIFS(Actuals!$E:$E,Actuals!$F:$F,'Proj 9.22'!$C26,Actuals!$A:$A,'Proj 9.22'!F$1) -> 468.29 | G26: =SUMIFS(Actuals!$E:$E,Actuals!$F:$F,'Proj 9.22'!$C26,Actuals!$A:$A,'Proj 9.22'!G$1) -> 883.33 | H26: =SUMIFS(Actuals!$E:$E,Actuals!$F:$F,'Proj 9.22'!$C26,Actuals!$A:$A,'Proj 9.22'!H$1) -> 361.54 | I26: =SUMIFS(Actuals!$E:$E,Actuals!$F:$F,'Proj 9.22'!$C26,Actuals!$A:$A,'Proj 9.22'!I$1) -> 4.01 | J26: =SUMIFS(Actuals!$E:$E,Actuals!$F:$F,'Proj 9.22'!$C26,Actuals!$A:$A,'Proj 9.22'!J$1) -> -0.15 | K26: =SUMIFS(Actuals!$E:$E,Actuals!$F:$F,'Proj 9.22'!$C26,Actuals!$A:$A,'Proj 9.22'!K$1) -> 26.49 | L26: =SUMIFS(Actuals!$E:$E,Actuals!$F:$F,'Proj 9.22'!$C26,Actuals!$A:$A,'Proj 9.22'!L$1) -> 356.58 | M26: 83.333333 | N26: 83.333333 | O26: 83.333333 | P26: =SUM(D26:O26) -> 4309.17
C27: Entertainment | D27: =SUMIFS(Actuals!$E:$E,Actuals!$F:$F,'Proj 9.22'!$C27,Actuals!$A:$A,'Proj 9.22'!D$1) -> 452.17 | E27: =SUMIFS(Actuals!$E:$E,Actuals!$F:$F,'Proj 9.22'!$C27,Actuals!$A:$A,'Proj 9.22'!E$1) -> 213.46 | F27: =SUMIFS(Actuals!$E:$E,Actuals!$F:$F,'Proj 9.22'!$C27,Actuals!$A:$A,'Proj 9.22'!F$1) -> 547.24 | G27: =SUMIFS(Actuals!$E:$E,Actuals!$F:$F,'Proj 9.22'!$C27,Actuals!$A:$A,'Proj 9.22'!G$1) -> 214.29 | H27: =SUMIFS(Actuals!$E:$E,Actuals!$F:$F,'Proj 9.22'!$C27,Actuals!$A:$A,'Proj 9.22'!H$1) -> 151.35 | I27: =SUMIFS(Actuals!$E:$E,Actuals!$F:$F,'Proj 9.22'!$C27,Actuals!$A:$A,'Proj 9.22'!I$1) -> 365.79 | J27: =SUMIFS(Actuals!$E:$E,Actuals!$F:$F,'Proj 9.22'!$C27,Actuals!$A:$A,'Proj 9.22'!J$1) -> 447.19 | K27: =SUMIFS(Actuals!$E:$E,Actuals!$F:$F,'Proj 9.22'!$C27,Actuals!$A:$A,'Proj 9.22'!K$1) -> 522.8 | L27: =SUMIFS(Actuals!$E:$E,Actuals!$F:$F,'Proj 9.22'!$C27,Actuals!$A:$A,'Proj 9.22'!L$1) -> 49.09 | M27: 57.34 | N27: 57.34 | O27: 57.34 | P27: =SUM(D27:O27) -> 3135.4
C28: Dry Cleaning | D28: =SUMIFS(Actuals!$E:$E,Actuals!$F:$F,'Proj 9.22'!$C28,Actuals!$A:$A,'Proj 9.22'!D$1) -> 0 | E28: =SUMIFS(Actuals!$E:$E,Actuals!$F:$F,'Proj 9.22'!$C28,Actuals!$A:$A,'Proj 9.22'!E$1) -> 0 | F28: =SUMIFS(Actuals!$E:$E,Actuals!$F:$F,'Proj 9.22'!$C28,Actuals!$A:$A,'Proj 9.22'!F$1) -> 0 | G28: =SUMIFS(Actuals!$E:$E,Actuals!$F:$F,'Proj 9.22'!$C28,Actuals!$A:$A,'Proj 9.22'!G$1) -> 36.6 | H28: =SUMIFS(Actuals!$E:$E,Actuals!$F:$F,'Proj 9.22'!$C28,Actuals!$A:$A,'Proj 9.22'!H$1) -> 0 | I28: =SUMIFS(Actuals!$E:$E,Actuals!$F:$F,'Proj 9.22'!$C28,Actuals!$A:$A,'Proj 9.22'!I$1) -> 35.93 | J28: =SUMIFS(Actuals!$E:$E,Actuals!$F:$F,'Proj 9.22'!$C28,Actuals!$A:$A,'Proj 9.22'!J$1) -> 113.36 | K28: =SUMIFS(Actuals!$E:$E,Actuals!$F:$F,'Proj 9.22'!$C28,Actuals!$A:$A,'Proj 9.22'!K$1) -> 59.35 | L28: =SUMIFS(Actuals!$E:$E,Actuals!$F:$F,'Proj 9.22'!$C28,Actuals!$A:$A,'Proj 9.22'!L$1) -> 0 | M28: 22.196667 | N28: 22.196667 | O28: 22.196667 | P28: =SUM(D28:O28) -> 311.83
C29: Gifts | D29: =SUMIFS(Actuals!$E:$E,Actuals!$F:$F,'Proj 9.22'!$C29,Actuals!$A:$A,'Proj 9.22'!D$1) -> 0 | E29: =SUMIFS(Actuals!$E:$E,Actuals!$F:$F,'Proj 9.22'!$C29,Actuals!$A:$A,'Proj 9.22'!E$1) -> 0 | F29: =SUMIFS(Actuals!$E:$E,Actuals!$F:$F,'Proj 9.22'!$C29,Actuals!$A:$A,'Proj 9.22'!F$1) -> 0 | G29: =SUMIFS(Actuals!$E:$E,Actuals!$F:$F,'Proj 9.22'!$C29,Actuals!$A:$A,'Proj 9.22'!G$1) -> 0 | H29: =SUMIFS(Actuals!$E:$E,Actuals!$F:$F,'Proj 9.22'!$C29,Actuals!$A:$A,'Proj 9.22'!H$1) -> 0 | I29: =SUMIFS(Actuals!$E:$E,Actuals!$F:$F,'Proj 9.22'!$C29,Actuals!$A:$A,'Proj 9.22'!I$1) -> 0 | J29: =SUMIFS(Actuals!$E:$E,Actuals!$F:$F,'Proj 9.22'!$C29,Actuals!$A:$A,'Proj 9.22'!J$1) -> 0 | K29: =SUMIFS(Actuals!$E:$E,Actuals!$F:$F,'Proj 9.22'!$C29,Actuals!$A:$A,'Proj 9.22'!K$1) -> 0 | L29: =SUMIFS(Actuals!$E:$E,Actuals!$F:$F,'Proj 9.22'!$C29,Actuals!$A:$A,'Proj 9.22'!L$1) -> 0 | M29: 103.6 | N29: 250 | O29: 250 | P29: =SUM(D29:O29) -> 603.6
C30: Misc | D30: =SUMIFS(Actuals!$E:$E,Actuals!$F:$F,'Proj 9.22'!$C30,Actuals!$A:$A,'Proj 9.22'!D$1) -> 110 | E30: =SUMIFS(Actuals!$E:$E,Actuals!$F:$F,'Proj 9.22'!$C30,Actuals!$A:$A,'Proj 9.22'!E$1) -> 0 | F30: =SUMIFS(Actuals!$E:$E,Actuals!$F:$F,'Proj 9.22'!$C30,Actuals!$A:$A,'Proj 9.22'!F$1) -> 0 | G30: =SUMIFS(Actuals!$E:$E,Actuals!$F:$F,'Proj 9.22'!$C30,Actuals!$A:$A,'Proj 9.22'!G$1) -> 124 | H30: =SUMIFS(Actuals!$E:$E,Actuals!$F:$F,'Proj 9.22'!$C30,Actuals!$A:$A,'Proj 9.22'!H$1) -> 0 | I30: =SUMIFS(Actuals!$E:$E,Actuals!$F:$F,'Proj 9.22'!$C30,Actuals!$A:$A,'Proj 9.22'!I$1) -> 5 | J30: =SUMIFS(Actuals!$E:$E,Actuals!$F:$F,'Proj 9.22'!$C30,Actuals!$A:$A,'Proj 9.22'!J$1) -> 0 | K30: =SUMIFS(Actuals!$E:$E,Actuals!$F:$F,'Proj 9.22'!$C30,Actuals!$A:$A,'Proj 9.22'!K$1) -> 0 | L30: =SUMIFS(Actuals!$E:$E,Actuals!$F:$F,'Proj 9.22'!$C30,Actuals!$A:$A,'Proj 9.22'!L$1) -> 0 | M30: 117.06333 | N30: 117.06333 | O30: 117.06333 | P30: =SUM(D30:O30) -> 590.19
C31: Total Other | D31: =SUM(D24:D30) -> 3189.94 | E31: =SUM(E24:E30) -> 2994.56 | F31: =SUM(F24:F30) -> 3383.16 | G31: =SUM(G24:G30) -> 2202.36 | H31: =SUM(H24:H30) -> 3113.89 | I31: =SUM(I24:I30) -> 1963.68 | J31: =SUM(J24:J30) -> 534.11 | K31: =SUM(K24:K30) -> 2852.2 | ... O31: =SUM(O24:O30) -> 2564.8733 | P31: =SUM(D31:O31) -> 30820.1
P32: =SUM(D32:O32) -> 0
C33: Total | D33: =SUM(D31,D22,D16) -> 12366.87 | E33: =SUM(E31,E22,E16) -> 13955.12 | F33: =SUM(F31,F22,F16) -> 12806.7 | G33: =SUM(G31,G22,G16) -> 11343.68 | H33: =SUM(H31,H22,H16) -> 10761.35 | I33: =SUM(I31,I22,I16) -> 13167.38 | J33: =SUM(J31,J22,J16) -> 11878.29 | K33: =SUM(K31,K22,K16) -> 11390.34 | ... O33: =SUM(O31,O22,O16) -> 10939.01 | P33: =SUM(D33:O33) -> 142898.68
C35: Healthcare | D35: =SUMIFS(Actuals!$E:$E,Actuals!$F:$F,'Proj 9.22'!$C35,Actuals!$A:$A,'Proj 9.22'!D$1) -> 555.18 | E35: =SUMIFS(Actuals!$E:$E,Actuals!$F:$F,'Proj 9.22'!$C35,Actuals!$A:$A,'Proj 9.22'!E$1) -> 246.17 | F35: =SUMIFS(Actuals!$E:$E,Actuals!$F:$F,'Proj 9.22'!$C35,Actuals!$A:$A,'Proj 9.22'!F$1) -> 227.94 | G35: =SUMIFS(Actuals!$E:$E,Actuals!$F:$F,'Proj 9.22'!$C35,Actuals!$A:$A,'Proj 9.22'!G$1) -> 0 | H35: =SUMIFS(Actuals!$E:$E,Actuals!$F:$F,'Proj 9.22'!$C35,Actuals!$A:$A,'Proj 9.22'!H$1) -> 253.53 | I35: =SUMIFS(Actuals!$E:$E,Actuals!$F:$F,'Proj 9.22'!$C35,Actuals!$A:$A,'Proj 9.22'!I$1) -> -14.1 | J35: =SUMIFS(Actuals!$E:$E,Actuals!$F:$F,'Proj 9.22'!$C35,Actuals!$A:$A,'Proj 9.22'!J$1) -> 124.06 | K35: =SUMIFS(Actuals!$E:$E,Actuals!$F:$F,'Proj 9.22'!$C35,Actuals!$A:$A,'Proj 9.22'!K$1) -> 0 | ... O35: =SUMIFS(Actuals!$E:$E,Actuals!$F:$F,'Proj 9.22'!$C35,Actuals!$A:$A,'Proj 9.22'!O$1) -> 1285.7 | P35: =SUM(D35:O35) -> 3948.01
C36: House | D36: =SUMIFS(Actuals!$E:$E,Actuals!$F:$F,'Proj 9.22'!$C36,Actuals!$A:$A,'Proj 9.22'!D$1) -> 30245.75 | E36: =SUMIFS(Actuals!$E:$E,Actuals!$F:$F,'Proj 9.22'!$C36,Actuals!$A:$A,'Proj 9.22'!E$1) -> 8816.97 | F36: =SUMIFS(Actuals!$E:$E,Actuals!$F:$F,'Proj 9.22'!$C36,Actuals!$A:$A,'Proj 9.22'!F$1) -> 24509 | G36: =SUMIFS(Actuals!$E:$E,Actuals!$F:$F,'Proj 9.22'!$C36,Actuals!$A:$A,'Proj 9.22'!G$1) -> 18027 | H36: =SUMIFS(Actuals!$E:$E,Actuals!$F:$F,'Proj 9.22'!$C36,Actuals!$A:$A,'Proj 9.22'!H$1) -> 5053.11 | I36: =SUMIFS(Actuals!$E:$E,Actuals!$F:$F,'Proj 9.22'!$C36,Actuals!$A:$A,'Proj 9.22'!I$1) -> 43385.5 | J36: =SUMIFS(Actuals!$E:$E,Actuals!$F:$F,'Proj 9.22'!$C36,Actuals!$A:$A,'Proj 9.22'!J$1) -> 48339 | K36: =SUMIFS(Actuals!$E:$E,Actuals!$F:$F,'Proj 9.22'!$C36,Actuals!$A:$A,'Proj 9.22'!K$1) -> 52 | ... O36: =SUMIFS(Actuals!$E:$E,Actuals!$F:$F,'Proj 9.22'!$C36,Actuals!$A:$A,'Proj 9.22'!O$1) -> 0 | P36: =SUM(D36:O36) -> 265799.33
C37: Travel | D37: =SUMIFS(Actuals!$E:$E,Actuals!$F:$F,'Proj 9.22'!$C37,Actuals!$A:$A,'Proj 9.22'!D$1) -> 2336.15 | E37: =SUMIFS(Actuals!$E:$E,Actuals!$F:$F,'Proj 9.22'!$C37,Actuals!$A:$A,'Proj 9.22'!E$1) -> 213.11 | F37: =SUMIFS(Actuals!$E:$E,Actuals!$F:$F,'Proj 9.22'!$C37,Actuals!$A:$A,'Proj 9.22'!F$1) -> 908.1 | G37: =SUMIFS(Actuals!$E:$E,Actuals!$F:$F,'Proj 9.22'!$C37,Actuals!$A:$A,'Proj 9.22'!G$1) -> 513.21 | H37: =SUMIFS(Actuals!$E:$E,Actuals!$F:$F,'Proj 9.22'!$C37,Actuals!$A:$A,'Proj 9.22'!H$1) -> 997.66 | I37: =SUMIFS(Actuals!$E:$E,Actuals!$F:$F,'Proj 9.22'!$C37,Actuals!$A:$A,'Proj 9.22'!I$1) -> 468.69 | J37: =SUMIFS(Actuals!$E:$E,Actuals!$F:$F,'Proj 9.22'!$C37,Actuals!$A:$A,'Proj 9.22'!J$1) -> 744.33 | K37: =SUMIFS(Actuals!$E:$E,Actuals!$F:$F,'Proj 9.22'!$C37,Actuals!$A:$A,'Proj 9.22'!K$1) -> 2249.71 | ... M37: =SUMIFS(Actuals!$E:$E,Actuals!$F:$F,'Proj 9.22'!$C37,Actuals!$A:$A,'Proj 9.22'!M$1) -> 4330.69 | N37: 1000 | O37: =SUMIFS(Actuals!$E:$E,Actuals!$F:$F,'Proj 9.22'!$C37,Actuals!$A:$A,'Proj 9.22'!O$1) -> 1788.34 | P37: =SUM(D37:O37) -> 16412.39
C38: Total Yearly | D38: =SUM(D35:D37) -> 33137.08 | E38: =SUM(E35:E37) -> 9276.25 | F38: =SUM(F35:F37) -> 25645.04 | G38: =SUM(G35:G37) -> 18540.21 | H38: =SUM(H35:H37) -> 6304.3 | I38: =SUM(I35:I37) -> 43840.09 | J38: =SUM(J35:J37) -> 49207.39 | K38: =SUM(K35:K37) -> 2301.71 | ... P38: =SUM(P35:P37) -> 286159.73
C44: Additional | D44: =SUM(D40:D43) -> 0 | E44: =SUM(E40:E43) -> 0 | F44: =SUM(F40:F43) -> 0 | G44: =SUM(G40:G43) -> 0 | H44: =SUM(H40:H43) -> 0 | I44: =SUM(I40:I43) -> 0 | J44: =SUM(J40:J43) -> 0 | K44: =SUM(K40:K43) -> 0 | ... O44: =SUM(O40:O43) -> 0 | P44: =SUM(D44:O44) -> 0
C46: Total All Spend | D46: =SUM(D38,D33) -> 45503.95 | E46: =SUM(E38,E33) -> 23231.37 | F46: =SUM(F38,F33) -> 38451.74 | G46: =SUM(G38,G33) -> 29883.89 | H46: =SUM(H38,H33) -> 17065.65 | I46: =SUM(I38,I33) -> 57007.47 | J46: =SUM(J38,J33) -> 61085.68 | K46: =SUM(K38,K33) -> 13692.05 | ... O46: =SUM(O38,O33) -> 14013.05 | P46: =SUM(P38,P33,P44) -> 429058.41
C47: Rent is monthy pmt - principle payment (principle paymet included in savings)

Sheet Proj 8.22
D1: =VALUE('1 MO'!$C$3&"01") -> 202501 | E1: =VALUE('1 MO'!$C$3&"02") -> 202502 | F1: =VALUE('1 MO'!$C$3&"03") -> 202503 | G1: =VALUE('1 MO'!$C$3&"04") -> 202504 | H1: =VALUE('1 MO'!$C$3&"05") -> 202505 | I1: =VALUE('1 MO'!$C$3&"06") -> 202506 | J1: =VALUE('1 MO'!$C$3&"07") -> 202507 | K1: =VALUE('1 MO'!$C$3&"08") -> 202508 | L1: =VALUE('1 MO'!$C$3&"09") -> 202509 | M1: =VALUE('1 MO'!$C$3&"10") -> 202510 | N1: =VALUE('1 MO'!$C$3&"11") -> 202511 | O1: =VALUE('1 MO'!$C$3&"12") -> 202512
C6: Revised Budget 8/2022
D7: =TEXT(DATE(LEFT(D1,4),RIGHT(D1,2),1),"MMM YYYY") -> Jan 2025 | E7: =TEXT(DATE(LEFT(E1,4),RIGHT(E1,2),1),"MMM YYYY") -> Feb 2025 | F7: =TEXT(DATE(LEFT(F1,4),RIGHT(F1,2),1),"MMM YYYY") -> Mar 2025 | G7: =TEXT(DATE(LEFT(G1,4),RIGHT(G1,2),1),"MMM YYYY") -> Apr 2025 | H7: =TEXT(DATE(LEFT(H1,4),RIGHT(H1,2),1),"MMM YYYY") -> May 2025 | I7: =TEXT(DATE(LEFT(I1,4),RIGHT(I1,2),1),"MMM YYYY") -> Jun 2025 | J7: =TEXT(DATE(LEFT(J1,4),RIGHT(J1,2),1),"MMM YYYY") -> Jul 2025 | K7: =TEXT(DATE(LEFT(K1,4),RIGHT(K1,2),1),"MMM YYYY") -> Aug 2025 | ... O7: =TEXT(DATE(LEFT(O1,4),RIGHT(O1,2),1),"MMM YYYY") -> Dec 2025 | P7: Total
C9: Rent | D9: 1816 | E9: 1816 | F9: 1816 | G9: 1816 | H9: 1816 | I9: 1816 | J9: 1817 | K9: 1816 | L9: 1816 | M9: 1816 | N9: 1816 | O9: 1816 | P9: =SUM(D9:O9) -> 21793
C10: House Maintenance | D10: =SUMIFS(Actuals!$E:$E,Actuals!$F:$F,'Proj 8.22'!$C10,Actuals!$A:$A,'Proj 8.22'!D$1) -> 158.51 | E10: =SUMIFS(Actuals!$E:$E,Actuals!$F:$F,'Proj 8.22'!$C10,Actuals!$A:$A,'Proj 8.22'!E$1) -> 72.41 | F10: =SUMIFS(Actuals!$E:$E,Actuals!$F:$F,'Proj 8.22'!$C10,Actuals!$A:$A,'Proj 8.22'!F$1) -> 432.06 | G10: =SUMIFS(Actuals!$E:$E,Actuals!$F:$F,'Proj 8.22'!$C10,Actuals!$A:$A,'Proj 8.22'!G$1) -> 532.52 | H10: =SUMIFS(Actuals!$E:$E,Actuals!$F:$F,'Proj 8.22'!$C10,Actuals!$A:$A,'Proj 8.22'!H$1) -> 296.68 | I10: =SUMIFS(Actuals!$E:$E,Actuals!$F:$F,'Proj 8.22'!$C10,Actuals!$A:$A,'Proj 8.22'!I$1) -> 719.26 | J10: =SUMIFS(Actuals!$E:$E,Actuals!$F:$F,'Proj 8.22'!$C10,Actuals!$A:$A,'Proj 8.22'!J$1) -> 373.78 | K10: =SUMIFS(Actuals!$E:$E,Actuals!$F:$F,'Proj 8.22'!$C10,Actuals!$A:$A,'Proj 8.22'!K$1) -> 127.46 | L10: 433.32333 | M10: 433.32333 | N10: 433.32333 | O10: 433.32333 | P10: =SUM(D10:O10) -> 4445.9733
C11: Utilities | D11: =SUMIFS(Actuals!$E:$E,Actuals!$F:$F,'Proj 8.22'!$C11,Actuals!$A:$A,'Proj 8.22'!D$1) -> 512.23 | E11: =SUMIFS(Actuals!$E:$E,Actuals!$F:$F,'Proj 8.22'!$C11,Actuals!$A:$A,'Proj 8.22'!E$1) -> 1454.37 | F11: =SUMIFS(Actuals!$E:$E,Actuals!$F:$F,'Proj 8.22'!$C11,Actuals!$A:$A,'Proj 8.22'!F$1) -> 404.52 | G11: =SUMIFS(Actuals!$E:$E,Actuals!$F:$F,'Proj 8.22'!$C11,Actuals!$A:$A,'Proj 8.22'!G$1) -> 507.12 | H11: =SUMIFS(Actuals!$E:$E,Actuals!$F:$F,'Proj 8.22'!$C11,Actuals!$A:$A,'Proj 8.22'!H$1) -> 726.93 | I11: =SUMIFS(Actuals!$E:$E,Actuals!$F:$F,'Proj 8.22'!$C11,Actuals!$A:$A,'Proj 8.22'!I$1) -> 2595.93 | J11: =SUMIFS(Actuals!$E:$E,Actuals!$F:$F,'Proj 8.22'!$C11,Actuals!$A:$A,'Proj 8.22'!J$1) -> 2949.64 | K11: =SUMIFS(Actuals!$E:$E,Actuals!$F:$F,'Proj 8.22'!$C11,Actuals!$A:$A,'Proj 8.22'!K$1) -> 744.52 | L11: 615.33 | M11: 615.33 | N11: 615.33 | O11: 615.33 | P11: =SUM(D11:O11) -> 12356.58
C12: Car Loan | D12: =SUMIFS(Actuals!$E:$E,Actuals!$F:$F,'Proj 8.22'!$C12,Actuals!$A:$A,'Proj 8.22'!D$1) -> 0 | E12: =SUMIFS(Actuals!$E:$E,Actuals!$F:$F,'Proj 8.22'!$C12,Actuals!$A:$A,'Proj 8.22'!E$1) -> 0 | F12: =SUMIFS(Actuals!$E:$E,Actuals!$F:$F,'Proj 8.22'!$C12,Actuals!$A:$A,'Proj 8.22'!F$1) -> 0 | G12: =SUMIFS(Actuals!$E:$E,Actuals!$F:$F,'Proj 8.22'!$C12,Actuals!$A:$A,'Proj 8.22'!G$1) -> 0 | H12: =SUMIFS(Actuals!$E:$E,Actuals!$F:$F,'Proj 8.22'!$C12,Actuals!$A:$A,'Proj 8.22'!H$1) -> 0 | I12: =SUMIFS(Actuals!$E:$E,Actuals!$F:$F,'Proj 8.22'!$C12,Actuals!$A:$A,'Proj 8.22'!I$1) -> 0 | J12: =SUMIFS(Actuals!$E:$E,Actuals!$F:$F,'Proj 8.22'!$C12,Actuals!$A:$A,'Proj 8.22'!J$1) -> 0 | K12: =SUMIFS(Actuals!$E:$E,Actuals!$F:$F,'Proj 8.22'!$C12,Actuals!$A:$A,'Proj 8.22'!K$1) -> 0 | L12: 585.31667 | M12: 585.31667 | N12: 585.31667 | O12: 585.31667 | P12: =SUM(D12:O12) -> 2341.2667
C13: Cleaning | D13: =SUMIFS(Actuals!$E:$E,Actuals!$F:$F,'Proj 8.22'!$C13,Actuals!$A:$A,'Proj 8.22'!D$1) -> 0 | E13: =SUMIFS(Actuals!$E:$E,Actuals!$F:$F,'Proj 8.22'!$C13,Actuals!$A:$A,'Proj 8.22'!E$1) -> 0 | F13: =SUMIFS(Actuals!$E:$E,Actuals!$F:$F,'Proj 8.22'!$C13,Actuals!$A:$A,'Proj 8.22'!F$1) -> 0 | G13: =SUMIFS(Actuals!$E:$E,Actuals!$F:$F,'Proj 8.22'!$C13,Actuals!$A:$A,'Proj 8.22'!G$1) -> 0 | H13: =SUMIFS(Actuals!$E:$E,Actuals!$F:$F,'Proj 8.22'!$C13,Actuals!$A:$A,'Proj 8.22'!H$1) -> 0 | I13: =SUMIFS(Actuals!$E:$E,Actuals!$F:$F,'Proj 8.22'!$C13,Actuals!$A:$A,'Proj 8.22'!I$1) -> 0 | J13: =SUMIFS(Actuals!$E:$E,Actuals!$F:$F,'Proj 8.22'!$C13,Actuals!$A:$A,'Proj 8.22'!J$1) -> 0 | K13: =SUMIFS(Actuals!$E:$E,Actuals!$F:$F,'Proj 8.22'!$C13,Actuals!$A:$A,'Proj 8.22'!K$1) -> 0 | L13: 250 | M13: 250 | N13: 250 | O13: 250 | P13: =SUM(D13:O13) -> 1000
C14: Insurance | D14: =SUMIFS(Actuals!$E:$E,Actuals!$F:$F,'Proj 8.22'!$C14,Actuals!$A:$A,'Proj 8.22'!D$1) -> 163.66 | E14: =SUMIFS(Actuals!$E:$E,Actuals!$F:$F,'Proj 8.22'!$C14,Actuals!$A:$A,'Proj 8.22'!E$1) -> 163.66 | F14: =SUMIFS(Actuals!$E:$E,Actuals!$F:$F,'Proj 8.22'!$C14,Actuals!$A:$A,'Proj 8.22'!F$1) -> 158.66 | G14: =SUMIFS(Actuals!$E:$E,Actuals!$F:$F,'Proj 8.22'!$C14,Actuals!$A:$A,'Proj 8.22'!G$1) -> 165.12 | H14: =SUMIFS(Actuals!$E:$E,Actuals!$F:$F,'Proj 8.22'!$C14,Actuals!$A:$A,'Proj 8.22'!H$1) -> 165.08 | I14: =SUMIFS(Actuals!$E:$E,Actuals!$F:$F,'Proj 8.22'!$C14,Actuals!$A:$A,'Proj 8.22'!I$1) -> 54.33 | J14: =SUMIFS(Actuals!$E:$E,Actuals!$F:$F,'Proj 8.22'!$C14,Actuals!$A:$A,'Proj 8.22'!J$1) -> 55.97 | K14: =SUMIFS(Actuals!$E:$E,Actuals!$F:$F,'Proj 8.22'!$C14,Actuals!$A:$A,'Proj 8.22'!K$1) -> 54.33 | L14: 102.48667 | M14: 102.48667 | N14: 102.48667 | O14: 102.48667 | P14: =SUM(D14:O14) -> 1390.7567
C15: Day Care | D15: =SUMIFS(Actuals!$E:$E,Actuals!$F:$F,'Proj 8.22'!$C15,Actuals!$A:$A,'Proj 8.22'!D$1) -> 4201.12 | E15: =SUMIFS(Actuals!$E:$E,Actuals!$F:$F,'Proj 8.22'!$C15,Actuals!$A:$A,'Proj 8.22'!E$1) -> 2625.59 | F15: =SUMIFS(Actuals!$E:$E,Actuals!$F:$F,'Proj 8.22'!$C15,Actuals!$A:$A,'Proj 8.22'!F$1) -> 2505.21 | G15: =SUMIFS(Actuals!$E:$E,Actuals!$F:$F,'Proj 8.22'!$C15,Actuals!$A:$A,'Proj 8.22'!G$1) -> 2173.36 | H15: =SUMIFS(Actuals!$E:$E,Actuals!$F:$F,'Proj 8.22'!$C15,Actuals!$A:$A,'Proj 8.22'!H$1) -> 797.3 | I15: =SUMIFS(Actuals!$E:$E,Actuals!$F:$F,'Proj 8.22'!$C15,Actuals!$A:$A,'Proj 8.22'!I$1) -> 1371.1 | J15: =SUMIFS(Actuals!$E:$E,Actuals!$F:$F,'Proj 8.22'!$C15,Actuals!$A:$A,'Proj 8.22'!J$1) -> 2393 | K15: =SUMIFS(Actuals!$E:$E,Actuals!$F:$F,'Proj 8.22'!$C15,Actuals!$A:$A,'Proj 8.22'!K$1) -> 2344.51 | L15: 1111.5 | M15: 1111.5 | N15: 1111.5 | O15: 1111.5 | P15: =SUM(D15:O15) -> 22857.19
C16: Total Rent & Utilitites | D16: =SUM(D9:D15) -> 6851.52 | E16: =SUM(E9:E15) -> 6132.03 | F16: =SUM(F9:F15) -> 5316.45 | G16: =SUM(G9:G15) -> 5194.12 | H16: =SUM(H9:H15) -> 3801.99 | I16: =SUM(I9:I15) -> 6556.62 | J16: =SUM(J9:J15) -> 7589.39 | K16: =SUM(K9:K15) -> 5086.82 | ... O16: =SUM(O9:O15) -> 4913.9567 | P16: =SUM(D16:O16) -> 66184.767
C18: Transportation | D18: =SUMIFS(Actuals!$E:$E,Actuals!$F:$F,'Proj 8.22'!$C18,Actuals!$A:$A,'Proj 8.22'!D$1) -> 36.35 | E18: =SUMIFS(Actuals!$E:$E,Actuals!$F:$F,'Proj 8.22'!$C18,Actuals!$A:$A,'Proj 8.22'!E$1) -> 1290.29 | F18: =SUMIFS(Actuals!$E:$E,Actuals!$F:$F,'Proj 8.22'!$C18,Actuals!$A:$A,'Proj 8.22'!F$1) -> 133.96 | G18: =SUMIFS(Actuals!$E:$E,Actuals!$F:$F,'Proj 8.22'!$C18,Actuals!$A:$A,'Proj 8.22'!G$1) -> 60.28 | H18: =SUMIFS(Actuals!$E:$E,Actuals!$F:$F,'Proj 8.22'!$C18,Actuals!$A:$A,'Proj 8.22'!H$1) -> 1459.98 | I18: =SUMIFS(Actuals!$E:$E,Actuals!$F:$F,'Proj 8.22'!$C18,Actuals!$A:$A,'Proj 8.22'!I$1) -> 86.91 | J18: =SUMIFS(Actuals!$E:$E,Actuals!$F:$F,'Proj 8.22'!$C18,Actuals!$A:$A,'Proj 8.22'!J$1) -> 993.97 | K18: =SUMIFS(Actuals!$E:$E,Actuals!$F:$F,'Proj 8.22'!$C18,Actuals!$A:$A,'Proj 8.22'!K$1) -> 47.12 | L18: 836.31667 | M18: 836.31667 | N18: 836.31667 | O18: 836.31667 | P18: =SUM(D18:O18) -> 7454.1267
C19: Restaurants | D19: =SUMIFS(Actuals!$E:$E,Actuals!$F:$F,'Proj 8.22'!$C19,Actuals!$A:$A,'Proj 8.22'!D$1) -> 1256.52 | E19: =SUMIFS(Actuals!$E:$E,Actuals!$F:$F,'Proj 8.22'!$C19,Actuals!$A:$A,'Proj 8.22'!E$1) -> 1258.33 | F19: =SUMIFS(Actuals!$E:$E,Actuals!$F:$F,'Proj 8.22'!$C19,Actuals!$A:$A,'Proj 8.22'!F$1) -> 2190.37 | G19: =SUMIFS(Actuals!$E:$E,Actuals!$F:$F,'Proj 8.22'!$C19,Actuals!$A:$A,'Proj 8.22'!G$1) -> 1732.92 | H19: =SUMIFS(Actuals!$E:$E,Actuals!$F:$F,'Proj 8.22'!$C19,Actuals!$A:$A,'Proj 8.22'!H$1) -> 1195.79 | I19: =SUMIFS(Actuals!$E:$E,Actuals!$F:$F,'Proj 8.22'!$C19,Actuals!$A:$A,'Proj 8.22'!I$1) -> 2520.29 | J19: =SUMIFS(Actuals!$E:$E,Actuals!$F:$F,'Proj 8.22'!$C19,Actuals!$A:$A,'Proj 8.22'!J$1) -> 2280.76 | K19: =SUMIFS(Actuals!$E:$E,Actuals!$F:$F,'Proj 8.22'!$C19,Actuals!$A:$A,'Proj 8.22'!K$1) -> 1833.45 | L19: 1275.2467 | M19: 1275.2467 | N19: 1275.2467 | O19: 1275.2467 | P19: =SUM(D19:O19) -> 19369.417
C20: Groceries | D20: =SUMIFS(Actuals!$E:$E,Actuals!$F:$F,'Proj 8.22'!$C20,Actuals!$A:$A,'Proj 8.22'!D$1) -> 1032.54 | E20: =SUMIFS(Actuals!$E:$E,Actuals!$F:$F,'Proj 8.22'!$C20,Actuals!$A:$A,'Proj 8.22'!E$1) -> 813.71 | F20: =SUMIFS(Actuals!$E:$E,Actuals!$F:$F,'Proj 8.22'!$C20,Actuals!$A:$A,'Proj 8.22'!F$1) -> 579.15 | G20: =SUMIFS(Actuals!$E:$E,Actuals!$F:$F,'Proj 8.22'!$C20,Actuals!$A:$A,'Proj 8.22'!G$1) -> 1295 | H20: =SUMIFS(Actuals!$E:$E,Actuals!$F:$F,'Proj 8.22'!$C20,Actuals!$A:$A,'Proj 8.22'!H$1) -> 1047.99 | I20: =SUMIFS(Actuals!$E:$E,Actuals!$F:$F,'Proj 8.22'!$C20,Actuals!$A:$A,'Proj 8.22'!I$1) -> 1176.28 | J20: =SUMIFS(Actuals!$E:$E,Actuals!$F:$F,'Proj 8.22'!$C20,Actuals!$A:$A,'Proj 8.22'!J$1) -> 341.28 | K20: =SUMIFS(Actuals!$E:$E,Actuals!$F:$F,'Proj 8.22'!$C20,Actuals!$A:$A,'Proj 8.22'!K$1) -> 1051.64 | L20: 888.73333 | M20: 888.73333 | N20: 888.73333 | O20: 888.73333 | P20: =SUM(D20:O20) -> 10892.523
C21: Target | D21: =SUMIFS(Actuals!$E:$E,Actuals!$F:$F,'Proj 8.22'!$C21,Actuals!$A:$A,'Proj 8.22'!D$1) -> 0 | E21: =SUMIFS(Actuals!$E:$E,Actuals!$F:$F,'Proj 8.22'!$C21,Actuals!$A:$A,'Proj 8.22'!E$1) -> 1466.2 | F21: =SUMIFS(Actuals!$E:$E,Actuals!$F:$F,'Proj 8.22'!$C21,Actuals!$A:$A,'Proj 8.22'!F$1) -> 1203.61 | G21: =SUMIFS(Actuals!$E:$E,Actuals!$F:$F,'Proj 8.22'!$C21,Actuals!$A:$A,'Proj 8.22'!G$1) -> 859 | H21: =SUMIFS(Actuals!$E:$E,Actuals!$F:$F,'Proj 8.22'!$C21,Actuals!$A:$A,'Proj 8.22'!H$1) -> 141.71 | I21: =SUMIFS(Actuals!$E:$E,Actuals!$F:$F,'Proj 8.22'!$C21,Actuals!$A:$A,'Proj 8.22'!I$1) -> 863.6 | J21: =SUMIFS(Actuals!$E:$E,Actuals!$F:$F,'Proj 8.22'!$C21,Actuals!$A:$A,'Proj 8.22'!J$1) -> 138.78 | K21: =SUMIFS(Actuals!$E:$E,Actuals!$F:$F,'Proj 8.22'!$C21,Actuals!$A:$A,'Proj 8.22'!K$1) -> 519.11 | L21: 459.88333 | M21: 459.88333 | N21: 459.88333 | O21: 459.88333 | P21: =SUM(D21:O21) -> 7031.5433
C22: Total Food & Car | D22: =SUM(D18:D21) -> 2325.41 | E22: =SUM(E18:E21) -> 4828.53 | F22: =SUM(F18:F21) -> 4107.09 | G22: =SUM(G18:G21) -> 3947.2 | H22: =SUM(H18:H21) -> 3845.47 | I22: =SUM(I18:I21) -> 4647.08 | J22: =SUM(J18:J21) -> 3754.79 | K22: =SUM(K18:K21) -> 3451.32 | ... O22: =SUM(O18:O21) -> 3460.18 | P22: =SUM(D22:O22) -> 44747.61
